Workbook

Sheet 📋 Master Plan
A1: 🎯 TECHNICAL INTERVIEW PREP — MASTER PLAN
A3: Target: 500+ Problems | Daily: 2 hrs DSA + 1 hr System Design | Total Duration: ~16 Weeks
A5: STUDY PHASES OVERVIEW
A6: Phase | B6: Weeks | C6: DSA Focus Area | D6: Key Concepts | E6: Problem Count Target | F6: System Design Topic | G6: Daily DSA Time | H6: Daily SD Time | I6: Difficulty Mix | J6: Cumulative Problems
A7: Phase 1 | B7: Wks 1–2 | C7: Foundations | D7: Arrays, Strings, Hashing, Two Pointers, Sliding Window | E7: 60 | F7: Scalability & Basics | G7: 90 min | H7: 30 min | I7: 80% Easy / 20% Med | J7: 60
A8: Phase 2 | B8: Wks 3–4 | C8: Linear Structures | D8: Linked Lists, Stacks, Queues, Monotonic Structures | E8: 60 | F8: Storage & Caching | G8: 90 min | H8: 30 min | I8: 60% Easy / 40% Med | J8: 120
A9: Phase 3 | B9: Wks 5–6 | C9: Trees & Graphs | D9: Binary Trees, BST, Tries, Graph BFS/DFS, Union-Find | E9: 80 | F9: Distributed Systems Intro | G9: 80 min | H9: 40 min | I9: 40% Easy / 50% Med / 10% Hard | J9: 200
A10: Phase 4 | B10: Wks 7–8 | C10: Recursion & DP | D10: Backtracking, 1D DP, 2D DP, Greedy | E10: 80 | F10: Design Deep Dives I | G10: 70 min | H10: 50 min | I10: 20% Easy / 60% Med / 20% Hard | J10: 280
A11: Phase 5 | B11: Wks 9–10 | C11: Advanced Algorithms | D11: Heaps, Advanced Graphs, Intervals, Bit Manipulation | E11: 70 | F11: Design Deep Dives II | G11: 60 min | H11: 60 min | I11: 10% Easy / 60% Med / 30% Hard | J11: 350
A12: Phase 6 | B12: Wks 11–12 | C12: Hard & Patterns | D12: Hard DP, Advanced Trees, Segment Trees, Math | E12: 60 | F12: Design Deep Dives III | G12: 60 min | H12: 60 min | I12: 5% Easy / 50% Med / 45% Hard | J12: 410
A13: Phase 7 | B13: Wks 13–14 | C13: Mock & Review | D13: Mixed company-tagged sets, timed contests | E13: 50 | F13: Full Mock System Designs | G13: 50 min | H13: 70 min | I13: Company-Specific Mix | J13: 460
A14: Phase 8 | B14: Wks 15–16 | C14: Final Sprint | D14: Weak-area revisit, top 75 NeetCode revisit | E14: 40 | F14: Behavioral + SD Combos | G14: 45 min | H14: 75 min | I14: Interview-Intensity | J14: 500+
A17: 📅 DAILY SCHEDULE TEMPLATE
A18: Time Block | B18: Duration | C18: Activity | D18: What To Do | E18: Notes
A19: Block 1 | B19: 30 min | C19: Warm-up / Review | D19: Re-read yesterday's notes, review 2–3 solved problems | E19: Active recall, not passive reading
A20: Block 2 | B20: 60 min | C20: New DSA Topic | D20: Study concept deeply → understand intuition → code from scratch | E20: No copy-paste; understand WHY
A21: Block 3 | B21: 30 min | C21: Practice Problems | D21: Solve 2–4 problems on current topic (timed: 20–25 min each) | E21: Track in Problem Log sheet
A22: Block 4 | B22: 60 min | C22: System Design | D22: Study 1 SD concept + design a system end-to-end with trade-offs | E22: Use the SD sheet as checklist
A23: Buffer | B23: — | C23: Spaced Repetition | D23: Flag hard problems for re-attempt in 3/7/14 days | E23: Use the Retry Tracker sheet

Sheet 🧠 DSA Topics & Problems
A1: 🧠 DSA TOPICS, KEY CONCEPTS & MUST-SOLVE PROBLEMS
A3: # | B3: Topic / Category | C3: Core Concepts to Understand | D3: Key Patterns & Techniques | E3: Must-Solve Problems (LeetCode) | F3: Difficulty | G3: # Problems | H3: Phase | I3: Concept Tags | J3: Notes / Tips | K3: Mastery Level
A4: 1 | B4: Arrays & Hashing | C4: Contiguous memory, index ops, hash maps for O(1) lookup, frequency counting | D4: Two-pass counting, complement lookup, prefix sum | E4: Two Sum (1), Contains Duplicate (217), Valid Anagram (242), Group Anagrams (49), Top K Frequent (347), Product of Array Except Self (238), Encode/Decode Strings (659), Longest Consecutive Sequence (128) | F4: E/M | G4: 8 | H4: Phase 1 | I4: Arrays, Hashing, Frequency | J4: Master HashMap before moving on | K4: ⬜ Not Started
A5: 2 | B5: Two Pointers | C5: Opposite-end pointers, same-direction pointers, fast/slow trick | D5: Sorted array scan, palindrome check, pair/triplet sums | E5: Valid Palindrome (125), Two Sum II (167), 3Sum (15), Container With Most Water (11), Trapping Rain Water (42) | F5: E/M/H | G5: 5 | H5: Phase 1 | I5: Two Pointers, Sorting | J5: Trapping Rain Water is a must-understand | K5: ⬜ Not Started
A6: 3 | B6: Sliding Window | C6: Fixed & variable window, window expansion/contraction, maintaining invariants | D6: Max/min subarray, distinct chars window, at-most-K variants | E6: Best Time to Buy & Sell Stock (121), Longest Substring Without Repeating (3), Longest Repeating Character Replacement (424), Permutation in String (567), Minimum Window Substring (76), Sliding Window Maximum (239) | F6: E/M/H | G6: 6 | H6: Phase 1 | I6: Sliding Window, Strings | J6: Variable window is trickier — master contraction logic | K6: ⬜ Not Started
A7: 4 | B7: Stack | C7: LIFO, monotonic stack, call stack simulation | D7: Next greater/smaller element, parenthesis matching, calculator eval | E7: Valid Parentheses (20), Min Stack (155), Evaluate Reverse Polish (150), Generate Parentheses (22), Daily Temperatures (739), Car Fleet (853), Largest Rectangle in Histogram (84) | F7: E/M/H | G7: 7 | H7: Phase 2 | I7: Stack, Monotonic Stack | J7: Monotonic stack pattern appears often in contests | K7: ⬜ Not Started
A8: 5 | B8: Linked Lists | C8: Node structure, pointer manipulation, dummy nodes, cycle detection | D8: Fast/slow pointers, reversal, merge, intersection | E8: Reverse Linked List (206), Merge Two Sorted Lists (21), Reorder List (143), Remove Nth Node (19), Copy List with Random Pointer (138), LRU Cache (146), Merge K Sorted Lists (23), Reverse Nodes in K-Group (25) | F8: E/M/H | G8: 8 | H8: Phase 2 | I8: Linked List, Two Pointers | J8: Draw diagrams; pointer bugs are common | K8: ⬜ Not Started
A9: 6 | B9: Binary Search | C9: Search space reduction, invariant maintenance, boundary conditions | D9: Left/right bisect, rotated array, search on answer (parametric) | E9: Binary Search (704), Search in Rotated Array (33), Find Minimum in Rotated Array (153), Search 2D Matrix (74), Koko Eating Bananas (875), Find in Mountain Array (1095), Median of Two Sorted Arrays (4) | F9: E/M/H | G9: 7 | H9: Phase 2 | I9: Binary Search, Divide & Conquer | J9: Off-by-one in lo/hi is the classic bug | K9: ⬜ Not Started
A10: 7 | B10: Trees — Basics | C10: DFS (pre/in/post), BFS (level order), height, diameter, LCA | D10: Recursive tree traversal, iterative with stack/queue | E10: Invert Binary Tree (226), Max Depth (104), Diameter of Binary Tree (543), Balanced Binary Tree (110), Same Tree (100), Subtree of Another Tree (572), Level Order Traversal (102), Right Side View (199) | F10: E/M | G10: 8 | H10: Phase 3 | I10: Trees, DFS, BFS | J10: Understand recursion return values clearly | K10: ⬜ Not Started
A11: 8 | B11: Trees — BST | C11: BST property, in-order gives sorted order, predecessor/successor | D11: Validation, range checks, kth smallest via in-order | E11: Lowest Common Ancestor BST (235), Insert into BST (701), Delete Node BST (450), Kth Smallest (230), Validate BST (98), Construct BST from Preorder (1008) | F11: E/M | G11: 6 | H11: Phase 3 | I11: BST, In-order | J11: In-order traversal is the BST superpower | K11: ⬜ Not Started
A12: 9 | B12: Tries | C12: Prefix tree, TrieNode structure, insert/search/startsWith | D12: Word search with backtracking, auto-complete, prefix frequency | E12: Implement Trie (208), Design Add and Search Words (211), Word Search II (212), Longest Word in Dictionary (720) | F12: M/H | G12: 4 | H12: Phase 3 | I12: Trie, Strings | J12: Word Search II combines Trie + backtracking | K12: ⬜ Not Started
A13: 10 | B13: Heap / Priority Queue | C13: Min-heap, max-heap, heapify, heap invariant, k-way merge | D13: Top-K pattern, streaming median, interval scheduling | E13: Kth Largest Element (215), K Closest Points (973), Task Scheduler (621), Design Twitter (355), Find Median from Data Stream (295), Merge K Sorted Lists (23), Top K Frequent (347) | F13: M/H | G13: 7 | H13: Phase 5 | I13: Heap, Priority Queue | J13: Python: heapq; Java: PriorityQueue; negate for max-heap | K13: ⬜ Not Started
A14: 11 | B14: Graphs — BFS/DFS | C14: Adjacency list/matrix, visited array, connected components, cycle detection | D14: Island counting, shortest path (BFS), topological sort | E14: Number of Islands (200), Clone Graph (133), Pacific Atlantic Water Flow (417), Surrounded Regions (130), Rotting Oranges (994), Walls and Gates (286), Course Schedule (207), Course Schedule II (210) | F14: M/H | G14: 8 | H14: Phase 3 | I14: Graph, BFS, DFS | J14: Know both recursive DFS and iterative BFS | K14: ⬜ Not Started
A15: 12 | B15: Advanced Graphs | C15: Dijkstra, Bellman-Ford, Union-Find, Minimum Spanning Tree, SCC | D15: Shortest paths, disjoint sets, Kruskal, Floyd-Warshall | E15: Network Delay Time (743), Swim in Rising Water (778), Alien Dictionary (269), Cheapest Flights K Stops (787), Min Cost to Connect Points (1584), Reconstruct Itinerary (332), Word Ladder (127) | F15: H | G15: 7 | H15: Phase 5 | I15: Dijkstra, Union-Find, MST | J15: Understand when to use which algorithm | K15: ⬜ Not Started
... A23: 20 | B23: Advanced Trees | C23: AVL concepts, Segment Trees, Fenwick Tree, Red-Black concepts | D23: Range queries, lazy propagation, order statistics | E23: Range Sum Query Mutable (307), Count of Smaller Numbers After Self (315), Reverse Pairs (493), My Calendar I/II (729/731), Falling Squares (699) | F23: H | G23: 5 | H23: Phase 6 | I23: Segment Tree, BIT, Advanced Trees | J23: Understand concept; BIT often sufficient in interviews | K23: ⬜ Not Started

Sheet 📊 Problem Tracker
A1: 📊 MASTER PROBLEM TRACKER — Mark ✅ Status here. All list sheets auto-sync via formula.
A3: # | B3: LC # | C3: Problem Title | D3: Topics | E3: Difficulty | F3: ✅ Status | G3: Date Solved | H3: Time (min) | I3: Key Insight / Pattern | J3: Retry? | K3: Retry Date | L3: Appears In | M3: Notes | N3: How to Solve | O3: Time Complexity | P3: Space Complexity | Q3: 🔗 LeetCode URL
A4: 1 | B4: 1 | C4: Two Sum | D4: Array, Hashing | E4: Easy | I4: HashMap (One-Pass) | L4: Amazon, Apple, Blind75, Google, Grind169, Grind75, Meta, Microsoft, NeetCode150, Uber | N4: HashMap (One-Pass): Store each number's index in a map. For each element, check if (target - num) exists before inserting. | O4: O(n) | P4: O(n) | Q4: https://leetcode.com/problems/two-sum/
A5: 2 | B5: 2 | C5: Add Two Numbers | D5: Linked List, Math | E5: Medium | I5: Linked List Traversal with Carry | L5: Amazon, Apple, Google, Grind169, Meta, Microsoft, Uber | N5: Linked List Traversal with Carry: Traverse both lists simultaneously, add digits plus carry, and handle remaining carry at the end. | O5: O(max(m, n)) | P5: O(max(m, n)) | Q5: https://leetcode.com/problems/add-two-numbers/
A6: 3 | B6: 3 | C6: Longest Substring Without Repeating Characters | D6: String, Sliding Window | E6: Medium | I6: Sliding Window + HashSet | L6: Amazon, Apple, Blind75, Google, Grind169, Grind75, Meta, Microsoft, NeetCode150, Uber | N6: Sliding Window + HashSet: Expand right pointer. If a char repeats, shrink left until removed. Track max window size. | O6: O(n) | P6: O(min(n, charset)) | Q6: https://leetcode.com/problems/longest-substring-without-repeating-characters/
A7: 4 | B7: 4 | C7: Median of Two Sorted Arrays | D7: Array, Binary Search | E7: Hard | I7: Binary Search on Smaller Array | L7: Amazon, Apple, Google, Grind169, Meta, Microsoft, NeetCode150, Uber | N7: Binary Search on Smaller Array: Partition the smaller array so all left-side values ≤ right-side values. Adjust lo/hi based on whether left-side max exceeds right-side min. | O7: O(log(min(m, n))) | P7: O(1) | Q7: https://leetcode.com/problems/median-of-two-sorted-arrays/
A8: 5 | B8: 5 | C8: Longest Palindromic Substring | D8: String, DP | E8: Medium | I8: Expand Around Center | L8: Amazon, Apple, Blind75, Google, Grind169, Grind75, Meta, Microsoft, NeetCode150, Uber | N8: Expand Around Center: For every character and gap center, expand outward while characters match and track the longest palindrome. | O8: O(n²) | P8: O(1) | Q8: https://leetcode.com/problems/longest-palindromic-substring/
A9: 6 | B9: 6 | C9: Zigzag Conversion | D9: String, Math | E9: Medium | I9: Row Assignment | L9: Amazon, Apple, Google, Meta | N9: Row Assignment: Simulate zigzag movement with a direction flag and append each character to the correct row. | O9: O(n) | P9: O(n) | Q9: https://leetcode.com/problems/zigzag-conversion/
A10: 7 | B10: 7 | C10: Reverse Integer | D10: Math | E10: Medium | I10: Math with Overflow Check | L10: Amazon, Apple, Google, Grind169, Meta, Microsoft, NeetCode150, Uber | N10: Math with Overflow Check: Pop digits one by one and push into result after checking INT_MIN/INT_MAX overflow boundaries. | O10: O(log n) | P10: O(1) | Q10: https://leetcode.com/problems/reverse-integer/
A11: 8 | B11: 8 | C11: String to Integer (atoi) | D11: String, Math | E11: Medium | I11: State Machine String Parsing | L11: Amazon, Apple, Google, Grind169, Grind75, Meta, Microsoft, Uber | N11: State Machine String Parsing: Skip spaces, handle sign, parse digits until a non-digit, and clamp to integer bounds. | O11: O(n) | P11: O(1) | Q11: https://leetcode.com/problems/string-to-integer-atoi/
A12: 9 | B12: 9 | C12: Palindrome Number | D12: Math | E12: Easy | I12: Revert Half the Number | L12: Amazon, Google, Grind169, Meta, Microsoft | N12: Revert Half the Number: Reverse the second half of the digits and compare it with the first half. | O12: O(log n) | P12: O(1) | Q12: https://leetcode.com/problems/palindrome-number/
A13: 10 | B13: 10 | C13: Regular Expression Matching | D13: String, DP | E13: Hard | I13: 2D DP - Regex Match | L13: Amazon, Apple, Google, Meta, Microsoft, NeetCode150, Uber | N13: 2D DP - Regex Match: Let dp[i][j] mean s[:i] matches p[:j]. Handle '*' as skip previous token or consume matching char. | O13: O(m·n) | P13: O(m·n) | Q13: https://leetcode.com/problems/regular-expression-matching/
A14: 11 | B14: 11 | C14: Container With Most Water | D14: Array, Two Pointers | E14: Medium | I14: Two Pointers from Both Ends | L14: Amazon, Apple, Blind75, Google, Grind169, Grind75, Meta, Microsoft, NeetCode150, Uber | N14: Two Pointers from Both Ends: Move the shorter height inward because it is the limiting side; update max area each step. | O14: O(n) | P14: O(1) | Q14: https://leetcode.com/problems/container-with-most-water/
A15: 12 | B15: 12 | C15: Integer to Roman | D15: String, Math | E15: Medium | I15: Greedy - Largest Symbol First | L15: Amazon, Google, Meta, Microsoft | N15: Greedy - Largest Symbol First: Process Roman values from largest to smallest, append symbols while subtracting their value. | O15: O(1) | P15: O(1) | Q15: https://leetcode.com/problems/integer-to-roman/
... A54: 51 | B54: 51 | C54: N-Queens | D54: Array, Backtracking | E54: Hard | I54: Backtracking | L54: Amazon, Google, Grind169, Meta, Microsoft, NeetCode150 | N54: Backtracking: Build candidates recursively, prune invalid choices early, add a result at the base case, and undo choices before returning. | O54: O(branch^depth) | P54: O(depth) | Q54: https://leetcode.com/problems/n-queens/
A55: 52 | B55: 52 | C55: N-Queens II | D55: Array, Backtracking | E55: Hard | I55: Backtracking | N55: Backtracking: Build candidates recursively, prune invalid choices early, add a result at the base case, and undo choices before returning. | O55: O(branch^depth) | P55: O(depth) | Q55: https://leetcode.com/problems/n-queens-ii/
A56: 53 | B56: 53 | C56: Maximum Subarray | D56: Array, DP | E56: Medium | I56: Kadane's Algorithm | L56: Amazon, Apple, Blind75, Google, Grind169, Grind75, Meta, Microsoft, NeetCode150, Uber | N56: Kadane's Algorithm: Track best subarray ending at current index and global best; restart when current value is better. | O56: O(n) | P56: O(1) | Q56: https://leetcode.com/problems/maximum-subarray/
A57: 54 | B57: 54 | C57: Spiral Matrix | D57: Array, Matrix | E57: Medium | I57: Boundary Shrinking | L57: Amazon, Apple, Blind75, Google, Grind169, Grind75, Meta, Microsoft, NeetCode150, Uber | N57: Boundary Shrinking: Maintain top, bottom, left, and right boundaries and traverse right, down, left, up while shrinking. | O57: O(m·n) | P57: O(1) | Q57: https://leetcode.com/problems/spiral-matrix/
A58: 55 | B58: 55 | C58: Jump Game | D58: Array, Greedy | E58: Medium | I58: Greedy - Track Max Reachable | L58: Amazon, Apple, Blind75, Google, Grind169, Meta, Microsoft, NeetCode150 | N58: Greedy - Track Max Reachable: Track the farthest reachable index and fail if the current index is beyond it. | O58: O(n) | P58: O(1) | Q58: https://leetcode.com/problems/jump-game/
A59: 56 | B59: 56 | C59: Merge Intervals | D59: Array, Intervals | E59: Medium | I59: Sort by Start + Merge Overlapping | L59: Amazon, Apple, Blind75, Google, Grind169, Grind75, Meta, Microsoft, NeetCode150, Uber | N59: Sort by Start + Merge Overlapping: Sort intervals by start and merge into the previous interval when they overlap. | O59: O(n log n) | P59: O(n) | Q59: https://leetcode.com/problems/merge-intervals/
A60: 57 | B60: 57 | C60: Insert Interval | D60: Array, Intervals | E60: Medium | I60: Three Phases | L60: Amazon, Apple, Blind75, Google, Grind169, Grind75, Microsoft, NeetCode150, Uber | N60: Three Phases: Before, Overlap, After: Add intervals before new interval, merge all overlaps with it, then append the rest. | O60: O(n) | P60: O(n) | Q60: https://leetcode.com/problems/insert-interval/
A61: 58 | B61: 58 | C61: Length of Last Word | D61: String | E61: Easy | I61: Scan from Right | L61: Amazon, Google, Meta, Microsoft | N61: Scan from Right: Skip trailing spaces, then count characters until the previous space. | O61: O(n) | P61: O(1) | Q61: https://leetcode.com/problems/length-of-last-word/
A62: 59 | B62: 59 | C62: Spiral Matrix II | D62: Array, Matrix | E62: Medium | I62: Boundary Simulation | L62: Amazon | N62: Boundary Simulation: Maintain top/bottom/left/right bounds and fill 1..n^2 while walking right, down, left, up, shrinking a bound after each edge. | O62: O(n^2) | P62: O(1) | Q62: https://leetcode.com/problems/spiral-matrix-ii/
A63: 60 | B63: 60 | C63: Permutation Sequence | D63: Math, Backtracking | E63: Hard | I63: Factorial Number System | L63: Amazon, Google | N63: Factorial Number System: Use factorial blocks to choose each digit of the kth permutation from remaining numbers. | O63: O(n²) | P63: O(n) | Q63: https://leetcode.com/problems/permutation-sequence/
A64: 61 | B64: 61 | C64: Rotate List | D64: Linked List | E64: Medium | I64: Find New Tail at Position (n-k%len) | L64: Amazon, Google, Grind169 | N64: Find New Tail at Position (n-k%len): Compute length, connect tail to head, then break at the new tail position. | O64: O(n) | P64: O(1) | Q64: https://leetcode.com/problems/rotate-list/
A65: 62 | B65: 62 | C65: Unique Paths | D65: DP, Math | E65: Medium | I65: DP - Unique Paths Grid | L65: Amazon, Blind75, Google, Grind169, Grind75, Meta, Microsoft, NeetCode150 | N65: DP - Unique Paths Grid: Use dp[i][j] = top + left, with first row and column initialized to 1. | O65: O(m·n) | P65: O(n) | Q65: https://leetcode.com/problems/unique-paths/
A66: 63 | B66: 63 | C66: Unique Paths II | D66: Array, Matrix, DP | E66: Medium | I66: Grid DP | L66: Amazon | N66: Grid DP: dp[j] = paths to a cell = 0 if obstacle else dp[j] (from above) + dp[j-1] (from left); use a 1D rolling row. | O66: O(m*n) | P66: O(n) | Q66: https://leetcode.com/problems/unique-paths-ii/
A67: 64 | B67: 64 | C67: Minimum Path Sum | D67: Array, Matrix, DP | E67: Medium | I67: DP - Min Path Sum | L67: Amazon, Google, Microsoft, Uber | N67: DP - Min Path Sum: Accumulate min cost from top or left; use the grid in-place when allowed. | O67: O(m·n) | P67: O(n) | Q67: https://leetcode.com/problems/minimum-path-sum/
... A79: 76 | B79: 76 | C79: Minimum Window Substring | D79: String, Sliding Window, Hashing | E79: Hard | I79: Sliding Window with Need/Have Counters | L79: Amazon, Apple, Blind75, Google, Grind169, Grind75, Meta, NeetCode150, Uber | N79: Sliding Window with Need/Have Counters: Expand right to satisfy required counts, shrink left while valid, and track the smallest window. | O79: O(n + m) | P79: O(k) | Q79: https://leetcode.com/problems/minimum-window-substring/
A80: 77 | B80: 77 | C80: Combinations | D80: Backtracking | E80: Medium | I80: Backtracking - Combinations | N80: Backtracking - Combinations: Iterate from start to n, add current to path, recurse for k-1, then backtrack. | O80: O(n) | P80: O(n) | Q80: https://leetcode.com/problems/combinations/
A81: 78 | B81: 78 | C81: Subsets | D81: Array, Backtracking | E81: Medium | I81: Backtracking / Iterative Subsets | L81: Amazon, Google, Grind169, Grind75, Meta, Microsoft, NeetCode150, Uber | N81: Backtracking / Iterative Subsets: For each number, either include or exclude it; collect all generated subsets. | O81: O(n · 2^n) | P81: O(n) | Q81: https://leetcode.com/problems/subsets/
A82: 79 | B82: 79 | C82: Word Search | D82: Array, Matrix, DFS | E82: Medium | I82: DFS Backtracking on Grid | L82: Amazon, Apple, Blind75, Google, Grind169, Grind75, Meta, Microsoft, NeetCode150, Uber | N82: DFS Backtracking on Grid: DFS from each matching start cell, mark visited in-place, explore 4 directions, then restore. | O82: O(m·n·4^L) | P82: O(L) | Q82: https://leetcode.com/problems/word-search/
A83: 80 | B83: 80 | C83: Remove Duplicates from Sorted Array II | D83: Array, Two Pointers | E83: Medium | I83: Two Pointers - Allow At Most 2 | L83: Amazon, Google | N83: Two Pointers - Allow At Most 2: Use a write pointer and keep an element only if it differs from the value two kept positions back. | O83: O(n) | P83: O(1) | Q83: https://leetcode.com/problems/remove-duplicates-from-sorted-array-ii/
A84: 81 | B84: 81 | C84: Search in Rotated Sorted Array II | D84: Array, Binary Search | E84: Medium | I84: Binary Search with Duplicate Handling | L84: Amazon, Uber | N84: Binary Search with Duplicate Handling: Use rotated binary search; when endpoints equal mid, shrink both ends. | O84: O(log n) avg, O(n) worst | P84: O(1) | Q84: https://leetcode.com/problems/search-in-rotated-sorted-array-ii/
A85: 82 | B85: 82 | C85: Remove Duplicates from Sorted List II | D85: Linked List | E85: Medium | I85: Linked List Pointers | L85: Apple | N85: Linked List Pointers: Use dummy nodes and careful prev/curr/next pointer updates to handle edge cases cleanly. | O85: O(n) | P85: O(1) | Q85: https://leetcode.com/problems/remove-duplicates-from-sorted-list-ii/
A86: 83 | B86: 83 | C86: Remove Duplicates from Sorted List | D86: Linked List | E86: Easy | I86: Linked List Pointers | L86: Amazon, Google | N86: Linked List Pointers: Use dummy nodes and careful prev/curr/next pointer updates to handle edge cases cleanly. | O86: O(n) | P86: O(1) | Q86: https://leetcode.com/problems/remove-duplicates-from-sorted-list/
A87: 84 | B87: 84 | C87: Largest Rectangle in Histogram | D87: Array, Stack, Monotonic Stack | E87: Hard | I87: Monotonic Stack - Extend Rectangles | L87: Amazon, Apple, Google, Grind169, Grind75, Meta, Microsoft, NeetCode150, Uber | N87: Monotonic Stack - Extend Rectangles: Maintain increasing bar indices; when a shorter bar appears, pop and compute rectangle area. | O87: O(n) | P87: O(n) | Q87: https://leetcode.com/problems/largest-rectangle-in-histogram/
A88: 85 | B88: 85 | C88: Maximal Rectangle | D88: Array, Matrix, Stack, DP | E88: Hard | I88: Extend LC84 Row by Row | L88: Amazon, Google, Meta, Microsoft | N88: Extend LC84 Row by Row: Convert each matrix row to histogram heights and apply largest rectangle in histogram. | O88: O(m·n) | P88: O(n) | Q88: https://leetcode.com/problems/maximal-rectangle/
A89: 86 | B89: 86 | C89: Partition List | D89: Linked List | E89: Medium | I89: Two Dummy Lists | L89: Amazon | N89: Two Dummy Lists: Build a 'less than x' list and a '>= x' list in one pass, then splice them together. | O89: O(n) | P89: O(1) | Q89: https://leetcode.com/problems/partition-list/
A90: 87 | B90: 88 | C90: Merge Sorted Array | D90: Array, Two Pointers | E90: Easy | I90: Three Pointers Merge from Back | L90: Amazon, Apple, Google, Meta, Microsoft | N90: Three Pointers Merge from Back: Merge nums2 into nums1 from the end so existing nums1 values are not overwritten. | O90: O(m+n) | P90: O(1) | Q90: https://leetcode.com/problems/merge-sorted-array/
A91: 88 | B91: 89 | C91: Gray Code | D91: Array, Math | E91: Medium | I91: Bit Trick | L91: Amazon | N91: Bit Trick: The i-th Gray code is i ^ (i >> 1); generate for i in 0..2^n-1. | O91: O(2^n) | P91: O(1) | Q91: https://leetcode.com/problems/gray-code/
A92: 89 | B92: 90 | C92: Subsets II | D92: Array, Backtracking | E92: Medium | I92: Backtracking | L92: Amazon, Apple, Google, NeetCode150 | N92: Backtracking: Build candidates recursively, prune invalid choices early, add a result at the base case, and undo choices before returning. | O92: O(n · 2^n) | P92: O(n) | Q92: https://leetcode.com/problems/subsets-ii/
... A96: 93 | B96: 94 | C96: Binary Tree Inorder Traversal | D96: Tree, DFS | E96: Easy | I96: Iterative Inorder with Stack | L96: Amazon, Google | N96: Iterative Inorder with Stack: Push left nodes, pop to visit, then traverse right subtree. | O96: O(n) | P96: O(h) | Q96: https://leetcode.com/problems/binary-tree-inorder-traversal/
A97: 94 | B97: 95 | C97: Unique Binary Search Trees II | D97: Tree, DP | E97: Medium | I97: Dynamic Programming | N97: Dynamic Programming: Define the state, initialize base cases, and transition from smaller subproblems to compute the answer. | O97: O(n) | P97: O(h) | Q97: https://leetcode.com/problems/unique-binary-search-trees-ii/
A98: 95 | B98: 96 | C98: Unique Binary Search Trees | D98: Tree, DP, Math | E98: Medium | I98: Binary Search | L98: Amazon, Meta | N98: Binary Search: Define a monotonic condition, check the middle value, and discard the half that cannot contain the answer. | O98: O(n²) | P98: O(n) | Q98: https://leetcode.com/problems/unique-binary-search-trees/
A99: 96 | B99: 97 | C99: Interleaving String | D99: String, DP | E99: Medium | I99: Dynamic Programming | L99: Amazon, Apple, Google, Microsoft, NeetCode150 | N99: Dynamic Programming: Define the state, initialize base cases, and transition from smaller subproblems to compute the answer. | O99: O(m·n) | P99: O(m·n) | Q99: https://leetcode.com/problems/interleaving-string/
A100: 97 | B100: 98 | C100: Validate Binary Search Tree | D100: Tree, DFS, BST | E100: Medium | I100: DFS with Min/Max Bounds | L100: Amazon, Apple, Blind75, Google, Grind169, Grind75, Meta, Microsoft, NeetCode150 | N100: DFS with Min/Max Bounds: Pass lower and upper bounds down the tree and ensure every node lies within its valid range. | O100: O(n) | P100: O(h) | Q100: https://leetcode.com/problems/validate-binary-search-tree/
A101: 98 | B101: 99 | C101: Recover Binary Search Tree | D101: Tree, DFS, BST | E101: Medium | I101: Binary Search | L101: Amazon, Google, Microsoft | N101: Binary Search: Define a monotonic condition, check the middle value, and discard the half that cannot contain the answer. | O101: O(n) | P101: O(h) | Q101: https://leetcode.com/problems/recover-binary-search-tree/
A102: 99 | B102: 100 | C102: Same Tree | D102: Tree, DFS | E102: Easy | I102: DFS - Compare Structure and Values | L102: Amazon, Apple, Blind75, Google, Grind169, Meta, Microsoft, NeetCode150 | N102: DFS - Compare Structure and Values: Recursively compare both trees for null structure, value equality, and matching children. | O102: O(n) | P102: O(h) | Q102: https://leetcode.com/problems/same-tree/
A103: 100 | B103: 101 | C103: Symmetric Tree | D103: Tree, DFS, BFS | E103: Easy | I103: DFS - Mirror Check on Left/Right | L103: Amazon, Apple, Google, Grind169, Meta, Microsoft | N103: DFS - Mirror Check on Left/Right: Recursively compare left.left with right.right and left.right with right.left. | O103: O(n) | P103: O(h) | Q103: https://leetcode.com/problems/symmetric-tree/
A104: 101 | B104: 102 | C104: Binary Tree Level Order Traversal | D104: Tree, BFS | E104: Medium | I104: BFS with Level Size Snapshot | L104: Amazon, Apple, Blind75, Google, Grind169, Grind75, Meta, Microsoft, NeetCode150 | N104: BFS with Level Size Snapshot: Use a queue and process exactly the current queue size for each level. | O104: O(n) | P104: O(n) | Q104: https://leetcode.com/problems/binary-tree-level-order-traversal/
A105: 102 | B105: 103 | C105: Binary Tree Zigzag Level Order Traversal | D105: Tree, BFS, Stack | E105: Medium | I105: Stack | L105: Amazon, Apple, Google, Grind169, Microsoft | N105: Stack: Push unresolved items and resolve them when the current item matches or dominates the stack top. | O105: O(n) | P105: O(n) | Q105: https://leetcode.com/problems/binary-tree-zigzag-level-order-traversal/
A106: 103 | B106: 104 | C106: Maximum Depth of Binary Tree | D106: Tree, DFS | E106: Easy | I106: DFS - Return Max Depth | L106: Amazon, Apple, Blind75, Google, Grind169, Grind75, Meta, Microsoft, NeetCode150, Uber | N106: DFS - Return Max Depth: Return 1 plus the maximum depth of left and right subtrees. | O106: O(n) | P106: O(h) | Q106: https://leetcode.com/problems/maximum-depth-of-binary-tree/
A107: 104 | B107: 105 | C107: Construct Binary Tree from Preorder and Inorder Traversal | D107: Tree, DFS, Array | E107: Medium | I107: Divide and Conquer with Inorder Index Map | L107: Amazon, Blind75, Google, Grind169, Grind75, Meta, Microsoft, NeetCode150 | N107: Divide and Conquer with Inorder Index Map: Use preorder root and inorder index to split left/right subtrees recursively. | O107: O(n) | P107: O(n) | Q107: https://leetcode.com/problems/construct-binary-tree-from-preorder-and-inorder-traversal/
A108: 105 | B108: 106 | C108: Construct Binary Tree from Inorder and Postorder Traversal | D108: Tree, DFS, Array | E108: Medium | I108: Recursive Build | L108: Amazon | N108: Recursive Build: Last value of postorder is the root; find it in inorder (hashmap) to split left/right, build right subtree before left. | O108: O(n) | P108: O(n) | Q108: https://leetcode.com/problems/construct-binary-tree-from-inorder-and-postorder-traversal/
A109: 106 | B109: 107 | C109: Binary Tree Level Order Traversal II | D109: Tree, BFS | E109: Medium | I109: BFS + Reverse | L109: Amazon | N109: BFS + Reverse: Standard level-order BFS collecting each level, then reverse the list of levels (or prepend each level). | O109: O(n) | P109: O(n) | Q109: https://leetcode.com/problems/binary-tree-level-order-traversal-ii/
... A112: 109 | B112: 110 | C112: Balanced Binary Tree | D112: Tree, DFS | E112: Easy | I112: Tree DFS/BFS | L112: Amazon, Google, Grind169, Grind75, Meta, Microsoft, NeetCode150 | N112: Tree DFS/BFS: Traverse the tree recursively or level by level, returning local information needed to build the global answer. | O112: O(n) | P112: O(h) | Q112: https://leetcode.com/problems/balanced-binary-tree/
A113: 110 | B113: 111 | C113: Minimum Depth of Binary Tree | D113: Tree, BFS | E113: Easy | I113: Tree DFS/BFS | N113: Tree DFS/BFS: Traverse the tree recursively or level by level, returning local information needed to build the global answer. | O113: O(n) | P113: O(n) | Q113: https://leetcode.com/problems/minimum-depth-of-binary-tree/
A114: 111 | B114: 112 | C114: Path Sum | D114: Tree, DFS | E114: Easy | I114: Tree DFS/BFS | L114: Apple, Google, Microsoft | N114: Tree DFS/BFS: Traverse the tree recursively or level by level, returning local information needed to build the global answer. | O114: O(n) | P114: O(h) | Q114: https://leetcode.com/problems/path-sum/
A115: 112 | B115: 113 | C115: Path Sum II | D115: Tree, DFS, Backtracking | E115: Medium | I115: Backtracking | L115: Amazon, Grind169 | N115: Backtracking: Build candidates recursively, prune invalid choices early, add a result at the base case, and undo choices before returning. | O115: O(n²) | P115: O(h) | Q115: https://leetcode.com/problems/path-sum-ii/
A116: 113 | B116: 114 | C116: Flatten Binary Tree to Linked List | D116: Tree, DFS | E116: Medium | I116: Linked List Pointers | L116: Amazon, Microsoft | N116: Linked List Pointers: Use dummy nodes and careful prev/curr/next pointer updates to handle edge cases cleanly. | O116: O(n) | P116: O(h) | Q116: https://leetcode.com/problems/flatten-binary-tree-to-linked-list/
A117: 114 | B117: 115 | C117: Distinct Subsequences | D117: String, DP | E117: Hard | I117: Dynamic Programming | L117: Google, Microsoft, NeetCode150 | N117: Dynamic Programming: Define the state, initialize base cases, and transition from smaller subproblems to compute the answer. | O117: O(m·n) | P117: O(n) | Q117: https://leetcode.com/problems/distinct-subsequences/
A118: 115 | B118: 116 | C118: Populating Next Right Pointers in Each Node | D118: Tree, BFS | E118: Medium | I118: Tree DFS/BFS | L118: Amazon, Google, Meta, Microsoft | N118: Tree DFS/BFS: Traverse the tree recursively or level by level, returning local information needed to build the global answer. | O118: O(n) | P118: O(1) | Q118: https://leetcode.com/problems/populating-next-right-pointers-in-each-node/
A119: 116 | B119: 117 | C119: Populating Next Right Pointers in Each Node II | D119: Tree, BFS | E119: Medium | I119: Tree DFS/BFS | L119: Meta | N119: Tree DFS/BFS: Traverse the tree recursively or level by level, returning local information needed to build the global answer. | O119: O(n) | P119: O(1) | Q119: https://leetcode.com/problems/populating-next-right-pointers-in-each-node-ii/
A120: 117 | B120: 118 | C120: Pascal's Triangle | D120: Array, Math | E120: Easy | I120: Math / Bit Manipulation | L120: Amazon, Apple, Google, Meta, Microsoft | N120: Math / Bit Manipulation: Use numeric properties or bit operations to avoid extra data structures and compute directly. | O120: O(n²) | P120: O(n²) | Q120: https://leetcode.com/problems/pascals-triangle/
A121: 118 | B121: 120 | C121: Triangle | D121: Array, DP | E121: Medium | I121: Dynamic Programming | L121: Amazon, Google | N121: Dynamic Programming: Define the state, initialize base cases, and transition from smaller subproblems to compute the answer. | O121: O(n²) | P121: O(n) | Q121: https://leetcode.com/problems/triangle/
A122: 119 | B122: 121 | C122: Best Time to Buy and Sell Stock | D122: Array, Greedy | E122: Easy | I122: Single Pass - Track Min Price | L122: Amazon, Apple, Blind75, Google, Grind169, Grind75, Meta, Microsoft, NeetCode150, Uber | N122: Single Pass - Track Min Price: Track the lowest price so far and update max profit using current price minus min price. | O122: O(n) | P122: O(1) | Q122: https://leetcode.com/problems/best-time-to-buy-and-sell-stock/
A123: 120 | B123: 122 | C123: Best Time to Buy and Sell Stock II | D123: Array, Greedy | E123: Medium | I123: Greedy - Take Every Upward Slope | L123: Amazon, Apple, Google, Meta, Microsoft | N123: Greedy - Take Every Upward Slope: Sum every positive day-to-day price difference. | O123: O(n) | P123: O(1) | Q123: https://leetcode.com/problems/best-time-to-buy-and-sell-stock-ii/
A124: 121 | B124: 123 | C124: Best Time to Buy and Sell Stock III | D124: Array, DP | E124: Hard | I124: Dynamic Programming | L124: Amazon, Apple, Google, Meta | N124: Dynamic Programming: Define the state, initialize base cases, and transition from smaller subproblems to compute the answer. | O124: O(n) | P124: O(1) | Q124: https://leetcode.com/problems/best-time-to-buy-and-sell-stock-iii/
A125: 122 | B125: 124 | C125: Binary Tree Maximum Path Sum | D125: Tree, DFS, DP | E125: Hard | I125: DFS - Global Max with Local Gain | L125: Amazon, Apple, Blind75, Google, Grind169, Meta, Microsoft, NeetCode150, Uber | N125: DFS - Global Max with Local Gain: Return max downward gain from each node and update global path using left + node + right. | O125: O(n) | P125: O(h) | Q125: https://leetcode.com/problems/binary-tree-maximum-path-sum/
... A159: 156 | B159: 165 | C159: Compare Version Numbers | D159: String | E159: Medium | I159: String Processing | L159: Amazon, Apple | N159: String Processing: Scan characters while maintaining the needed state, counters, or parsed tokens. | O159: O(n) | P159: O(n) | Q159: https://leetcode.com/problems/compare-version-numbers/
A160: 157 | B160: 166 | C160: Fraction to Recurring Decimal | D160: Math, Hashing, String | E160: Medium | I160: Long Division | N160: Long Division: Divide numerator by denominator tracking remainders in a HashMap. When remainder repeats, insert parentheses at that position. | O160: O(n) | P160: O(n) | Q160: https://leetcode.com/problems/fraction-to-recurring-decimal/
A161: 158 | B161: 167 | C161: Two Sum II - Input Array Is Sorted | D161: Array, Two Pointers | E161: Medium | I161: Two Pointers | L161: Amazon, Apple, Google, Meta, NeetCode150 | N161: Two Pointers: Maintain two indices and move the pointer that helps satisfy the condition while updating the answer. | O161: O(n) | P161: O(1) | Q161: https://leetcode.com/problems/two-sum-ii-input-array-is-sorted/
A162: 159 | B162: 168 | C162: Excel Sheet Column Title | D162: Math, String | E162: Easy | I162: Base-26 Conversion | L162: Amazon, Google | N162: Base-26 Conversion: Convert number to base-26 with A=1..Z=26 (no zero digit). Repeatedly take (n-1)%26 and prepend letter, then n=(n-1)/26. | O162: O(n) | P162: O(n) | Q162: https://leetcode.com/problems/excel-sheet-column-title/
A163: 160 | B163: 169 | C163: Majority Element | D163: Array | E163: Easy | I163: Boyer-Moore Voting Algorithm | L163: Amazon, Google, Grind169, Grind75, Meta, Microsoft | N163: Boyer-Moore Voting Algorithm: Maintain a candidate and count; majority survives cancellations, then candidate is answer. | O163: O(n) | P163: O(1) | Q163: https://leetcode.com/problems/majority-element/
A164: 161 | B164: 171 | C164: Excel Sheet Column Number | D164: Math, Hashing | E164: Easy | I164: HashMap / HashSet | L164: Uber | N164: HashMap / HashSet: Store seen values or counts for O(1) average lookups and update the answer during one pass. | O164: O(n) | P164: O(1) | Q164: https://leetcode.com/problems/excel-sheet-column-number/
A165: 162 | B165: 172 | C165: Factorial Trailing Zeroes | D165: Math | E165: Medium | I165: Count Factors of 5 | L165: Amazon | N165: Count Factors of 5: Trailing zeros = n/5 + n/25 + n/125 + ... since 5s are scarcer than 2s. | O165: O(log n) | P165: O(1) | Q165: https://leetcode.com/problems/factorial-trailing-zeroes/
A166: 163 | B166: 173 | C166: Binary Search Tree Iterator | D166: Tree, BST, Design | E166: Medium | I166: Binary Search | L166: Amazon, Apple, Meta, Microsoft | N166: Binary Search: Define a monotonic condition, check the middle value, and discard the half that cannot contain the answer. | O166: O(1) avg next | P166: O(h) | Q166: https://leetcode.com/problems/binary-search-tree-iterator/
A167: 164 | B167: 174 | C167: Dungeon Game | D167: Array, DP | E167: Hard | I167: DP Bottom-Up from Bottom-Right | L167: Amazon, Google, Uber | N167: DP Bottom-Up from Bottom-Right: dp[i][j]=min health to survive. At exit: max(1,1-dungeon[m-1][n-1]). Backward transition: max(1, min(dp[i+1][j], dp[i][j+1]) - dungeon[i][j]). | O167: O(m*n) | P167: O(m*n) | Q167: https://leetcode.com/problems/dungeon-game/
A168: 165 | B168: 175 | C168: Combine Two Tables | D168: SQL | E168: Easy | I168: SQL LEFT JOIN | L168: Amazon | N168: SQL LEFT JOIN: LEFT JOIN Persons and Addresses on PersonId to include persons with no address (NULL for city/state). | O168: O(n) | P168: O(n) | Q168: https://leetcode.com/problems/combine-two-tables/
A169: 166 | B169: 176 | C169: Second Highest Salary | D169: SQL | E169: Medium | I169: SQL Subquery/LIMIT | L169: Amazon, Apple, Google, Meta | N169: SQL Subquery/LIMIT: SELECT DISTINCT salary FROM Employee ORDER BY salary DESC LIMIT 1 OFFSET 1. Return NULL if not found. | O169: O(n) | P169: O(n) | Q169: https://leetcode.com/problems/second-highest-salary/
A170: 167 | B170: 177 | C170: Nth Highest Salary | D170: SQL | E170: Medium | I170: SQL Nth | L170: Amazon | N170: SQL Nth: SELECT DISTINCT salary FROM Employee ORDER BY salary DESC LIMIT 1 OFFSET N-1. Use variable offset. | O170: O(n) | P170: O(n) | Q170: https://leetcode.com/problems/nth-highest-salary/
A171: 168 | B171: 178 | C171: Rank Scores | D171: SQL | E171: Medium | I171: SQL Window | L171: Amazon | N171: SQL Window: DENSE_RANK() OVER (ORDER BY score DESC) gives the rank with no gaps for ties. | O171: O(n log n) | P171: O(n) | Q171: https://leetcode.com/problems/rank-scores/
A172: 169 | B172: 179 | C172: Largest Number | D172: Array, String, Sorting | E172: Medium | I172: Custom Comparator Sort | L172: Amazon, Grind169, Microsoft | N172: Custom Comparator Sort: Sort by comparing concatenated strings ab vs ba. comparator: return b+a > a+b. | O172: O(n log n · k) | P172: O(n·k) | Q172: https://leetcode.com/problems/largest-number/
... A185: 182 | B185: 193 | C185: Valid Phone Numbers | D185: String | E185: Easy | I185: Regex Line Filter | L185: Amazon | N185: Regex Line Filter: grep a line against ^(\d{3}-|\(\d{3}\) )\d{3}-\d{4}$ to keep valid phone numbers. | O185: O(n) | P185: O(1) | Q185: https://leetcode.com/problems/valid-phone-numbers/
A186: 183 | B186: 196 | C186: Delete Duplicate Emails | D186: Database (SQL) | E186: Easy | I186: SQL DELETE Self-Join | N186: SQL DELETE Self-Join: DELETE p1 FROM Person p1, Person p2 WHERE p1.Email=p2.Email AND p1.Id > p2.Id. | O186: O(n) | P186: O(n) | Q186: https://leetcode.com/problems/delete-duplicate-emails/
A187: 184 | B187: 197 | C187: Rising Temperature | D187: SQL | E187: Easy | I187: SQL Date Diff Join | L187: Amazon, Google | N187: SQL Date Diff Join: JOIN Weather w1 with w2 on DATEDIFF(w1.recordDate, w2.recordDate)=1 WHERE w1.temperature > w2.temperature. | O187: O(n) | P187: O(n) | Q187: https://leetcode.com/problems/rising-temperature/
A188: 185 | B188: 198 | C188: House Robber | D188: Array, DP | E188: Medium | I188: DP - Rob or Skip | L188: Amazon, Apple, Blind75, Google, Grind169, Meta, Microsoft, NeetCode150, Uber | N188: DP - Rob or Skip: For each house, choose max of skipping it or robbing it plus best two positions back. | O188: O(n) | P188: O(1) | Q188: https://leetcode.com/problems/house-robber/
A189: 186 | B189: 199 | C189: Binary Tree Right Side View | D189: Tree, BFS, DFS | E189: Medium | I189: Tree DFS/BFS | L189: Amazon, Apple, Grind169, Grind75, Meta, Microsoft, NeetCode150, Uber | N189: Tree DFS/BFS: Traverse the tree recursively or level by level, returning local information needed to build the global answer. | O189: O(n) | P189: O(n) | Q189: https://leetcode.com/problems/binary-tree-right-side-view/
A190: 187 | B190: 200 | C190: Number of Islands | D190: Array, Matrix, DFS, BFS | E190: Medium | I190: DFS/BFS Flood Fill | L190: Amazon, Apple, Blind75, Google, Grind169, Grind75, Meta, Microsoft, NeetCode150, Uber | N190: DFS/BFS Flood Fill: For each unvisited land cell, flood-fill the whole island and increment count. | O190: O(m·n) | P190: O(m·n) | Q190: https://leetcode.com/problems/number-of-islands/
A191: 188 | B191: 202 | C191: Happy Number | D191: Hashing, Two Pointers, Math | E191: Easy | I191: Fast/Slow Pointers on Number Sequence | L191: Amazon, Apple, Google, Meta, Microsoft, Uber | N191: Fast/Slow Pointers on Number Sequence: Repeatedly transform number to sum of squared digits and detect cycle; reaching 1 means happy. | O191: O(log n) | P191: O(1) | Q191: https://leetcode.com/problems/happy-number/
A192: 189 | B192: 203 | C192: Remove Linked List Elements | D192: Linked List | E192: Easy | I192: Linked List Pointers | L192: Amazon, Apple | N192: Linked List Pointers: Use dummy nodes and careful prev/curr/next pointer updates to handle edge cases cleanly. | O192: O(n) | P192: O(1) | Q192: https://leetcode.com/problems/remove-linked-list-elements/
A193: 190 | B193: 204 | C193: Count Primes | D193: Math | E193: Medium | I193: Math / Bit Manipulation | L193: Amazon, Apple, Google | N193: Math / Bit Manipulation: Use numeric properties or bit operations to avoid extra data structures and compute directly. | O193: O(n log log n) | P193: O(n) | Q193: https://leetcode.com/problems/count-primes/
A194: 191 | B194: 205 | C194: Isomorphic Strings | D194: String, Hashing | E194: Easy | I194: HashMap / HashSet | L194: Amazon, Google, Meta, Microsoft | N194: HashMap / HashSet: Store seen values or counts for O(1) average lookups and update the answer during one pass. | O194: O(n) | P194: O(1) | Q194: https://leetcode.com/problems/isomorphic-strings/
A195: 192 | B195: 206 | C195: Reverse Linked List | D195: Linked List | E195: Easy | I195: Iterative with Prev/Curr Pointers | L195: Amazon, Apple, Blind75, Google, Grind169, Grind75, Meta, Microsoft, NeetCode150, Uber | N195: Iterative with Prev/Curr Pointers: Reverse links one by one using prev, curr, and next pointers. | O195: O(n) | P195: O(1) | Q195: https://leetcode.com/problems/reverse-linked-list/
A196: 193 | B196: 207 | C196: Course Schedule | D196: Graph, Topological Sort | E196: Medium | I196: Topological Sort / Cycle Detection | L196: Amazon, Apple, Blind75, Google, Grind169, Grind75, Meta, Microsoft, NeetCode150, Uber | N196: Topological Sort / Cycle Detection: Build graph and indegrees; process zero-indegree courses and verify all are processed. | O196: O(V+E) | P196: O(V+E) | Q196: https://leetcode.com/problems/course-schedule/
A197: 194 | B197: 208 | C197: Implement Trie (Prefix Tree) | D197: Trie, Design | E197: Medium | I197: TrieNode with children + isEnd | L197: Amazon, Apple, Blind75, Google, Grind169, Grind75, Meta, Microsoft, NeetCode150, Uber | N197: TrieNode with children + isEnd: Insert and search by walking character nodes; mark word endings separately. | O197: O(L) per op | P197: O(total characters) | Q197: https://leetcode.com/problems/implement-trie-prefix-tree/
A198: 195 | B198: 209 | C198: Minimum Size Subarray Sum | D198: Array, Sliding Window | E198: Medium | I198: Sliding Window | L198: Amazon, Apple, Google, Microsoft | N198: Sliding Window: Expand the right pointer to include new items, shrink from the left when the constraint is violated, and track the best valid window. | O198: O(n) | P198: O(1) | Q198: https://leetcode.com/problems/minimum-size-subarray-sum/
... A254: 251 | B254: 287 | C254: Find the Duplicate Number | D254: Array, Two Pointers, Binary Search | E254: Medium | I254: Floyd's Cycle Detection | L254: Amazon, Google, Grind169, Meta, Microsoft, NeetCode150 | N254: Floyd's Cycle Detection: Treat nums as a linked list from index to nums[index]; cycle entry is duplicate. | O254: O(n) | P254: O(1) | Q254: https://leetcode.com/problems/find-the-duplicate-number/
A255: 252 | B255: 289 | C255: Game of Life | D255: Array, Matrix | E255: Medium | I255: Array Scan | N255: Array Scan: Iterate through the array while maintaining running state and update the result in-place when possible. | O255: O(m·n) | P255: O(1) | Q255: https://leetcode.com/problems/game-of-life/
...

Sheet 📈 Progress Dashboard
A1: 📈 AGGREGATE PROGRESS DASHBOARD
A2: Mark each problem's Status in the 📊 Problem Tracker (column F). Everything below updates automatically — the Tracker is the single source of truth.
A4: OVERALL
A5: Total Unique | B5: ✅ Solved | C5: 🚧 In Progress | D5: 🔁 Retry | E5: Remaining | F5: % Complete
A6: =COUNT('📊 Problem Tracker'!$B$4:$B$1200) -> 880 | B6: =COUNTIF('📊 Problem Tracker'!$F$4:$F$1200,"✅ Solved") -> 0 | C6: =COUNTIF('📊 Problem Tracker'!$F$4:$F$1200,"🚧 In Progress") -> 0 | D6: =COUNTIF('📊 Problem Tracker'!$F$4:$F$1200,"🔁 Retry") -> 0 | E6: =A6-B6 -> 880 | F6: =IFERROR(B6/A6,0) -> 0
A8: BY DIFFICULTY
A9: Difficulty | B9: Total | C9: ✅ Solved | D9: % Complete | E9: Progress
A10: Easy | B10: =COUNTIF('📊 Problem Tracker'!$E$4:$E$1200,"Easy") -> 233 | C10: =COUNTIFS('📊 Problem Tracker'!$E$4:$E$1200,"Easy",'📊 Problem Tracker'!$F$4:$F$1200,"✅ Solved") -> 0 | D10: =IFERROR(C10/B10,0) -> 0 | E10: =REPT("█",ROUND(D10*10,0))&REPT("░",10-ROUND(D10*10,0)) -> ░░░░░░░░░░
A11: Medium | B11: =COUNTIF('📊 Problem Tracker'!$E$4:$E$1200,"Medium") -> 503 | C11: =COUNTIFS('📊 Problem Tracker'!$E$4:$E$1200,"Medium",'📊 Problem Tracker'!$F$4:$F$1200,"✅ Solved") -> 0 | D11: =IFERROR(C11/B11,0) -> 0 | E11: =REPT("█",ROUND(D11*10,0))&REPT("░",10-ROUND(D11*10,0)) -> ░░░░░░░░░░
A12: Hard | B12: =COUNTIF('📊 Problem Tracker'!$E$4:$E$1200,"Hard") -> 144 | C12: =COUNTIFS('📊 Problem Tracker'!$E$4:$E$1200,"Hard",'📊 Problem Tracker'!$F$4:$F$1200,"✅ Solved") -> 0 | D12: =IFERROR(C12/B12,0) -> 0 | E12: =REPT("█",ROUND(D12*10,0))&REPT("░",10-ROUND(D12*10,0)) -> ░░░░░░░░░░
A13: BY PROBLEM LIST
A14: List | B14: Total | C14: ✅ Solved | D14: 🔁 Retry | E14: Remaining | F14: % Complete | G14: Progress
A15: 🎯 Blind 75 | B15: =COUNTIF('📊 Problem Tracker'!$L$4:$L$1200,"*Blind75*") -> 75 | C15: =COUNTIFS('📊 Problem Tracker'!$L$4:$L$1200,"*Blind75*",'📊 Problem Tracker'!$F$4:$F$1200,"✅ Solved") -> 0 | D15: =COUNTIFS('📊 Problem Tracker'!$L$4:$L$1200,"*Blind75*",'📊 Problem Tracker'!$F$4:$F$1200,"🔁 Retry") -> 0 | E15: =B15-C15 -> 75 | F15: =IFERROR(C15/B15,0) -> 0 | G15: =REPT("█",ROUND(F15*10,0))&REPT("░",10-ROUND(F15*10,0)) -> ░░░░░░░░░░
A16: ⚡ Grind 75 | B16: =COUNTIF('📊 Problem Tracker'!$L$4:$L$1200,"*Grind75*") -> 75 | C16: =COUNTIFS('📊 Problem Tracker'!$L$4:$L$1200,"*Grind75*",'📊 Problem Tracker'!$F$4:$F$1200,"✅ Solved") -> 0 | D16: =COUNTIFS('📊 Problem Tracker'!$L$4:$L$1200,"*Grind75*",'📊 Problem Tracker'!$F$4:$F$1200,"🔁 Retry") -> 0 | E16: =B16-C16 -> 75 | F16: =IFERROR(C16/B16,0) -> 0 | G16: =REPT("█",ROUND(F16*10,0))&REPT("░",10-ROUND(F16*10,0)) -> ░░░░░░░░░░
A17: 🔥 Grind 169 | B17: =COUNTIF('📊 Problem Tracker'!$L$4:$L$1200,"*Grind169*") -> 169 | C17: =COUNTIFS('📊 Problem Tracker'!$L$4:$L$1200,"*Grind169*",'📊 Problem Tracker'!$F$4:$F$1200,"✅ Solved") -> 0 | D17: =COUNTIFS('📊 Problem Tracker'!$L$4:$L$1200,"*Grind169*",'📊 Problem Tracker'!$F$4:$F$1200,"🔁 Retry") -> 0 | E17: =B17-C17 -> 169 | F17: =IFERROR(C17/B17,0) -> 0 | G17: =REPT("█",ROUND(F17*10,0))&REPT("░",10-ROUND(F17*10,0)) -> ░░░░░░░░░░
A18: 🚀 NeetCode 150 | B18: =COUNTIF('📊 Problem Tracker'!$L$4:$L$1200,"*NeetCode150*") -> 141 | C18: =COUNTIFS('📊 Problem Tracker'!$L$4:$L$1200,"*NeetCode150*",'📊 Problem Tracker'!$F$4:$F$1200,"✅ Solved") -> 0 | D18: =COUNTIFS('📊 Problem Tracker'!$L$4:$L$1200,"*NeetCode150*",'📊 Problem Tracker'!$F$4:$F$1200,"🔁 Retry") -> 0 | E18: =B18-C18 -> 141 | F18: =IFERROR(C18/B18,0) -> 0 | G18: =REPT("█",ROUND(F18*10,0))&REPT("░",10-ROUND(F18*10,0)) -> ░░░░░░░░░░
A19: 🔵 Google | B19: =COUNTIF('📊 Problem Tracker'!$L$4:$L$1200,"*Google*") -> 310 | C19: =COUNTIFS('📊 Problem Tracker'!$L$4:$L$1200,"*Google*",'📊 Problem Tracker'!$F$4:$F$1200,"✅ Solved") -> 0 | D19: =COUNTIFS('📊 Problem Tracker'!$L$4:$L$1200,"*Google*",'📊 Problem Tracker'!$F$4:$F$1200,"🔁 Retry") -> 0 | E19: =B19-C19 -> 310 | F19: =IFERROR(C19/B19,0) -> 0 | G19: =REPT("█",ROUND(F19*10,0))&REPT("░",10-ROUND(F19*10,0)) -> ░░░░░░░░░░
A20: 🍎 Apple | B20: =COUNTIF('📊 Problem Tracker'!$L$4:$L$1200,"*Apple*") -> 298 | C20: =COUNTIFS('📊 Problem Tracker'!$L$4:$L$1200,"*Apple*",'📊 Problem Tracker'!$F$4:$F$1200,"✅ Solved") -> 0 | D20: =COUNTIFS('📊 Problem Tracker'!$L$4:$L$1200,"*Apple*",'📊 Problem Tracker'!$F$4:$F$1200,"🔁 Retry") -> 0 | E20: =B20-C20 -> 298 | F20: =IFERROR(C20/B20,0) -> 0 | G20: =REPT("█",ROUND(F20*10,0))&REPT("░",10-ROUND(F20*10,0)) -> ░░░░░░░░░░
A21: 🔷 Meta | B21: =COUNTIF('📊 Problem Tracker'!$L$4:$L$1200,"*Meta*") -> 225 | C21: =COUNTIFS('📊 Problem Tracker'!$L$4:$L$1200,"*Meta*",'📊 Problem Tracker'!$F$4:$F$1200,"✅ Solved") -> 0 | D21: =COUNTIFS('📊 Problem Tracker'!$L$4:$L$1200,"*Meta*",'📊 Problem Tracker'!$F$4:$F$1200,"🔁 Retry") -> 0 | E21: =B21-C21 -> 225 | F21: =IFERROR(C21/B21,0) -> 0 | G21: =REPT("█",ROUND(F21*10,0))&REPT("░",10-ROUND(F21*10,0)) -> ░░░░░░░░░░
A22: 🪟 Microsoft | B22: =COUNTIF('📊 Problem Tracker'!$L$4:$L$1200,"*Microsoft*") -> 218 | C22: =COUNTIFS('📊 Problem Tracker'!$L$4:$L$1200,"*Microsoft*",'📊 Problem Tracker'!$F$4:$F$1200,"✅ Solved") -> 0 | D22: =COUNTIFS('📊 Problem Tracker'!$L$4:$L$1200,"*Microsoft*",'📊 Problem Tracker'!$F$4:$F$1200,"🔁 Retry") -> 0 | E22: =B22-C22 -> 218 | F22: =IFERROR(C22/B22,0) -> 0 | G22: =REPT("█",ROUND(F22*10,0))&REPT("░",10-ROUND(F22*10,0)) -> ░░░░░░░░░░
A23: 🚗 Uber | B23: =COUNTIF('📊 Problem Tracker'!$L$4:$L$1200,"*Uber*") -> 183 | C23: =COUNTIFS('📊 Problem Tracker'!$L$4:$L$1200,"*Uber*",'📊 Problem Tracker'!$F$4:$F$1200,"✅ Solved") -> 0 | D23: =COUNTIFS('📊 Problem Tracker'!$L$4:$L$1200,"*Uber*",'📊 Problem Tracker'!$F$4:$F$1200,"🔁 Retry") -> 0 | E23: =B23-C23 -> 183 | F23: =IFERROR(C23/B23,0) -> 0 | G23: =REPT("█",ROUND(F23*10,0))&REPT("░",10-ROUND(F23*10,0)) -> ░░░░░░░░░░
A24: 📦 Amazon | B24: =COUNTIF('📊 Problem Tracker'!$L$4:$L$1200,"*Amazon*") -> 659 | C24: =COUNTIFS('📊 Problem Tracker'!$L$4:$L$1200,"*Amazon*",'📊 Problem Tracker'!$F$4:$F$1200,"✅ Solved") -> 0 | D24: =COUNTIFS('📊 Problem Tracker'!$L$4:$L$1200,"*Amazon*",'📊 Problem Tracker'!$F$4:$F$1200,"🔁 Retry") -> 0 | E24: =B24-C24 -> 659 | F24: =IFERROR(C24/B24,0) -> 0 | G24: =REPT("█",ROUND(F24*10,0))&REPT("░",10-ROUND(F24*10,0)) -> ░░░░░░░░░░
A26: DSA TOPIC MASTERY
A27: Mastery Level | B27: # Topics
A28: ⬜ Not Started | B28: =COUNTIF('🧠 DSA Topics & Problems'!$K$4:$K$23,"⬜ Not Started") -> 20
A29: 📖 Learning | B29: =COUNTIF('🧠 DSA Topics & Problems'!$K$4:$K$23,"📖 Learning") -> 0
A30: 🛠️ Practiced | B30: =COUNTIF('🧠 DSA Topics & Problems'!$K$4:$K$23,"🛠️ Practiced") -> 0
A31: 💪 Confident | B31: =COUNTIF('🧠 DSA Topics & Problems'!$K$4:$K$23,"💪 Confident") -> 0
A32: 🏆 Mastered | B32: =COUNTIF('🧠 DSA Topics & Problems'!$K$4:$K$23,"🏆 Mastered") -> 0
A34: SYSTEM DESIGN
A35: Track | B35: Total | C35: ✅ Done | D35: % Complete | E35: Progress
A36: Mock Designs | B36: =COUNTA('🏗️ System Design'!B29:B44) -> 16 | C36: =COUNTIF('🏗️ System Design'!J29:J44,"✅ Done") -> 0 | D36: =IFERROR(C36/B36,0) -> 0 | E36: =REPT("█",ROUND(D36*10,0))&REPT("░",10-ROUND(D36*10,0)) -> ░░░░░░░░░░
A37: Building Blocks | B37: =COUNTA('🏗️ System Design'!B7:B24) -> 18 | C37: =COUNTIF('🏗️ System Design'!J7:J24,"✅ Covered") -> 0 | D37: =IFERROR(C37/B37,0) -> 0 | E37: =REPT("█",ROUND(D37*10,0))&REPT("░",10-ROUND(D37*10,0)) -> ░░░░░░░░░░

Sheet 🏗️ System Design
A1: 🏗️ SYSTEM DESIGN — CONCEPTS, FRAMEWORKS & MOCK DESIGNS
A3: SD INTERVIEW FRAMEWORK: Clarify Requirements → Estimate Scale → High-Level Design → Deep Dive → Trade-offs → Bottlenecks
A5: CORE BUILDING BLOCKS — Must Know Before Any Design
A6: # | B6: Building Block | C6: What It Does | D6: When to Use | E6: Key Trade-offs | F6: Interview Keywords | G6: Phase | H6: Study Resource | I6: Depth Required | J6: ✓ Covered
A7: 1 | B7: DNS & CDN | C7: Domain resolution; edge caching of static/dynamic content | D7: Any global-scale service | E7: Cache invalidation; TTL vs consistency | F7: Anycast, PoP, Cache-Control, CloudFront | G7: Phase 1 | H7: ByteByteGo Cap 1 | I7: Medium | J7: ⬜ Not Started
A8: 2 | B8: Load Balancer | C8: Distributes traffic across servers; health checks | D8: Any service with >1 server | E8: L4 vs L7; sticky sessions; SSL termination | F8: Round-robin, Least-conn, Consistent hash, NGINX | G8: Phase 1 | H8: ByteByteGo Cap 2 | I8: High | J8: ⬜ Not Started
A9: 3 | B9: Horizontal Scaling | C9: Add more instances instead of bigger instances | D9: Stateless services | E9: Stateless design; session externalization | F9: Stateless, session store, auto-scaling group | G9: Phase 1 | H9: Designing Data-Intensive Apps | I9: High | J9: ⬜ Not Started
A10: 4 | B10: Caching | C10: Redis/Memcached for hot data; multiple layers | D10: Read-heavy workloads | E10: Consistency, invalidation, thundering herd | F10: Cache-aside, Write-through, TTL, Eviction, LRU | G10: Phase 1 | H10: ByteByteGo Cap 4 | I10: High | J10: ⬜ Not Started
A11: 5 | B11: Message Queues | C11: Async decoupling; Kafka, RabbitMQ, SQS | D11: Event-driven, background jobs, fan-out | E11: At-least-once vs exactly-once; ordering | F11: Producer-Consumer, Pub-Sub, Partition, Offset, DLQ | G11: Phase 2 | H11: Kafka Definitive Guide | I11: High | J11: ⬜ Not Started
A12: 6 | B12: Databases — SQL | C12: ACID transactions, relational model, B-tree index | D12: Structured relational data, complex queries | E12: Vertical scale limits; shard complexity | F12: Normalization, Index, ACID, Join, Partition | G12: Phase 2 | H12: Use The Index Luke | I12: High | J12: ⬜ Not Started
A13: 7 | B13: Databases — NoSQL | C13: Document, KV, Wide-column, Graph stores | D13: Flexible schema, massive scale | E13: Eventual consistency; limited query patterns | F13: DynamoDB, Cassandra, MongoDB, BASE, CAP | G13: Phase 2 | H13: DDIA Ch 2 | I13: High | J13: ⬜ Not Started
A14: 8 | B14: Database Sharding | C14: Horizontal partitioning across DB nodes | D14: When single DB can't handle load | E14: Hotspot keys, cross-shard joins, rebalancing | F14: Shard key, Consistent hashing, Hotspot | G14: Phase 3 | H14: DDIA Ch 6 | I14: High | J14: ⬜ Not Started
A15: 9 | B15: Replication | C15: Primary-replica; multi-master for HA | D15: Read scaling; disaster recovery | E15: Replication lag; split-brain | F15: Leader election, WAL, Replica lag, Failover | G15: Phase 3 | H15: DDIA Ch 5 | I15: High | J15: ⬜ Not Started
A16: 10 | B16: Consistent Hashing | C16: Maps keys to nodes on a hash ring | D16: Distributed caches, load balancers | E16: Virtual nodes for uniform distribution | F16: Hash ring, Virtual nodes, Rendezvous hashing | G16: Phase 3 | H16: ByteByteGo Ch 5 | I16: Medium | J16: ⬜ Not Started
A17: 11 | B17: Rate Limiting | C17: Throttle requests per user/IP/token | D17: API protection, abuse prevention | E17: Distributed counters, accuracy vs overhead | F17: Token bucket, Leaky bucket, Sliding window, Redis | G17: Phase 3 | H17: ByteByteGo Ch 4 | I17: High | J17: ⬜ Not Started
A18: 12 | B18: API Design | C18: REST vs GraphQL vs gRPC; pagination; versioning | D18: Every service boundary | E18: Coupling, backward compat, latency | F18: REST, GraphQL, gRPC, Pagination cursor, Idempotency | G18: Phase 2 | H18: API Design Patterns (Geewax) | I18: High | J18: ⬜ Not Started
... A24: 18 | B24: Security Basics | C24: AuthN/AuthZ, OAuth2, JWT, HTTPS, RBAC | D24: Every system | E24: Token revocation; over-privilege | F24: OAuth2, JWT, mTLS, RBAC, CORS, CSRF | G24: Phase 2 | H24: Auth0 Docs, OWASP | I24: Medium | J24: ⬜ Not Started
A27: SYSTEM DESIGN MOCK PROBLEMS — 1 Per Day, Timed 45–60 Minutes
A28: # | B28: System to Design | C28: Core Challenges | D28: Key Components | E28: Scale Target | F28: Bottlenecks to Discuss | G28: Trade-offs | H28: Phase | I28: Difficulty | J28: ✓ Done
A29: 1 | B29: URL Shortener (TinyURL) | C29: Hash collision, redirect latency, analytics | D29: KV store, Base62 encoding, Bloom filter | E29: 100M URLs, 10B redirects/day | F29: Cache hot URLs, DB read replicas | G29: Custom alias vs random; hash vs counter | H29: Phase 1 | I29: Beginner | J29: ⬜ Not Started
A30: 2 | B30: Rate Limiter | C30: Distributed counters, multi-data-center | D30: Redis + Lua script, sliding window | E30: 10K RPS per user | F30: Redis cluster; clock skew | G30: Exact vs approx counting; local vs global | H30: Phase 1 | I30: Beginner | J30: ⬜ Not Started
A31: 3 | B31: Key-Value Store | C31: Consistent hashing, replication, compaction | D31: Ring, LSM tree, WAL, Gossip protocol | E31: 10K writes/sec, 100K reads/sec | F31: Hot partitions, GC pauses | G31: Consistency levels; read-repair vs quorum | H31: Phase 2 | I31: Intermediate | J31: ⬜ Not Started
A32: 4 | B32: Unique ID Generator | C32: Clock skew, monotonic ordering, multi-DC | D32: Snowflake ID, UUID v4, DB sequences | E32: 100K IDs/sec, globally unique | F32: Time sync; NTP drift | G32: Ordered vs random; size tradeoffs | H32: Phase 2 | I32: Beginner | J32: ⬜ Not Started
A33: 5 | B33: Web Crawler | C33: Politeness, dedup, URL frontier priority | D33: BFS queue, Bloom filter, DNS cache, Robot.txt parser | E33: 1B pages/month | F33: DNS lookup bottleneck; duplicate content | G33: BFS vs DFS; centralized vs distributed | H33: Phase 2 | I33: Intermediate | J33: ⬜ Not Started
A34: 6 | B34: Notification System | C34: Fan-out on write vs read, delivery guarantee | D34: Kafka, push/email/SMS workers, user prefs DB | E34: 10M notifications/day | F34: Celebrity problem, mobile push limits | G34: Exactly-once vs at-least-once; freshness | H34: Phase 3 | I34: Intermediate | J34: ⬜ Not Started
A35: 7 | B35: News Feed (Facebook/Twitter) | C35: Fan-out, feed ranking, hot celebrity | D35: Write/read fan-out hybrid, Redis feed cache, ML rank | E35: 500M DAU, 5M posts/day | F35: Celeb accounts (50M followers) | G35: Hybrid fan-out threshold; pre-compute vs lazy | H35: Phase 3 | I35: Intermediate | J35: ⬜ Not Started
A36: 8 | B36: Chat System (WhatsApp) | C36: Real-time delivery, presence, message ordering | D36: WebSocket, Kafka, Cassandra (time-series), Redis presence | E36: 2B users, 100B messages/day | F36: Connection servers scaling; message ordering | G36: End-to-end encrypt; store vs ephemeral | H36: Phase 3 | I36: Intermediate | J36: ⬜ Not Started
A37: 9 | B37: Search Autocomplete | C37: Prefix trie, top-K tracking, latency budget | D37: Distributed trie, Redis ZSET, data aggregation pipeline | E37: 10M queries/sec, p99 < 100ms | F37: Trie rebalancing; stale suggestions | G37: Exact vs fuzzy; personalization | H37: Phase 4 | I37: Advanced | J37: ⬜ Not Started
A38: 10 | B38: YouTube / Video Platform | C38: Upload pipeline, streaming, CDN, transcoding | D38: Object storage, transcoding queue, CDN, HLS/DASH | E38: 1B hours viewed/day, 500h video uploaded/min | F38: Transcoding farm capacity; CDN egress cost | G38: ABR streaming; copyright detection | H38: Phase 4 | I38: Advanced | J38: ⬜ Not Started
A39: 11 | B39: Ride-Sharing (Uber) | C39: Real-time matching, location updates, surge | D39: WebSocket, geospatial index (QuadTree/S2), Kafka | E39: 5M trips/day, 500K active drivers | F39: Location update write volume; matching latency | G39: Strong vs eventual for driver location | H39: Phase 4 | I39: Advanced | J39: ⬜ Not Started
A40: 12 | B40: Hotel Booking (Airbnb) | C40: Double booking prevention, search, payments | D40: Distributed lock / idempotency, Elasticsearch, Stripe | E40: 10M listings, 1M bookings/day | F40: Race condition on last room; search freshness | G40: Optimistic vs pessimistic locking | H40: Phase 4 | I40: Advanced | J40: ⬜ Not Started
... A44: 16 | B44: Ad Click Aggregator | C44: Real-time stream + batch lambda, dedup | D44: Kafka, Flink, ClickHouse, Bloom filter dedup | E44: 1B clicks/day, report in 1 min | F44: Late data, dedup at scale | G44: Lambda vs Kappa; accuracy vs freshness | H44: Phase 6 | I44: Expert | J44: ⬜ Not Started

Sheet 🗣️ Behavioral (STAR)
A1: 🗣️ BEHAVIORAL PREP — STAR STORIES
A2: STAR = Situation · Task · Action · Result. Draft 1–2 crisp, quantified stories per competency and reuse them across questions. Keep the Result measurable (%, $, time, scale). Most rows map to an Amazon Leadership Principle — but they work for any company.
A4: STAR STORY BANK
A5: # | B5: Theme / Story Title | C5: Competency | D5: Common Questions It Answers | E5: S — Situation | F5: T — Task | G5: A — Action | H5: R — Result (quantify!) | I5: Maps To (Amazon LP) | J5: Status
A6: Ex | B6: ‹EXAMPLE — replace with your own› | C6: Ownership | D6: Took ownership beyond role | E6: A data-ingest service was dropping batches silently in production and no one owned it. | F6: I volunteered to stabilize it before the next release. | G6: Added structured logging, root-caused the dropped batches, and drove a cross-team fix. | H6: Cut data-loss incidents to ~0 and reduced on-call pages by ~70% over two months. | I6: Ownership | J6: ✅ Ready
A7: 1 | B7: Ownership | C7: Ownership | D7: Tell me about a time you took ownership of something beyond your role. | I7: Ownership | J7: ⬜ Not Drafted
A8: 2 | B8: Customer Focus | C8: Customer Focus | D8: Describe a time you went above and beyond for a customer or end user. | I8: Customer Obsession | J8: ⬜ Not Drafted
A9: 3 | B9: Failure / Lessons | C9: Failure / Lessons | D9: Tell me about a time you failed. What did you learn? | I9: Learn and Be Curious | J9: ⬜ Not Drafted
A10: 4 | B10: Conflict / Trust | C10: Conflict / Trust | D10: Describe a conflict with a teammate and how you resolved it. | I10: Earn Trust | J10: ⬜ Not Drafted
A11: 5 | B11: Disagreeing Up | C11: Disagreeing Up | D11: Tell me about a time you disagreed with your manager or a decision. | I11: Have Backbone; Disagree and Commit | J11: ⬜ Not Drafted
A12: 6 | B12: Ambiguity | C12: Ambiguity | D12: Describe a time you had to act with incomplete information. | I12: Bias for Action | J12: ⬜ Not Drafted
A13: 7 | B13: Tight Deadline | C13: Tight Deadline | D13: Tell me about a time you delivered under significant time pressure. | I13: Deliver Results | J13: ⬜ Not Drafted
A14: 8 | B14: Innovation / Simplify | C14: Innovation / Simplify | D14: Tell me about a time you invented or simplified a process. | I14: Invent and Simplify | J14: ⬜ Not Drafted
A15: 9 | B15: Highest Standards | C15: Highest Standards | D15: Tell me about a time you refused to compromise on quality. | I15: Insist on the Highest Standards | J15: ⬜ Not Drafted
A16: 10 | B16: Developing Others | C16: Developing Others | D16: Tell me about a time you mentored or grew someone. | I16: Hire and Develop the Best | J16: ⬜ Not Drafted
A17: 11 | B17: Data / Deep Dive | C17: Data / Deep Dive | D17: Tell me about a time data changed your decision. | I17: Dive Deep | J17: ⬜ Not Drafted
A18: 12 | B18: Long-Term Thinking | C18: Long-Term Thinking | D18: Tell me about a time you chose the long-term win over a quick fix. | I18: Think Big | J18: ⬜ Not Drafted
... A21: 15 | B21: Doing More with Less | C21: Doing More with Less | D21: Tell me about a time you achieved more with limited resources. | I21: Frugality | J21: ⬜ Not Drafted
A23: AMAZON LEADERSHIP PRINCIPLES — QUICK REFERENCE
A24: # | B24: Leadership Principle | C24: What It Means (one line)
A25: 1 | B25: Customer Obsession | C25: Start from the customer and work backwards; earn and keep their trust.
A26: 2 | B26: Ownership | C26: Think long-term, act on behalf of the whole company, never say 'not my job'.
A27: 3 | B27: Invent and Simplify | C27: Seek new ideas from everywhere; simplify as you scale.
A28: 4 | B28: Are Right, A Lot | C28: Strong judgment; seek diverse perspectives and disconfirm your own beliefs.
A29: 5 | B29: Learn and Be Curious | C29: Always improving; curious about new possibilities.
A30: 6 | B30: Hire and Develop the Best | C30: Raise the bar; coach others and build leaders.
A31: 7 | B31: Insist on the Highest Standards | C31: Relentlessly high bar; defects don't move downstream.
A32: 8 | B32: Think Big | C32: Bold direction that inspires results; think differently.
A33: 9 | B33: Bias for Action | C33: Speed matters; many decisions are reversible (two-way doors).
A34: 10 | B34: Frugality | C34: Do more with less; constraints breed resourcefulness.
A35: 11 | B35: Earn Trust | C35: Listen, speak candidly, treat others respectfully, admit mistakes.
A36: 12 | B36: Dive Deep | C36: Stay connected to details, audit frequently, no task beneath you.
... A40: 16 | B40: Success and Scale Bring Broad Responsibility | C40: Be humble; consider the broader impact of decisions.

Sheet 📅 16-Week Schedule
A1: 📅 16-WEEK DETAILED SCHEDULE — DSA + SYSTEM DESIGN
A3: Week | B3: Phase | C3: DSA Topic (Days 1-5) | D3: Problems to Solve | E3: Target Problem Count | F3: System Design Topic | G3: SD Deep Dive | H3: Key Goal | I3: Checkpoint
A4: 1 | B4: Phase 1 | C4: Arrays & Hashing | D4: Two Sum, Valid Anagram, Contains Duplicate, Group Anagrams, Top K Frequent, Product Except Self, Longest Consecutive Sequence | E4: 25 | F4: Scalability 101: vertical vs horizontal, CAP theorem basics | G4: Understand SLA, SLO, SLI; latency vs throughput | H4: Nail HashMap O(1) lookups | I4: Can you solve Two Sum 5 ways?
A5: 2 | B5: Phase 1 | C5: Two Pointers + Sliding Window | D5: Valid Palindrome, 3Sum, Container With Most Water, Best Time Buy/Sell, Longest Substring No Repeat, Min Window Substring | E5: 20 | F5: Load Balancers deep dive: L4 vs L7, algorithms | G5: Design a simple API gateway | H5: Master variable-window pattern | I5: Solve Min Window Substring from scratch
A6: 3 | B6: Phase 2 | C6: Stack + Queues | D6: Valid Parentheses, Min Stack, Daily Temperatures, Car Fleet, Largest Rectangle Histogram, Sliding Window Max | E6: 20 | F6: Caching: Redis internals, eviction, cache patterns | G6: Design a distributed cache (Redis-like) | H6: Monotonic stack mastery | I6: Implement LRU Cache from memory
A7: 4 | B7: Phase 2 | C7: Linked Lists | D7: Reverse LL, Merge Two Sorted, Reorder List, Remove Nth Node, LRU Cache, Merge K Sorted Lists | E7: 20 | F7: Databases: SQL indexing, query planning, ACID | G7: Design URL shortener | H7: Pointer manipulation fluency | I7: No bugs in LL reversal
A8: 5 | B8: Phase 3 | C8: Binary Search | D8: Binary Search, Search Rotated Array, Find Min Rotated, Search 2D Matrix, Koko Eating Bananas, Median Two Arrays | E8: 20 | F8: NoSQL: DynamoDB, Cassandra, consistency models | G8: Design a KV store | H8: Master search on answer | I8: Solve Median Two Arrays without hints
A9: 6 | B9: Phase 3 | C9: Trees — BFS/DFS | D9: Invert Tree, Max Depth, Diameter, Level Order, Right Side View, Balanced Tree, Same Tree, Subtree | E9: 20 | F9: API Design: REST principles, pagination, versioning | G9: Design Twitter API | H9: Tree recursion mental model | I9: Implement iterative in-order traversal
A10: 7 | B10: Phase 3 | C10: BST + Trie | D10: LCA BST, Validate BST, Kth Smallest, Implement Trie, Add/Search Words, Word Search II | E10: 20 | F10: Message Queues: Kafka architecture, partitions, consumer groups | G10: Design notification system | H10: BST in-order = sorted; Trie prefix power | I10: Build Trie from scratch
A11: 8 | B11: Phase 3 | C11: Graphs — BFS/DFS | D11: Number of Islands, Clone Graph, Course Schedule I/II, Pacific Atlantic, Rotting Oranges, Word Ladder | E11: 25 | F11: Consistent Hashing + Sharding | G11: Design distributed cache with sharding | H11: DFS/BFS template mastery | I11: Topological sort both BFS & DFS
A12: 9 | B12: Phase 4 | C12: 1D DP | D12: Climbing Stairs, House Robber I/II, LIS, Coin Change, Word Break, Decode Ways, Palindromic Substrings, Max Product Subarray | E12: 25 | F12: Rate Limiting deep dive: token bucket, leaky bucket | G12: Design API rate limiter | H12: Define dp[i] precisely before coding | I12: Coin Change bottom-up and top-down
A13: 10 | B13: Phase 4 | C13: Backtracking + Greedy | D13: Subsets, Combination Sum I/II, Permutations, Palindrome Partitioning, N-Queens, Jump Game I/II, Gas Station | E13: 25 | F13: Blob Storage + CDN: S3, CloudFront, presigned URLs | G13: Design photo sharing (Instagram) | H13: Decision tree visualization | I13: N-Queens with pruning from memory
A14: 11 | B14: Phase 4 | C14: 2D DP | D14: Unique Paths, LCS, Edit Distance, Interleaving String, Burst Balloons, Best Time Buy/Sell III/IV, Distinct Subsequences | E14: 20 | F14: Search systems: Elasticsearch, inverted index, ranking | G14: Design type-ahead / autocomplete | H14: DP table transitions clarity | I14: Edit Distance with DP table drawn out
A15: 12 | B15: Phase 5 | C15: Heaps + Intervals | D15: K Closest Points, Task Scheduler, Find Median Stream, Merge K Sorted, Non-Overlapping Intervals, Meeting Rooms II | E15: 20 | F15: Real-time systems: WebSockets, long-polling, SSE | G15: Design chat application (WhatsApp) | H15: Heap invariants; interval sweep line | I15: Implement heap from scratch in Java
... A18: 15 | B18: Phase 7 | C18: Mock Interviews — Mixed | D18: FAANG-tagged problems: Amazon 40, Google 40, Meta 30, Microsoft 30 — timed 45-min sessions per problem | E18: 20 | F18: Full mock SDs: 60-min timed — Uber, Google Drive, Twitter | G18: Practice talking through design out loud | H18: Interview simulation under pressure | I18: Complete 2 full mock interviews
A19: 16 | B19: Phase 8 | C19: Final Sprint + Revision | D19: Re-solve all flagged retry problems; NeetCode 75 speed run; any weak areas | E19: 20+ | F19: Review all SD building blocks; practice trade-off discussions | G19: Behavioral + SD combos | H19: Confidence & polish | I19: Can you do any problem in under 25 min?

Sheet ⚡ Pattern Cheatsheet
A1: ⚡ PATTERN RECOGNITION CHEATSHEET — Identify the Pattern, Not Just the Problem
A3: Pattern | B3: Recognize When… | C3: Template / Approach | D3: Time Complexity | E3: Space Complexity | F3: Key Problems | G3: Gotchas
A4: Sliding Window (Variable) | B4: Max/min subarray satisfying a constraint; 'longest substring with...' | C4: Expand right pointer always; shrink left when constraint violated; track window state with map/int | D4: O(n) | E4: O(k) window size | F4: Min Window Substring, Longest Substring No Repeat, Fruit Into Baskets | G4: Define precisely when to shrink; avoid over-shrinking
A5: Two Pointers (Opposite Ends) | B5: Sorted array + pair/triplet sum; palindrome check; container problems | C5: lo=0, hi=n-1; move based on comparison to target; sort first if needed | D5: O(n log n) with sort | E5: O(1) | F5: 3Sum, Container With Water, Trapping Rain Water | G5: Sort destroys index — use values; watch duplicate skipping in 3Sum
A6: Fast & Slow Pointers | B6: Cycle detection, finding middle, kth from end | C6: slow=head, fast=head; slow moves 1, fast moves 2; check fast==slow for cycle | D6: O(n) | E6: O(1) | F6: Linked List Cycle, Find Duplicate Number, Happy Number | G6: For find duplicate: Floyd's cycle = detect, find entry = cycle start
A7: BFS (Level Order / Shortest Path) | B7: Shortest path in unweighted graph; level-by-level processing | C7: Queue with (node, dist/level); mark visited before enqueue not after dequeue | D7: O(V+E) | E7: O(V) | F7: Word Ladder, Rotting Oranges, Shortest Path in Binary Matrix | G7: Mark visited at enqueue time to avoid TLE
A8: DFS + Backtracking | B8: Generate all combinations/permutations/subsets; constraint satisfaction | C8: Choose → recurse → unchoose; prune early; track current path | D8: O(2^n) or O(n!) | E8: O(n) stack depth | F8: Subsets, Permutations, N-Queens, Sudoku Solver | G8: Draw decision tree first; add index param to avoid reuse
A9: Monotonic Stack (Decreasing) | B9: Next Greater Element; temperatures; histogram rectangle | C9: Maintain decreasing stack; pop when current > stack top; record answer at pop time | D9: O(n) | E9: O(n) | F9: Daily Temperatures, Largest Rect Histogram, Trapping Rain Water | G9: Know whether to store index vs value in stack
A10: Binary Search on Answer | B10: 'Minimum maximum' or 'Maximum minimum'; feasibility function exists | C10: lo=min_val, hi=max_val; binary search; write isValid(mid) function | D10: O(n log(range)) | E10: O(1) | F10: Koko Eating Bananas, Split Array Largest Sum, Capacity to Ship | G10: isValid() must be monotonic; think about lo/hi edge cases
A11: Top-K with Heap | B11: Kth largest/smallest; K most frequent; K closest | C11: Min-heap of size K for Kth largest; pop when size>K; heap top = answer | D11: O(n log k) | E11: O(k) | F11: Kth Largest, K Closest Points, Top K Frequent, Find Median Stream | G11: Min-heap for top-K largest (counter-intuitive); max-heap for Kth smallest
A12: 1D DP — Knapsack | B12: Include/exclude decision; optimal value with constraint | C12: dp[i] = max/min considering first i items; dp[i] = max(dp[i-1], dp[i-w]+val) | D12: O(n*W) | E12: O(n) or O(W) optimized | F12: 0/1 Knapsack, Coin Change, House Robber, Partition Equal Subset | G12: Traverse inner loop backwards for 0/1 (avoid reuse)
A13: 2D DP — Two Sequences | B13: LCS, Edit Distance, Interleaving — comparing two strings/arrays | C13: dp[i][j] = answer for s1[:i] and s2[:j]; fill row by row | D13: O(m*n) | E13: O(m*n) or O(n) optimized | F13: LCS, Edit Distance, Regex Match, Distinct Subsequences | G13: Define dp[0][j] and dp[i][0] base cases carefully
A14: Union-Find | B14: Connected components; dynamic connectivity; cycle in undirected graph | C14: find() with path compression; union() with rank; detect cycle if find(u)==find(v) before union | D14: O(α(n)) ≈ O(1) | E14: O(n) | F14: Redundant Connection, Number of Islands II, Accounts Merge | G14: Always implement both path compression AND union by rank
... A18: Interval Merge/Overlap | B18: Merging overlapping intervals; scheduling conflicts | C18: Sort by start; if curr.start <= prev.end → merge (update end); else add to result | D18: O(n log n) | E18: O(n) | F18: Merge Intervals, Non-Overlapping Intervals, Meeting Rooms II | G18: Sort by start for merge; sort by end for greedy scheduling

Sheet 🔁 Retry Tracker
A1: 🔁 SPACED REPETITION RETRY TRACKER — Revisit Hard Problems at 3 / 7 / 14 Days
A3: 🔍 FILTER TIPS: ▼ on Difficulty → filter Easy / Medium / Hard | ▼ on Topic → Text Filters → Contains → type e.g. 'Array' or 'DP'
A4: # | B4: LeetCode # | C4: Problem Name | D4: Topic | E4: Difficulty | F4: First Attempt Date | G4: Retry 1 Date (3 days) | H4: Retry 2 Date (7 days) | I4: Retry 3 Date (14 days) | K4: Cols B–E auto-fill from problems you mark 🔁 Retry in the Tracker (Excel 365 / Sheets). Fill the retry dates yourself.
A5: 1
A6: 2
A7: 3
A8: 4
A9: 5
A10: 6
A11: 7
A12: 8
A13: 9
A14: 10
A15: 11
A16: 12
... A104: 100

Sheet 🎯 Blind 75
A1: 🎯 BLIND 75 — Complete LeetCode Problem List with Patterns & Tracker | L1: 🎯 BLIND 75 — Complete LeetCode Problem List with Patterns & Tracker
A3: Curated by Krishna Dey | 75 problems covering all core interview patterns | Solve in order: Easy → Medium → Hard within each category
A4: 🔍 FILTER TIPS: ▼ on Difficulty → filter Easy / Medium / Hard | ▼ on Problem Types → Text Filters → Contains → type e.g. 'Array' or 'DP' | For multiple types: Custom Filter → Contains 'Array' AND/OR Contains 'BFS'
A5: # | B5: Category | C5: LC # | D5: Problem Title | E5: Difficulty | F5: Key Pattern / Insight | G5: LeetCode URL | H5: Premium? | I5: ✅ Status (auto) | J5: Date Solved | K5: Notes / Your Insight | L5: Problem Types | M5: How to Solve | N5: Time Complexity | O5: Space Complexity
A6: ARRAY — 10 problems
A7: 1 | B7: Array | C7: 1 | D7: Two Sum | E7: Easy | F7: HashMap complement lookup | G7: =HYPERLINK("https://leetcode.com/problems/two-sum/","https://leetcode.com/problems/two-sum/") -> https://leetcode.com/problems/two-sum/ | I7: =IFERROR(VLOOKUP(C7,'📊 Problem Tracker'!$B$4:$F$1200,5,FALSE()),"") -> 0 | L7: Array, Hashing | M7: HashMap (One-Pass): Store each number's index in a map. For each element, check if (target - num) exists before inserting. | N7: O(n) | O7: O(n)
A8: 2 | B8: Array | C8: 121 | D8: Best Time to Buy and Sell Stock | E8: Easy | F8: Track running min; max profit at each step | G8: =HYPERLINK("https://leetcode.com/problems/best-time-to-buy-and-sell-stock/","https://leetcode.com/problems/best-time-to-buy-and-sell-stock/") -> https://leetcode.com/problems/best-time-to-buy-and-sell-stock/ | I8: =IFERROR(VLOOKUP(C8,'📊 Problem Tracker'!$B$4:$F$1200,5,FALSE()),"") -> 0 | L8: Array, Greedy | M8: Single Pass - Track Min Price: Track the lowest price so far and update max profit using current price minus min price. | N8: O(n) | O8: O(1)
A9: 3 | B9: Array | C9: 217 | D9: Contains Duplicate | E9: Easy | F9: HashSet membership | G9: =HYPERLINK("https://leetcode.com/problems/contains-duplicate/","https://leetcode.com/problems/contains-duplicate/") -> https://leetcode.com/problems/contains-duplicate/ | I9: =IFERROR(VLOOKUP(C9,'📊 Problem Tracker'!$B$4:$F$1200,5,FALSE()),"") -> 0 | L9: Array, Hashing | M9: HashSet Membership Check: Insert each value into a set and return true if it already exists. | N9: O(n) | O9: O(n)
A10: 4 | B10: Array | C10: 238 | D10: Product of Array Except Self | E10: Medium | F10: Prefix & suffix product passes; no division | G10: =HYPERLINK("https://leetcode.com/problems/product-of-array-except-self/","https://leetcode.com/problems/product-of-array-except-self/") -> https://leetcode.com/problems/product-of-array-except-self/ | I10: =IFERROR(VLOOKUP(C10,'📊 Problem Tracker'!$B$4:$F$1200,5,FALSE()),"") -> 0 | L10: Array, Prefix Sum | M10: Prefix and Suffix Products: Compute product of all elements left of each index, then multiply by running suffix from the right. | N10: O(n) | O10: O(1) excluding output
A11: 5 | B11: Array | C11: 53 | D11: Maximum Subarray | E11: Medium | F11: Kadane's algorithm — reset when sum < 0 | G11: =HYPERLINK("https://leetcode.com/problems/maximum-subarray/","https://leetcode.com/problems/maximum-subarray/") -> https://leetcode.com/problems/maximum-subarray/ | I11: =IFERROR(VLOOKUP(C11,'📊 Problem Tracker'!$B$4:$F$1200,5,FALSE()),"") -> 0 | L11: Array, DP | M11: Kadane's Algorithm: Track best subarray ending at current index and global best; restart when current value is better. | N11: O(n) | O11: O(1)
A12: 6 | B12: Array | C12: 152 | D12: Maximum Product Subarray | E12: Medium | F12: Track max & min (negatives flip sign) | G12: =HYPERLINK("https://leetcode.com/problems/maximum-product-subarray/","https://leetcode.com/problems/maximum-product-subarray/") -> https://leetcode.com/problems/maximum-product-subarray/ | I12: =IFERROR(VLOOKUP(C12,'📊 Problem Tracker'!$B$4:$F$1200,5,FALSE()),"") -> 0 | L12: Array, DP | M12: DP - Track Max and Min Product: Track both max and min product ending here because negatives can flip them. | N12: O(n) | O12: O(1)
A13: 7 | B13: Array | C13: 153 | D13: Find Minimum in Rotated Sorted Array | E13: Medium | F13: Binary search — which half is sorted? | G13: =HYPERLINK("https://leetcode.com/problems/find-minimum-in-rotated-sorted-array/","https://leetcode.com/problems/find-minimum-in-rotated-sorted-array/") -> https://leetcode.com/problems/find-minimum-in-rotated-sorted-array/ | I13: =IFERROR(VLOOKUP(C13,'📊 Problem Tracker'!$B$4:$F$1200,5,FALSE()),"") -> 0 | L13: Array, Binary Search | M13: Binary Search - Minimum in Rotated: Compare mid with right boundary to decide which side contains the minimum. | N13: O(log n) | O13: O(1)
A14: 8 | B14: Array | C14: 33 | D14: Search in Rotated Sorted Array | E14: Medium | F14: Binary search with rotation pivot logic | G14: =HYPERLINK("https://leetcode.com/problems/search-in-rotated-sorted-array/","https://leetcode.com/problems/search-in-rotated-sorted-array/") -> https://leetcode.com/problems/search-in-rotated-sorted-array/ | I14: =IFERROR(VLOOKUP(C14,'📊 Problem Tracker'!$B$4:$F$1200,5,FALSE()),"") -> 0 | L14: Array, Binary Search | M14: Binary Search - Identify Sorted Half: At each mid, determine which half is sorted and narrow search to the half that can contain target. | N14: O(log n) | O14: O(1)
A15: 9 | B15: Array | C15: 15 | D15: 3Sum | E15: Medium | F15: Sort + two pointers; skip duplicates carefully | G15: =HYPERLINK("https://leetcode.com/problems/3sum/","https://leetcode.com/problems/3sum/") -> https://leetcode.com/problems/3sum/ | I15: =IFERROR(VLOOKUP(C15,'📊 Problem Tracker'!$B$4:$F$1200,5,FALSE()),"") -> 0 | L15: Array, Two Pointers | M15: Sort + Two Pointers: Sort, fix one index, then use two pointers for the remaining pair while skipping duplicates. | N15: O(n²) | O15: O(1)
A16: 10 | B16: Array | C16: 11 | D16: Container With Most Water | E16: Medium | F16: Two pointers — move shorter side inward | G16: =HYPERLINK("https://leetcode.com/problems/container-with-most-water/","https://leetcode.com/problems/container-with-most-water/") -> https://leetcode.com/problems/container-with-most-water/ | I16: =IFERROR(VLOOKUP(C16,'📊 Problem Tracker'!$B$4:$F$1200,5,FALSE()),"") -> 0 | L16: Array, Two Pointers | M16: Two Pointers from Both Ends: Move the shorter height inward because it is the limiting side; update max area each step. | N16: O(n) | O16: O(1)
A17: BINARY — 5 problems
A18: 1 | B18: Binary | C18: 371 | D18: Sum of Two Integers | E18: Medium | F18: XOR for sum bits, AND<<1 for carry; iterate | G18: =HYPERLINK("https://leetcode.com/problems/sum-of-two-integers/","https://leetcode.com/problems/sum-of-two-integers/") -> https://leetcode.com/problems/sum-of-two-integers/ | I18: =IFERROR(VLOOKUP(C18,'📊 Problem Tracker'!$B$4:$F$1200,5,FALSE()),"") -> 0 | L18: Bit Manipulation, Math | M18: Bit Manipulation - XOR and AND: Use XOR for sum without carry and AND shifted left for carry; repeat until carry is zero. | N18: O(1) | O18: O(1)
A19: 2 | B19: Binary | C19: 191 | D19: Number of 1 Bits | E19: Easy | F19: n & (n-1) clears lowest set bit; count rounds | G19: =HYPERLINK("https://leetcode.com/problems/number-of-1-bits/","https://leetcode.com/problems/number-of-1-bits/") -> https://leetcode.com/problems/number-of-1-bits/ | I19: =IFERROR(VLOOKUP(C19,'📊 Problem Tracker'!$B$4:$F$1200,5,FALSE()),"") -> 0 | L19: Bit Manipulation | M19: HashMap / HashSet: Store seen values or counts for O(1) average lookups and update the answer during one pass. | N19: O(1) | O19: O(1)
A20: 3 | B20: Binary | C20: 338 | D20: Counting Bits | E20: Easy | F20: dp[i] = dp[i>>1] + (i&1) | G20: =HYPERLINK("https://leetcode.com/problems/counting-bits/","https://leetcode.com/problems/counting-bits/") -> https://leetcode.com/problems/counting-bits/ | I20: =IFERROR(VLOOKUP(C20,'📊 Problem Tracker'!$B$4:$F$1200,5,FALSE()),"") -> 0 | L20: Bit Manipulation, DP | M20: Dynamic Programming: Define the state, initialize base cases, and transition from smaller subproblems to compute the answer. | N20: O(n) | O20: O(n)
A21: 4 | B21: Binary | C21: 268 | D21: Missing Number | E21: Easy | F21: XOR all indices & values; or Gauss formula | G21: =HYPERLINK("https://leetcode.com/problems/missing-number/","https://leetcode.com/problems/missing-number/") -> https://leetcode.com/problems/missing-number/ | I21: =IFERROR(VLOOKUP(C21,'📊 Problem Tracker'!$B$4:$F$1200,5,FALSE()),"") -> 0 | L21: Array, Bit Manipulation, Math | M21: XOR All Indices and Values: XOR 0..n and every array value; matching pairs cancel and missing value remains. | N21: O(n) | O21: O(1)
A22: 5 | B22: Binary | C22: 190 | D22: Reverse Bits | E22: Easy | F22: Shift result left, OR in LSB of n, shift n right | G22: =HYPERLINK("https://leetcode.com/problems/reverse-bits/","https://leetcode.com/problems/reverse-bits/") -> https://leetcode.com/problems/reverse-bits/ | I22: =IFERROR(VLOOKUP(C22,'📊 Problem Tracker'!$B$4:$F$1200,5,FALSE()),"") -> 0 | L22: Bit Manipulation | M22: Math / Bit Manipulation: Use numeric properties or bit operations to avoid extra data structures and compute directly. | N22: O(1) | O22: O(1)
A23: DYNAMIC PROGRAMMING — 11 problems
A24: 1 | B24: Dynamic Programming | C24: 70 | D24: Climbing Stairs | E24: Easy | F24: Fibonacci DP — dp[i] = dp[i-1] + dp[i-2] | G24: =HYPERLINK("https://leetcode.com/problems/climbing-stairs/","https://leetcode.com/problems/climbing-stairs/") -> https://leetcode.com/problems/climbing-stairs/ | I24: =IFERROR(VLOOKUP(C24,'📊 Problem Tracker'!$B$4:$F$1200,5,FALSE()),"") -> 0 | L24: Array, DP, Math | M24: DP Fibonacci: Use the recurrence ways[i] = ways[i-1] + ways[i-2] with two rolling variables. | N24: O(n) | O24: O(1)
A25: 2 | B25: Dynamic Programming | C25: 322 | D25: Coin Change | E25: Medium | F25: BFS on amounts OR dp[i] = min(dp[i-coin]+1) | G25: =HYPERLINK("https://leetcode.com/problems/coin-change/","https://leetcode.com/problems/coin-change/") -> https://leetcode.com/problems/coin-change/ | I25: =IFERROR(VLOOKUP(C25,'📊 Problem Tracker'!$B$4:$F$1200,5,FALSE()),"") -> 0 | L25: Array, DP, BFS | M25: DP - Coin Change: For every amount, try each coin and take the minimum coins from dp[amount-coin]+1. | N25: O(amount · n) | O25: O(amount)
A26: 3 | B26: Dynamic Programming | C26: 300 | D26: Longest Increasing Subsequence | E26: Medium | F26: dp[i] = max(dp[j]+1) for j<i,nums[j]<nums[i]; or patience sort O(n log n) | G26: =HYPERLINK("https://leetcode.com/problems/longest-increasing-subsequence/","https://leetcode.com/problems/longest-increasing-subsequence/") -> https://leetcode.com/problems/longest-increasing-subsequence/ | I26: =IFERROR(VLOOKUP(C26,'📊 Problem Tracker'!$B$4:$F$1200,5,FALSE()),"") -> 0 | L26: Array, DP, Binary Search | M26: DP + Binary Search (Patience Sort): Maintain tails where tails[i] is the smallest tail of an increasing subsequence of length i+1. | N26: O(n log n) | O26: O(n)
A27: 4 | B27: Dynamic Programming | C27: 1143 | D27: Longest Common Subsequence | E27: Medium | F27: 2D DP — match extends diagonal; else max of left/up | G27: =HYPERLINK("https://leetcode.com/problems/longest-common-subsequence/","https://leetcode.com/problems/longest-common-subsequence/") -> https://leetcode.com/problems/longest-common-subsequence/ | I27: =IFERROR(VLOOKUP(C27,'📊 Problem Tracker'!$B$4:$F$1200,5,FALSE()),"") -> 0 | L27: String, DP | M27: 2D DP - LCS: Use dp[i][j] for longest common subsequence of prefixes; match adds one, otherwise take max neighbor. | N27: O(n) | O27: O(n)
A28: 5 | B28: Dynamic Programming | C28: 139 | D28: Word Break | E28: Medium | F28: dp[i] = any dp[j] where s[j:i] in wordSet | G28: =HYPERLINK("https://leetcode.com/problems/word-break/","https://leetcode.com/problems/word-break/") -> https://leetcode.com/problems/word-break/ | I28: =IFERROR(VLOOKUP(C28,'📊 Problem Tracker'!$B$4:$F$1200,5,FALSE()),"") -> 0 | L28: String, DP, Hashing | M28: Dynamic Programming: Define the state, initialize base cases, and transition from smaller subproblems to compute the answer. | N28: O(n²) | O28: O(n)
A29: 6 | B29: Dynamic Programming | C29: 377 | D29: Combination Sum IV | E29: Medium | F29: dp[target] = sum of dp[target-num] for all nums | G29: =HYPERLINK("https://leetcode.com/problems/combination-sum-iv/","https://leetcode.com/problems/combination-sum-iv/") -> https://leetcode.com/problems/combination-sum-iv/ | I29: =IFERROR(VLOOKUP(C29,'📊 Problem Tracker'!$B$4:$F$1200,5,FALSE()),"") -> 0 | L29: Array, DP | M29: Dynamic Programming: Define the state, initialize base cases, and transition from smaller subproblems to compute the answer. | N29: O(n * target) | O29: O(target)
A30: 7 | B30: Dynamic Programming | C30: 198 | D30: House Robber | E30: Medium | F30: dp[i] = max(dp[i-1], dp[i-2]+nums[i]) | G30: =HYPERLINK("https://leetcode.com/problems/house-robber/","https://leetcode.com/problems/house-robber/") -> https://leetcode.com/problems/house-robber/ | I30: =IFERROR(VLOOKUP(C30,'📊 Problem Tracker'!$B$4:$F$1200,5,FALSE()),"") -> 0 | L30: Array, DP | M30: DP - Rob or Skip: For each house, choose max of skipping it or robbing it plus best two positions back. | N30: O(n) | O30: O(1)
A31: 8 | B31: Dynamic Programming | C31: 213 | D31: House Robber II | E31: Medium | F31: Run House Robber on [0..n-2] and [1..n-1], take max | G31: =HYPERLINK("https://leetcode.com/problems/house-robber-ii/","https://leetcode.com/problems/house-robber-ii/") -> https://leetcode.com/problems/house-robber-ii/ | I31: =IFERROR(VLOOKUP(C31,'📊 Problem Tracker'!$B$4:$F$1200,5,FALSE()),"") -> 0 | L31: Array, DP | M31: Dynamic Programming: Define the state, initialize base cases, and transition from smaller subproblems to compute the answer. | N31: O(n) | O31: O(n)
A32: 9 | B32: Dynamic Programming | C32: 91 | D32: Decode Ways | E32: Medium | F32: dp[i] depends on 1-digit & 2-digit valid decodings | G32: =HYPERLINK("https://leetcode.com/problems/decode-ways/","https://leetcode.com/problems/decode-ways/") -> https://leetcode.com/problems/decode-ways/ | I32: =IFERROR(VLOOKUP(C32,'📊 Problem Tracker'!$B$4:$F$1200,5,FALSE()),"") -> 0 | L32: String, DP | M32: DP - Count Valid Decodings: At each index, add ways from a valid one-digit decode and a valid two-digit decode. | N32: O(n) | O32: O(1)
A33: 10 | B33: Dynamic Programming | C33: 62 | D33: Unique Paths | E33: Medium | F33: dp[i][j] = dp[i-1][j] + dp[i][j-1] | G33: =HYPERLINK("https://leetcode.com/problems/unique-paths/","https://leetcode.com/problems/unique-paths/") -> https://leetcode.com/problems/unique-paths/ | I33: =IFERROR(VLOOKUP(C33,'📊 Problem Tracker'!$B$4:$F$1200,5,FALSE()),"") -> 0 | L33: DP, Math | M33: DP - Unique Paths Grid: Use dp[i][j] = top + left, with first row and column initialized to 1. | N33: O(m·n) | O33: O(n)
A34: 11 | B34: Dynamic Programming | C34: 55 | D34: Jump Game | E34: Medium | F34: Track max reachable index greedily | G34: =HYPERLINK("https://leetcode.com/problems/jump-game/","https://leetcode.com/problems/jump-game/") -> https://leetcode.com/problems/jump-game/ | I34: =IFERROR(VLOOKUP(C34,'📊 Problem Tracker'!$B$4:$F$1200,5,FALSE()),"") -> 0 | L34: Array, Greedy | M34: Greedy - Track Max Reachable: Track the farthest reachable index and fail if the current index is beyond it. | N34: O(n) | O34: O(1)
A35: GRAPH — 8 problems
A36: 1 | B36: Graph | C36: 133 | D36: Clone Graph | E36: Medium | F36: DFS/BFS + HashMap<original, clone> | G36: =HYPERLINK("https://leetcode.com/problems/clone-graph/","https://leetcode.com/problems/clone-graph/") -> https://leetcode.com/problems/clone-graph/ | I36: =IFERROR(VLOOKUP(C36,'📊 Problem Tracker'!$B$4:$F$1200,5,FALSE()),"") -> 0 | L36: Graph, DFS, BFS, Hashing | M36: Graph Traversal: Build adjacency/state representation, use BFS for shortest path or DFS for reachability/components, and track visited states. | N36: O(V+E) | O36: O(V)
A37: 2 | B37: Graph | C37: 207 | D37: Course Schedule | E37: Medium | F37: Topological sort / cycle detection in directed graph | G37: =HYPERLINK("https://leetcode.com/problems/course-schedule/","https://leetcode.com/problems/course-schedule/") -> https://leetcode.com/problems/course-schedule/ | I37: =IFERROR(VLOOKUP(C37,'📊 Problem Tracker'!$B$4:$F$1200,5,FALSE()),"") -> 0 | L37: Graph, DFS, BFS, Topological Sort | M37: Topological Sort / Cycle Detection: Build graph and indegrees; process zero-indegree courses and verify all are processed. | N37: O(V+E) | O37: O(V+E)
A38: 3 | B38: Graph | C38: 417 | D38: Pacific Atlantic Water Flow | E38: Medium | F38: Reverse BFS from both oceans; find intersection | G38: =HYPERLINK("https://leetcode.com/problems/pacific-atlantic-water-flow/","https://leetcode.com/problems/pacific-atlantic-water-flow/") -> https://leetcode.com/problems/pacific-atlantic-water-flow/ | I38: =IFERROR(VLOOKUP(C38,'📊 Problem Tracker'!$B$4:$F$1200,5,FALSE()),"") -> 0 | L38: Array, Matrix, DFS, BFS | M38: Graph Traversal: Build adjacency/state representation, use BFS for shortest path or DFS for reachability/components, and track visited states. | N38: O(m·n) | O38: O(m·n)
A39: 4 | B39: Graph | C39: 200 | D39: Number of Islands | E39: Medium | F39: DFS/BFS flood fill; mark visited in-place | G39: =HYPERLINK("https://leetcode.com/problems/number-of-islands/","https://leetcode.com/problems/number-of-islands/") -> https://leetcode.com/problems/number-of-islands/ | I39: =IFERROR(VLOOKUP(C39,'📊 Problem Tracker'!$B$4:$F$1200,5,FALSE()),"") -> 0 | L39: Array, Matrix, DFS, BFS, Union-Find | M39: DFS/BFS Flood Fill: For each unvisited land cell, flood-fill the whole island and increment count. | N39: O(m·n) | O39: O(m·n)
A40: 5 | B40: Graph | C40: 128 | D40: Longest Consecutive Sequence | E40: Medium | F40: HashSet; only start chain when num-1 not in set | G40: =HYPERLINK("https://leetcode.com/problems/longest-consecutive-sequence/","https://leetcode.com/problems/longest-consecutive-sequence/") -> https://leetcode.com/problems/longest-consecutive-sequence/ | I40: =IFERROR(VLOOKUP(C40,'📊 Problem Tracker'!$B$4:$F$1200,5,FALSE()),"") -> 0 | L40: Array, Hashing, Union-Find | M40: HashSet - Chain Counting: Start counting only from numbers that have no predecessor and extend the consecutive chain. | N40: O(n) | O40: O(n)
A41: 6 | B41: Graph | C41: 269 | D41: Alien Dictionary | E41: Hard | F41: Topological sort on char precedence graph | G41: =HYPERLINK("https://leetcode.com/problems/alien-dictionary/","https://leetcode.com/problems/alien-dictionary/") -> https://leetcode.com/problems/alien-dictionary/ | H41: ⭐ Premium | I41: =IFERROR(VLOOKUP(C41,'📊 Problem Tracker'!$B$4:$F$1200,5,FALSE()),"") -> 0 | L41: Graph, BFS, Topological Sort | M41: Graph Traversal: Build adjacency/state representation, use BFS for shortest path or DFS for reachability/components, and track visited states. | N41: O(C) | O41: O(1)
A42: 7 | B42: Graph | C42: 261 | D42: Graph Valid Tree | E42: Medium | F42: Union-Find or BFS: n-1 edges + no cycle | G42: =HYPERLINK("https://leetcode.com/problems/graph-valid-tree/","https://leetcode.com/problems/graph-valid-tree/") -> https://leetcode.com/problems/graph-valid-tree/ | H42: ⭐ Premium | I42: =IFERROR(VLOOKUP(C42,'📊 Problem Tracker'!$B$4:$F$1200,5,FALSE()),"") -> 0 | L42: Graph, DFS, BFS, Union-Find | M42: Tree DFS/BFS: Traverse the tree recursively or level by level, returning local information needed to build the global answer. | N42: O(V+E) | O42: O(V+E)
A43: 8 | B43: Graph | C43: 323 | D43: Number of Connected Components | E43: Medium | F43: Union-Find or DFS; count components | G43: =HYPERLINK("https://leetcode.com/problems/number-of-connected-components-in-an-undirected-graph/","https://leetcode.com/problems/number-of-connected-components-in-an-undirected-graph/") -> https://leetcode.com/problems/number-of-connected-components-in-an-undirected-graph/ | H43: ⭐ Premium | I43: =IFERROR(VLOOKUP(C43,'📊 Problem Tracker'!$B$4:$F$1200,5,FALSE()),"") -> 0 | L43: Graph, DFS, Union-Find | M43: Graph Traversal: Build adjacency/state representation, use BFS for shortest path or DFS for reachability/components, and track visited states. | N43: O(V + E) | O43: O(V)
A44: INTERVAL — 5 problems
A45: 1 | B45: Interval | C45: 57 | D45: Insert Interval | E45: Medium | F45: Find overlap range, merge, rebuild list | G45: =HYPERLINK("https://leetcode.com/problems/insert-interval/","https://leetcode.com/problems/insert-interval/") -> https://leetcode.com/problems/insert-interval/ | I45: =IFERROR(VLOOKUP(C45,'📊 Problem Tracker'!$B$4:$F$1200,5,FALSE()),"") -> 0 | L45: Array, Intervals | M45: Three Phases: Before, Overlap, After: Add intervals before new interval, merge all overlaps with it, then append the rest. | N45: O(n) | O45: O(n)
A46: 2 | B46: Interval | C46: 56 | D46: Merge Intervals | E46: Medium | F46: Sort by start; merge when overlap | G46: =HYPERLINK("https://leetcode.com/problems/merge-intervals/","https://leetcode.com/problems/merge-intervals/") -> https://leetcode.com/problems/merge-intervals/ | I46: =IFERROR(VLOOKUP(C46,'📊 Problem Tracker'!$B$4:$F$1200,5,FALSE()),"") -> 0 | L46: Array, Intervals | M46: Sort by Start + Merge Overlapping: Sort intervals by start and merge into the previous interval when they overlap. | N46: O(n log n) | O46: O(n)
A47: 3 | B47: Interval | C47: 435 | D47: Non-overlapping Intervals | E47: Medium | F47: Greedy — sort by end; remove if overlaps prev end | G47: =HYPERLINK("https://leetcode.com/problems/non-overlapping-intervals/","https://leetcode.com/problems/non-overlapping-intervals/") -> https://leetcode.com/problems/non-overlapping-intervals/ | I47: =IFERROR(VLOOKUP(C47,'📊 Problem Tracker'!$B$4:$F$1200,5,FALSE()),"") -> 0 | L47: Array, Intervals, Greedy | M47: Sorting + Scan: Sort to expose ordering, then scan once or use pointers to merge, group, or find valid combinations. | N47: O(n log n) | O47: O(1)
A48: 4 | B48: Interval | C48: 252 | D48: Meeting Rooms | E48: Easy | F48: Sort by start; check if any overlap | G48: =HYPERLINK("https://leetcode.com/problems/meeting-rooms/","https://leetcode.com/problems/meeting-rooms/") -> https://leetcode.com/problems/meeting-rooms/ | H48: ⭐ Premium | I48: =IFERROR(VLOOKUP(C48,'📊 Problem Tracker'!$B$4:$F$1200,5,FALSE()),"") -> 0 | L48: Array, Intervals, Sorting | M48: Sorting + Scan: Sort to expose ordering, then scan once or use pointers to merge, group, or find valid combinations. | N48: O(n log n) | O48: O(n)
A49: 5 | B49: Interval | C49: 253 | D49: Meeting Rooms II | E49: Medium | F49: Min-heap of end times; heap size = min rooms | G49: =HYPERLINK("https://leetcode.com/problems/meeting-rooms-ii/","https://leetcode.com/problems/meeting-rooms-ii/") -> https://leetcode.com/problems/meeting-rooms-ii/ | H49: ⭐ Premium | I49: =IFERROR(VLOOKUP(C49,'📊 Problem Tracker'!$B$4:$F$1200,5,FALSE()),"") -> 0 | L49: Array, Intervals, Heap, Sorting | M49: Heap / Priority Queue: Keep the next best candidate at the heap top, pop in priority order, and push newly reachable candidates. | N49: O(n log k) | O49: O(k)
A50: LINKED LIST — 6 problems
A51: 1 | B51: Linked List | C51: 206 | D51: Reverse a Linked List | E51: Easy | F51: Iterative: prev/curr pointers; or recursive | G51: =HYPERLINK("https://leetcode.com/problems/reverse-linked-list/","https://leetcode.com/problems/reverse-linked-list/") -> https://leetcode.com/problems/reverse-linked-list/ | I51: =IFERROR(VLOOKUP(C51,'📊 Problem Tracker'!$B$4:$F$1200,5,FALSE()),"") -> 0 | L51: Linked List | M51: Iterative with Prev/Curr Pointers: Reverse links one by one using prev, curr, and next pointers. | N51: O(n) | O51: O(1)
A52: 2 | B52: Linked List | C52: 141 | D52: Detect Cycle in a Linked List | E52: Easy | F52: Fast & slow pointers (Floyd's cycle detection) | G52: =HYPERLINK("https://leetcode.com/problems/linked-list-cycle/","https://leetcode.com/problems/linked-list-cycle/") -> https://leetcode.com/problems/linked-list-cycle/ | I52: =IFERROR(VLOOKUP(C52,'📊 Problem Tracker'!$B$4:$F$1200,5,FALSE()),"") -> 0 | L52: Linked List, Two Pointers | M52: Fast and Slow Pointers: Move slow by 1 and fast by 2; if they meet, a cycle exists. | N52: O(n) | O52: O(1)
A53: 3 | B53: Linked List | C53: 21 | D53: Merge Two Sorted Lists | E53: Easy | F53: Dummy head; compare and advance pointers | G53: =HYPERLINK("https://leetcode.com/problems/merge-two-sorted-lists/","https://leetcode.com/problems/merge-two-sorted-lists/") -> https://leetcode.com/problems/merge-two-sorted-lists/ | I53: =IFERROR(VLOOKUP(C53,'📊 Problem Tracker'!$B$4:$F$1200,5,FALSE()),"") -> 0 | L53: Linked List | M53: Iterative Merge with Dummy Head: Compare list heads, attach the smaller node, advance that list, and attach the remainder. | N53: O(m + n) | O53: O(1) iterative / O(m+n) recursive
A54: 4 | B54: Linked List | C54: 23 | D54: Merge K Sorted Lists | E54: Hard | F54: Min-heap of (val, node); or divide & conquer merge | G54: =HYPERLINK("https://leetcode.com/problems/merge-k-sorted-lists/","https://leetcode.com/problems/merge-k-sorted-lists/") -> https://leetcode.com/problems/merge-k-sorted-lists/ | I54: =IFERROR(VLOOKUP(C54,'📊 Problem Tracker'!$B$4:$F$1200,5,FALSE()),"") -> 0 | L54: Linked List, Heap | M54: Min-Heap with (val, node): Push each list head into a min-heap, repeatedly pop the minimum node, and push its next node. | N54: O(N log k) | O54: O(k)
A55: 5 | B55: Linked List | C55: 19 | D55: Remove Nth Node From End Of List | E55: Medium | F55: Two pointers n+1 apart; dummy head handles edge | G55: =HYPERLINK("https://leetcode.com/problems/remove-nth-node-from-end-of-list/","https://leetcode.com/problems/remove-nth-node-from-end-of-list/") -> https://leetcode.com/problems/remove-nth-node-from-end-of-list/ | I55: =IFERROR(VLOOKUP(C55,'📊 Problem Tracker'!$B$4:$F$1200,5,FALSE()),"") -> 0 | L55: Linked List, Two Pointers | M55: Two Pointers - n+1 Gap: Use a dummy head, move fast n+1 steps ahead, then move both pointers until fast reaches the end. | N55: O(n) | O55: O(1)
A56: 6 | B56: Linked List | C56: 143 | D56: Reorder List | E56: Medium | F56: Find mid → reverse second half → merge interleaved | G56: =HYPERLINK("https://leetcode.com/problems/reorder-list/","https://leetcode.com/problems/reorder-list/") -> https://leetcode.com/problems/reorder-list/ | I56: =IFERROR(VLOOKUP(C56,'📊 Problem Tracker'!$B$4:$F$1200,5,FALSE()),"") -> 0 | L56: Linked List, Two Pointers | M56: Linked List Pointers: Use dummy nodes and careful prev/curr/next pointer updates to handle edge cases cleanly. | N56: O(n) | O56: O(1)
A57: MATRIX — 4 problems
A58: 1 | B58: Matrix | C58: 73 | D58: Set Matrix Zeroes | E58: Medium | F58: Record zero rows/cols first; then zero out | G58: =HYPERLINK("https://leetcode.com/problems/set-matrix-zeroes/","https://leetcode.com/problems/set-matrix-zeroes/") -> https://leetcode.com/problems/set-matrix-zeroes/ | I58: =IFERROR(VLOOKUP(C58,'📊 Problem Tracker'!$B$4:$F$1200,5,FALSE()),"") -> 0 | L58: Array, Matrix | M58: First Pass Record, Second Pass Zero: Use first row and first column as markers, then zero marked rows and columns. | N58: O(m·n) | O58: O(1)
A59: 2 | B59: Matrix | C59: 54 | D59: Spiral Matrix | E59: Medium | F59: Shrink boundaries (top/bottom/left/right) inward | G59: =HYPERLINK("https://leetcode.com/problems/spiral-matrix/","https://leetcode.com/problems/spiral-matrix/") -> https://leetcode.com/problems/spiral-matrix/ | I59: =IFERROR(VLOOKUP(C59,'📊 Problem Tracker'!$B$4:$F$1200,5,FALSE()),"") -> 0 | L59: Array, Matrix | M59: Boundary Shrinking: Maintain top, bottom, left, and right boundaries and traverse right, down, left, up while shrinking. | N59: O(m·n) | O59: O(1)
A60: 3 | B60: Matrix | C60: 48 | D60: Rotate Image | E60: Medium | F60: Transpose then reverse each row (in-place) | G60: =HYPERLINK("https://leetcode.com/problems/rotate-image/","https://leetcode.com/problems/rotate-image/") -> https://leetcode.com/problems/rotate-image/ | I60: =IFERROR(VLOOKUP(C60,'📊 Problem Tracker'!$B$4:$F$1200,5,FALSE()),"") -> 0 | L60: Array, Matrix | M60: Transpose then Reverse Each Row: Transpose the square matrix across the diagonal, then reverse every row. | N60: O(n²) | O60: O(1)
A61: 4 | B61: Matrix | C61: 79 | D61: Word Search | E61: Medium | F61: Backtracking DFS; mark visited in-place | G61: =HYPERLINK("https://leetcode.com/problems/word-search/","https://leetcode.com/problems/word-search/") -> https://leetcode.com/problems/word-search/ | I61: =IFERROR(VLOOKUP(C61,'📊 Problem Tracker'!$B$4:$F$1200,5,FALSE()),"") -> 0 | L61: Array, Matrix, Backtracking, DFS | M61: DFS Backtracking on Grid: DFS from each matching start cell, mark visited in-place, explore 4 directions, then restore. | N61: O(m·n·4^L) | O61: O(L)
A62: STRING — 10 problems
A63: 1 | B63: String | C63: 3 | D63: Longest Substring Without Repeating Chars | E63: Medium | F63: Sliding window + char index map | G63: =HYPERLINK("https://leetcode.com/problems/longest-substring-without-repeating-characters/","https://leetcode.com/problems/longest-substring-without-repeating-characters/") -> https://leetcode.com/problems/longest-substring-without-repeating-characters/ | I63: =IFERROR(VLOOKUP(C63,'📊 Problem Tracker'!$B$4:$F$1200,5,FALSE()),"") -> 0 | L63: String, Sliding Window, Hashing | M63: Sliding Window + HashSet: Expand right pointer. If a char repeats, shrink left until removed. Track max window size. | N63: O(n) | O63: O(min(n, charset))
A64: 2 | B64: String | C64: 424 | D64: Longest Repeating Character Replacement | E64: Medium | F64: Sliding window; window_len - max_freq <= k | G64: =HYPERLINK("https://leetcode.com/problems/longest-repeating-character-replacement/","https://leetcode.com/problems/longest-repeating-character-replacement/") -> https://leetcode.com/problems/longest-repeating-character-replacement/ | I64: =IFERROR(VLOOKUP(C64,'📊 Problem Tracker'!$B$4:$F$1200,5,FALSE()),"") -> 0 | L64: String, Sliding Window, Hashing | M64: Sliding Window - Max Freq + K Replacements: Maintain window max frequency; window is valid if size - maxFreq <= k. | N64: O(n) | O64: O(1) to O(k)
A65: 3 | B65: String | C65: 76 | D65: Minimum Window Substring | E65: Hard | F65: Sliding window with need/have counters | G65: =HYPERLINK("https://leetcode.com/problems/minimum-window-substring/","https://leetcode.com/problems/minimum-window-substring/") -> https://leetcode.com/problems/minimum-window-substring/ | I65: =IFERROR(VLOOKUP(C65,'📊 Problem Tracker'!$B$4:$F$1200,5,FALSE()),"") -> 0 | L65: String, Sliding Window, Hashing | M65: Sliding Window with Need/Have Counters: Expand right to satisfy required counts, shrink left while valid, and track the smallest window. | N65: O(n + m) | O65: O(k)
A66: 4 | B66: String | C66: 242 | D66: Valid Anagram | E66: Easy | F66: Char frequency count or sorted comparison | G66: =HYPERLINK("https://leetcode.com/problems/valid-anagram/","https://leetcode.com/problems/valid-anagram/") -> https://leetcode.com/problems/valid-anagram/ | I66: =IFERROR(VLOOKUP(C66,'📊 Problem Tracker'!$B$4:$F$1200,5,FALSE()),"") -> 0 | L66: String, Hashing | M66: Char Frequency Count: Count characters in one string and decrement using the other; all counts must end at zero. | N66: O(n) | O66: O(1)
A67: 5 | B67: String | C67: 49 | D67: Group Anagrams | E67: Medium | F67: Sort each string as key; or char-count tuple key | G67: =HYPERLINK("https://leetcode.com/problems/group-anagrams/","https://leetcode.com/problems/group-anagrams/") -> https://leetcode.com/problems/group-anagrams/ | I67: =IFERROR(VLOOKUP(C67,'📊 Problem Tracker'!$B$4:$F$1200,5,FALSE()),"") -> 0 | L67: Array, String, Hashing | M67: HashMap with Sorted String Key: Sort each word to form a key and group words with the same key. | N67: O(n·k) | O67: O(n·k)
A68: 6 | B68: String | C68: 20 | D68: Valid Parentheses | E68: Easy | F68: Stack — push open, pop and match on close | G68: =HYPERLINK("https://leetcode.com/problems/valid-parentheses/","https://leetcode.com/problems/valid-parentheses/") -> https://leetcode.com/problems/valid-parentheses/ | I68: =IFERROR(VLOOKUP(C68,'📊 Problem Tracker'!$B$4:$F$1200,5,FALSE()),"") -> 0 | L68: String, Stack | M68: Stack - Match Brackets: Push opening brackets. For closing brackets, validate against the stack top and ensure stack is empty at the end. | N68: O(n) | O68: O(n)
A69: 7 | B69: String | C69: 125 | D69: Valid Palindrome | E69: Easy | F69: Two pointers; skip non-alphanumeric | G69: =HYPERLINK("https://leetcode.com/problems/valid-palindrome/","https://leetcode.com/problems/valid-palindrome/") -> https://leetcode.com/problems/valid-palindrome/ | I69: =IFERROR(VLOOKUP(C69,'📊 Problem Tracker'!$B$4:$F$1200,5,FALSE()),"") -> 0 | L69: String, Two Pointers | M69: Two Pointers - Skip Non-Alphanumeric: Move inward while skipping non-alphanumeric chars and compare lowercase values. | N69: O(n) | O69: O(1)
A70: 8 | B70: String | C70: 5 | D70: Longest Palindromic Substring | E70: Medium | F70: Expand around center (2n-1 centers) | G70: =HYPERLINK("https://leetcode.com/problems/longest-palindromic-substring/","https://leetcode.com/problems/longest-palindromic-substring/") -> https://leetcode.com/problems/longest-palindromic-substring/ | I70: =IFERROR(VLOOKUP(C70,'📊 Problem Tracker'!$B$4:$F$1200,5,FALSE()),"") -> 0 | L70: String, DP | M70: Expand Around Center: For every character and gap center, expand outward while characters match and track the longest palindrome. | N70: O(n²) | O70: O(1)
A71: 9 | B71: String | C71: 647 | D71: Palindromic Substrings | E71: Medium | F71: Expand around center; count each valid expansion | G71: =HYPERLINK("https://leetcode.com/problems/palindromic-substrings/","https://leetcode.com/problems/palindromic-substrings/") -> https://leetcode.com/problems/palindromic-substrings/ | I71: =IFERROR(VLOOKUP(C71,'📊 Problem Tracker'!$B$4:$F$1200,5,FALSE()),"") -> 0 | L71: String, DP, Two Pointers | M71: Tree DFS/BFS: Traverse the tree recursively or level by level, returning local information needed to build the global answer. | N71: O(n²) | O71: O(1)
A72: 10 | B72: String | C72: 659 | D72: Encode and Decode Strings | E72: Medium | F72: Length-prefix encoding: '4#word' | G72: =HYPERLINK("https://leetcode.com/problems/encode-and-decode-strings/","https://leetcode.com/problems/encode-and-decode-strings/") -> https://leetcode.com/problems/encode-and-decode-strings/ | H72: ⭐ Premium | I72: =IFERROR(VLOOKUP(C72,'📊 Problem Tracker'!$B$4:$F$1200,5,FALSE()),"") -> 0 | L72: String, Design, Array | M72: String Processing: Scan characters while maintaining the needed state, counters, or parsed tokens. | N72: O(n) | O72: O(n)
A73: TREE — 14 problems
A74: 1 | B74: Tree | C74: 104 | D74: Maximum Depth of Binary Tree | E74: Easy | F74: DFS: 1 + max(left, right) | G74: =HYPERLINK("https://leetcode.com/problems/maximum-depth-of-binary-tree/","https://leetcode.com/problems/maximum-depth-of-binary-tree/") -> https://leetcode.com/problems/maximum-depth-of-binary-tree/ | I74: =IFERROR(VLOOKUP(C74,'📊 Problem Tracker'!$B$4:$F$1200,5,FALSE()),"") -> 0 | L74: Tree, DFS | M74: DFS - Return Max Depth: Return 1 plus the maximum depth of left and right subtrees. | N74: O(n) | O74: O(h)
A75: 2 | B75: Tree | C75: 100 | D75: Same Tree | E75: Easy | F75: DFS: both null=true; one null or val!=val=false | G75: =HYPERLINK("https://leetcode.com/problems/same-tree/","https://leetcode.com/problems/same-tree/") -> https://leetcode.com/problems/same-tree/ | I75: =IFERROR(VLOOKUP(C75,'📊 Problem Tracker'!$B$4:$F$1200,5,FALSE()),"") -> 0 | L75: Tree, DFS | M75: DFS - Compare Structure and Values: Recursively compare both trees for null structure, value equality, and matching children. | N75: O(n) | O75: O(h)
A76: 3 | B76: Tree | C76: 226 | D76: Invert/Flip Binary Tree | E76: Easy | F76: DFS: swap left/right at every node | G76: =HYPERLINK("https://leetcode.com/problems/invert-binary-tree/","https://leetcode.com/problems/invert-binary-tree/") -> https://leetcode.com/problems/invert-binary-tree/ | I76: =IFERROR(VLOOKUP(C76,'📊 Problem Tracker'!$B$4:$F$1200,5,FALSE()),"") -> 0 | L76: Tree, DFS | M76: DFS - Swap Left and Right: Recursively invert children by swapping left and right at every node. | N76: O(n) | O76: O(h)
A77: 4 | B77: Tree | C77: 124 | D77: Binary Tree Maximum Path Sum | E77: Hard | F77: DFS returning max gain; track global max with both branches | G77: =HYPERLINK("https://leetcode.com/problems/binary-tree-maximum-path-sum/","https://leetcode.com/problems/binary-tree-maximum-path-sum/") -> https://leetcode.com/problems/binary-tree-maximum-path-sum/ | I77: =IFERROR(VLOOKUP(C77,'📊 Problem Tracker'!$B$4:$F$1200,5,FALSE()),"") -> 0 | L77: Tree, DFS, DP | M77: DFS - Global Max with Local Gain: Return max downward gain from each node and update global path using left + node + right. | N77: O(n) | O77: O(h)
A78: 5 | B78: Tree | C78: 102 | D78: Binary Tree Level Order Traversal | E78: Medium | F78: BFS queue; snapshot queue size per level | G78: =HYPERLINK("https://leetcode.com/problems/binary-tree-level-order-traversal/","https://leetcode.com/problems/binary-tree-level-order-traversal/") -> https://leetcode.com/problems/binary-tree-level-order-traversal/ | I78: =IFERROR(VLOOKUP(C78,'📊 Problem Tracker'!$B$4:$F$1200,5,FALSE()),"") -> 0 | L78: Tree, BFS | M78: BFS with Level Size Snapshot: Use a queue and process exactly the current queue size for each level. | N78: O(n) | O78: O(n)
A79: 6 | B79: Tree | C79: 297 | D79: Serialize and Deserialize Binary Tree | E79: Hard | F79: BFS or pre-order with null markers; parse back | G79: =HYPERLINK("https://leetcode.com/problems/serialize-and-deserialize-binary-tree/","https://leetcode.com/problems/serialize-and-deserialize-binary-tree/") -> https://leetcode.com/problems/serialize-and-deserialize-binary-tree/ | I79: =IFERROR(VLOOKUP(C79,'📊 Problem Tracker'!$B$4:$F$1200,5,FALSE()),"") -> 0 | L79: Tree, BFS, DFS, Design | M79: Tree DFS/BFS: Traverse the tree recursively or level by level, returning local information needed to build the global answer. | N79: O(n) | O79: O(n)
A80: 7 | B80: Tree | C80: 572 | D80: Subtree of Another Tree | E80: Easy | F80: isSameTree at every node; O(m*n) | G80: =HYPERLINK("https://leetcode.com/problems/subtree-of-another-tree/","https://leetcode.com/problems/subtree-of-another-tree/") -> https://leetcode.com/problems/subtree-of-another-tree/ | I80: =IFERROR(VLOOKUP(C80,'📊 Problem Tracker'!$B$4:$F$1200,5,FALSE()),"") -> 0 | L80: Tree, DFS | M80: Tree DFS/BFS: Traverse the tree recursively or level by level, returning local information needed to build the global answer. | N80: O(m * n) | O80: O(h)
A81: 8 | B81: Tree | C81: 105 | D81: Construct BT from Preorder and Inorder | E81: Medium | F81: Root = preorder[0]; find in inorder to split | G81: =HYPERLINK("https://leetcode.com/problems/construct-binary-tree-from-preorder-and-inorder-traversal/","https://leetcode.com/problems/construct-binary-tree-from-preorder-and-inorder-traversal/") -> https://leetcode.com/problems/construct-binary-tree-from-preorder-and-inorder-traversal/ | I81: =IFERROR(VLOOKUP(C81,'📊 Problem Tracker'!$B$4:$F$1200,5,FALSE()),"") -> 0 | L81: Tree, DFS, Array | M81: Divide and Conquer with Inorder Index Map: Use preorder root and inorder index to split left/right subtrees recursively. | N81: O(n) | O81: O(n)
A82: 9 | B82: Tree | C82: 98 | D82: Validate Binary Search Tree | E82: Medium | F82: DFS with (min, max) bounds passed down | G82: =HYPERLINK("https://leetcode.com/problems/validate-binary-search-tree/","https://leetcode.com/problems/validate-binary-search-tree/") -> https://leetcode.com/problems/validate-binary-search-tree/ | I82: =IFERROR(VLOOKUP(C82,'📊 Problem Tracker'!$B$4:$F$1200,5,FALSE()),"") -> 0 | L82: Tree, DFS, BST | M82: DFS with Min/Max Bounds: Pass lower and upper bounds down the tree and ensure every node lies within its valid range. | N82: O(n) | O82: O(h)
A83: 10 | B83: Tree | C83: 230 | D83: Kth Smallest Element in a BST | E83: Medium | F83: In-order traversal (sorted); count down to k | G83: =HYPERLINK("https://leetcode.com/problems/kth-smallest-element-in-a-bst/","https://leetcode.com/problems/kth-smallest-element-in-a-bst/") -> https://leetcode.com/problems/kth-smallest-element-in-a-bst/ | I83: =IFERROR(VLOOKUP(C83,'📊 Problem Tracker'!$B$4:$F$1200,5,FALSE()),"") -> 0 | L83: Tree, DFS, BST | M83: Tree DFS/BFS: Traverse the tree recursively or level by level, returning local information needed to build the global answer. | N83: O(h+k) | O83: O(h)
A84: 11 | B84: Tree | C84: 235 | D84: Lowest Common Ancestor of BST | E84: Medium | F84: Navigate by BST property: both > root → go right | G84: =HYPERLINK("https://leetcode.com/problems/lowest-common-ancestor-of-a-binary-search-tree/","https://leetcode.com/problems/lowest-common-ancestor-of-a-binary-search-tree/") -> https://leetcode.com/problems/lowest-common-ancestor-of-a-binary-search-tree/ | I84: =IFERROR(VLOOKUP(C84,'📊 Problem Tracker'!$B$4:$F$1200,5,FALSE()),"") -> 0 | L84: Tree, DFS, BST | M84: Tree DFS/BFS: Traverse the tree recursively or level by level, returning local information needed to build the global answer. | N84: O(h) | O84: O(1)
A85: 12 | B85: Tree | C85: 208 | D85: Implement Trie (Prefix Tree) | E85: Medium | F85: TrieNode with children[26] + isEnd; insert/search | G85: =HYPERLINK("https://leetcode.com/problems/implement-trie-prefix-tree/","https://leetcode.com/problems/implement-trie-prefix-tree/") -> https://leetcode.com/problems/implement-trie-prefix-tree/ | I85: =IFERROR(VLOOKUP(C85,'📊 Problem Tracker'!$B$4:$F$1200,5,FALSE()),"") -> 0 | L85: Trie, Design | M85: TrieNode with children + isEnd: Insert and search by walking character nodes; mark word endings separately. | N85: O(L) per op | O85: O(total characters)
A86: 13 | B86: Tree | C86: 211 | D86: Add and Search Word | E86: Medium | F86: Trie + DFS for '.' wildcard matching | G86: =HYPERLINK("https://leetcode.com/problems/add-and-search-word-data-structure-design/","https://leetcode.com/problems/add-and-search-word-data-structure-design/") -> https://leetcode.com/problems/add-and-search-word-data-structure-design/ | I86: =IFERROR(VLOOKUP(C86,'📊 Problem Tracker'!$B$4:$F$1200,5,FALSE()),"") -> 0 | L86: Trie, DFS, Design | M86: Trie: Store words/prefixes character by character and traverse the trie to answer prefix or wildcard queries efficiently. | N86: O(L) add, O(26^wildcards) search | O86: O(total characters)
A87: 14 | B87: Tree | C87: 212 | D87: Word Search II | E87: Hard | F87: Trie of words + backtracking DFS on grid | G87: =HYPERLINK("https://leetcode.com/problems/word-search-ii/","https://leetcode.com/problems/word-search-ii/") -> https://leetcode.com/problems/word-search-ii/ | I87: =IFERROR(VLOOKUP(C87,'📊 Problem Tracker'!$B$4:$F$1200,5,FALSE()),"") -> 0 | L87: Trie, Backtracking, DFS, Matrix | M87: Backtracking: Build candidates recursively, prune invalid choices early, add a result at the base case, and undo choices before returning. | N87: O(m·n·4^L) | O87: O(total characters)
A88: HEAP — 3 problems
A89: 1 | B89: Heap | C89: 23 | D89: Merge K Sorted Lists | E89: Hard | F89: Min-heap (val, list_idx, node); poll and advance | G89: =HYPERLINK("https://leetcode.com/problems/merge-k-sorted-lists/","https://leetcode.com/problems/merge-k-sorted-lists/") -> https://leetcode.com/problems/merge-k-sorted-lists/ | I89: =IFERROR(VLOOKUP(C89,'📊 Problem Tracker'!$B$4:$F$1200,5,FALSE()),"") -> 0 | L89: Linked List, Heap | M89: Min-Heap with (val, node): Push each list head into a min-heap, repeatedly pop the minimum node, and push its next node. | N89: O(N log k) | O89: O(k)
A90: 2 | B90: Heap | C90: 347 | D90: Top K Frequent Elements | E90: Medium | F90: Bucket sort OR min-heap of size K | G90: =HYPERLINK("https://leetcode.com/problems/top-k-frequent-elements/","https://leetcode.com/problems/top-k-frequent-elements/") -> https://leetcode.com/problems/top-k-frequent-elements/ | I90: =IFERROR(VLOOKUP(C90,'📊 Problem Tracker'!$B$4:$F$1200,5,FALSE()),"") -> 0 | L90: Array, Hashing, Heap | M90: Bucket Sort / Min-Heap of Size K: Count frequencies and either bucket by frequency or maintain a heap of top k. | N90: O(n) | O90: O(n)
A91: 3 | B91: Heap | C91: 295 | D91: Find Median from Data Stream | E91: Hard | F91: Max-heap (lower half) + min-heap (upper half); balance sizes | G91: =HYPERLINK("https://leetcode.com/problems/find-median-from-data-stream/","https://leetcode.com/problems/find-median-from-data-stream/") -> https://leetcode.com/problems/find-median-from-data-stream/ | I91: =IFERROR(VLOOKUP(C91,'📊 Problem Tracker'!$B$4:$F$1200,5,FALSE()),"") -> 0 | L91: Heap, Design, Two Pointers | M91: Two Heaps - Lower and Upper Half: Maintain max-heap for lower half and min-heap for upper half, balanced by size. | N91: O(log n) add, O(1) median | O91: O(n)
A93: BLIND 75 — CATEGORY SUMMARY
A94: Category | B94: Total Problems | C94: Easy | D94: Medium | E94: Hard | F94: Premium Count | N94: O(n) | O94: O(n)
A95: Array | B95: 10 | C95: 3 | D95: 7 | E95: 0 | F95: 0 | I95: =IFERROR(VLOOKUP(C95,'📊 Problem Tracker'!$B$4:$F$1200,5,FALSE()),"") -> 0 | L95: String, Sliding Window, Hashing | M95: Sliding Window + HashSet: Expand right pointer. If a char repeats, shrink left until removed. Track max window size.
A96: Binary | B96: 5 | C96: 4 | D96: 1 | E96: 0 | F96: 0 | I96: =IFERROR(VLOOKUP(C96,'📊 Problem Tracker'!$B$4:$F$1200,5,FALSE()),"") -> 0 | L96: Array, Binary Search, Divide & Conquer | M96: Binary Search on Smaller Array: Partition the smaller array and infer the larger partition so all left-side values are <= right-side values.
A97: Dynamic Programming | B97: 11 | C97: 1 | D97: 10 | E97: 0 | F97: 0 | I97: =IFERROR(VLOOKUP(C97,'📊 Problem Tracker'!$B$4:$F$1200,5,FALSE()),"") -> 0 | L97: Array, Hashing | M97: HashMap (One-Pass): Store each number's index in a map. For each element, check if (target - num) exists before inserting.
A98: Graph | B98: 8 | C98: 0 | D98: 7 | E98: 1 | F98: 3 | I98: =IFERROR(VLOOKUP(C98,'📊 Problem Tracker'!$B$4:$F$1200,5,FALSE()),"") | M98: Pattern-Based Approach: Identify the invariant from the problem constraints, maintain it while scanning or recursing, and update the result when the invariant is satisfied.
A99: Interval | B99: 5 | C99: 1 | D99: 4 | E99: 0 | F99: 2 | I99: =IFERROR(VLOOKUP(C99,'📊 Problem Tracker'!$B$4:$F$1200,5,FALSE()),"") -> 0 | L99: Array, Hashing | M99: HashMap (One-Pass): Store each number's index in a map. For each element, check if (target - num) exists before inserting.
A100: Linked List | B100: 6 | C100: 3 | D100: 2 | E100: 1 | F100: 0 | I100: =IFERROR(VLOOKUP(C100,'📊 Problem Tracker'!$B$4:$F$1200,5,FALSE()),"") -> 0 | L100: String, Sliding Window, Hashing | M100: Sliding Window + HashSet: Expand right pointer. If a char repeats, shrink left until removed. Track max window size.
A101: Matrix | B101: 4 | C101: 0 | D101: 4 | E101: 0 | F101: 0 | I101: =IFERROR(VLOOKUP(C101,'📊 Problem Tracker'!$B$4:$F$1200,5,FALSE()),"") | M101: Pattern-Based Approach: Identify the invariant from the problem constraints, maintain it while scanning or recursing, and update the result when the invariant is satisfied.
A102: String | B102: 10 | C102: 3 | D102: 6 | E102: 1 | F102: 1 | I102: =IFERROR(VLOOKUP(C102,'📊 Problem Tracker'!$B$4:$F$1200,5,FALSE()),"") -> 0 | L102: String, Sliding Window, Hashing | M102: Sliding Window + HashSet: Expand right pointer. If a char repeats, shrink left until removed. Track max window size.
...

Sheet 🔥 Grind 169
A1: 🔥 GRIND 169 — Full Problem List with Pattern Mapping
A3: 🔍 FILTER TIPS: ▼ on Difficulty → filter Easy / Medium / Hard | ▼ on Problem Types → Text Filters → Contains → type e.g. 'Array' or 'DP' | For multiple types: Custom Filter → Contains 'Array' AND/OR Contains 'BFS'
A4: # | B4: LC # | C4: Problem Title | D4: Difficulty | E4: Primary Pattern | F4: Secondary Pattern | G4: Status | H4: ✅ Status (auto) | I4: Notes | J4: Problem Types | K4: How to Solve | L4: Time Complexity | M4: Space Complexity | N4: 🔗 LeetCode URL
A5: 1 | B5: 1 | C5: Two Sum | D5: Easy | E5: Hashing | H5: =IFERROR(VLOOKUP(B5,'📊 Problem Tracker'!$B$4:$F$1200,5,FALSE()),"") -> 0 | J5: Array, Hashing | K5: HashMap (One-Pass): Store each number's index in a map. For each element, check if (target - num) exists before inserting. | L5: O(n) | M5: O(n) | N5: =HYPERLINK("https://leetcode.com/problems/two-sum/","https://leetcode.com/problems/two-sum/") -> https://leetcode.com/problems/two-sum/
A6: 2 | B6: 2 | C6: Add Two Numbers | D6: Medium | E6: Linked List | H6: =IFERROR(VLOOKUP(B6,'📊 Problem Tracker'!$B$4:$F$1200,5,FALSE()),"") -> 0 | J6: Linked List, Math | K6: Linked List Traversal with Carry: Traverse both lists simultaneously, add digits plus carry, and handle remaining carry at the end. | L6: O(max(m, n)) | M6: O(max(m, n)) | N6: =HYPERLINK("https://leetcode.com/problems/add-two-numbers/","https://leetcode.com/problems/add-two-numbers/") -> https://leetcode.com/problems/add-two-numbers/
A7: 3 | B7: 3 | C7: Longest Substring Without Repeating Characters | D7: Medium | E7: Sliding Window | F7: Hashing | H7: =IFERROR(VLOOKUP(B7,'📊 Problem Tracker'!$B$4:$F$1200,5,FALSE()),"") -> 0 | J7: String, Sliding Window, Hashing | K7: Sliding Window + HashSet: Expand right pointer. If a char repeats, shrink left until removed. Track max window size. | L7: O(n) | M7: O(min(n, charset)) | N7: =HYPERLINK("https://leetcode.com/problems/longest-substring-without-repeating-characters/","https://leetcode.com/problems/longest-substring-without-repeating-characters/") -> https://leetcode.com/problems/longest-substring-without-repeating-characters/
A8: 4 | B8: 4 | C8: Median of Two Sorted Arrays | D8: Hard | E8: Binary Search | F8: Divide & Conquer | H8: =IFERROR(VLOOKUP(B8,'📊 Problem Tracker'!$B$4:$F$1200,5,FALSE()),"") -> 0 | J8: Array, Binary Search, Divide & Conquer | K8: Binary Search on Smaller Array: Partition the smaller array and infer the larger partition so all left-side values are <= right-side values. | L8: O(log(min(m, n))) | M8: O(1) | N8: =HYPERLINK("https://leetcode.com/problems/median-of-two-sorted-arrays/","https://leetcode.com/problems/median-of-two-sorted-arrays/") -> https://leetcode.com/problems/median-of-two-sorted-arrays/
A9: 5 | B9: 5 | C9: Longest Palindromic Substring | D9: Medium | E9: DP / Expand Around Center | H9: =IFERROR(VLOOKUP(B9,'📊 Problem Tracker'!$B$4:$F$1200,5,FALSE()),"") -> 0 | J9: String, DP | K9: Expand Around Center: For every character and gap center, expand outward while characters match and track the longest palindrome. | L9: O(n²) | M9: O(1) | N9: =HYPERLINK("https://leetcode.com/problems/longest-palindromic-substring/","https://leetcode.com/problems/longest-palindromic-substring/") -> https://leetcode.com/problems/longest-palindromic-substring/
A10: 6 | B10: 7 | C10: Reverse Integer | D10: Medium | E10: Math | H10: =IFERROR(VLOOKUP(B10,'📊 Problem Tracker'!$B$4:$F$1200,5,FALSE()),"") -> 0 | J10: Math | K10: Math with Overflow Check: Pop digits one by one and push into result after checking INT_MIN/INT_MAX overflow boundaries. | L10: O(log n) | M10: O(1) | N10: =HYPERLINK("https://leetcode.com/problems/reverse-integer/","https://leetcode.com/problems/reverse-integer/") -> https://leetcode.com/problems/reverse-integer/
A11: 7 | B11: 8 | C11: String to Integer (atoi) | D11: Medium | E11: String Parsing | H11: =IFERROR(VLOOKUP(B11,'📊 Problem Tracker'!$B$4:$F$1200,5,FALSE()),"") -> 0 | J11: String, Math | K11: State Machine String Parsing: Skip spaces, handle sign, parse digits until a non-digit, and clamp to integer bounds. | L11: O(n) | M11: O(1) | N11: =HYPERLINK("https://leetcode.com/problems/string-to-integer-atoi/","https://leetcode.com/problems/string-to-integer-atoi/") -> https://leetcode.com/problems/string-to-integer-atoi/
A12: 8 | B12: 9 | C12: Palindrome Number | D12: Easy | E12: Math | H12: =IFERROR(VLOOKUP(B12,'📊 Problem Tracker'!$B$4:$F$1200,5,FALSE()),"") -> 0 | J12: Math | K12: Revert Half the Number: Reverse the second half of the digits and compare it with the first half. | L12: O(log n) | M12: O(1) | N12: =HYPERLINK("https://leetcode.com/problems/palindrome-number/","https://leetcode.com/problems/palindrome-number/") -> https://leetcode.com/problems/palindrome-number/
A13: 9 | B13: 11 | C13: Container With Most Water | D13: Medium | E13: Two Pointers | H13: =IFERROR(VLOOKUP(B13,'📊 Problem Tracker'!$B$4:$F$1200,5,FALSE()),"") -> 0 | J13: Array, Two Pointers | K13: Two Pointers from Both Ends: Move the shorter height inward because it is the limiting side; update max area each step. | L13: O(n) | M13: O(1) | N13: =HYPERLINK("https://leetcode.com/problems/container-with-most-water/","https://leetcode.com/problems/container-with-most-water/") -> https://leetcode.com/problems/container-with-most-water/
A14: 10 | B14: 994 | C14: Rotting Oranges | D14: Medium | E14: BFS / Multi-source | H14: =IFERROR(VLOOKUP(B14,'📊 Problem Tracker'!$B$4:$F$1200,5,FALSE()),"") -> 0 | J14: Array, Matrix, BFS | K14: Multi-Source BFS from Rotten Oranges: Start BFS from all rotten oranges and spread level by level to fresh neighbors. | L14: O(m·n) | M14: O(m·n) | N14: =HYPERLINK("https://leetcode.com/problems/rotting-oranges/","https://leetcode.com/problems/rotting-oranges/") -> https://leetcode.com/problems/rotting-oranges/
A15: 11 | B15: 13 | C15: Roman to Integer | D15: Easy | E15: Math / String | H15: =IFERROR(VLOOKUP(B15,'📊 Problem Tracker'!$B$4:$F$1200,5,FALSE()),"") -> 0 | J15: String, Math | K15: Single Pass with Lookahead: Add the current Roman value unless it is smaller than the next value; then subtract it. | L15: O(n) | M15: O(1) | N15: =HYPERLINK("https://leetcode.com/problems/roman-to-integer/","https://leetcode.com/problems/roman-to-integer/") -> https://leetcode.com/problems/roman-to-integer/
A16: 12 | B16: 14 | C16: Longest Common Prefix | D16: Easy | E16: String | H16: =IFERROR(VLOOKUP(B16,'📊 Problem Tracker'!$B$4:$F$1200,5,FALSE()),"") -> 0 | J16: String | K16: Vertical Scan: Use the first string as reference and compare each character position across all strings. | L16: O(S) | M16: O(1) | N16: =HYPERLINK("https://leetcode.com/problems/longest-common-prefix/","https://leetcode.com/problems/longest-common-prefix/") -> https://leetcode.com/problems/longest-common-prefix/
A17: 13 | B17: 15 | C17: 3Sum | D17: Medium | E17: Two Pointers | F17: Sorting | H17: =IFERROR(VLOOKUP(B17,'📊 Problem Tracker'!$B$4:$F$1200,5,FALSE()),"") -> 0 | J17: Array, Two Pointers | K17: Sort + Two Pointers: Sort, fix one index, then use two pointers for the remaining pair while skipping duplicates. | L17: O(n²) | M17: O(1) | N17: =HYPERLINK("https://leetcode.com/problems/3sum/","https://leetcode.com/problems/3sum/") -> https://leetcode.com/problems/3sum/
A18: 14 | B18: 16 | C18: 3Sum Closest | D18: Medium | E18: Two Pointers | F18: Binary Search | H18: =IFERROR(VLOOKUP(B18,'📊 Problem Tracker'!$B$4:$F$1200,5,FALSE()),"") -> 0 | J18: Array, Two Pointers, Binary Search | K18: Sort + Two Pointers + Track Closest: Sort, fix one index, use two pointers, and update closest sum whenever the distance to target improves. | L18: O(n²) | M18: O(1) | N18: =HYPERLINK("https://leetcode.com/problems/3sum-closest/","https://leetcode.com/problems/3sum-closest/") -> https://leetcode.com/problems/3sum-closest/
A19: 15 | B19: 17 | C19: Letter Combinations of a Phone Number | D19: Medium | E19: Backtracking | H19: =IFERROR(VLOOKUP(B19,'📊 Problem Tracker'!$B$4:$F$1200,5,FALSE()),"") -> 0 | J19: String, Backtracking | K19: Backtracking with Phone Map: Map each digit to letters, recursively choose one letter per digit, and backtrack. | L19: O(4^n · n) | M19: O(n) | N19: =HYPERLINK("https://leetcode.com/problems/letter-combinations-of-a-phone-number/","https://leetcode.com/problems/letter-combinations-of-a-phone-number/") -> https://leetcode.com/problems/letter-combinations-of-a-phone-number/
A20: 16 | B20: 525 | C20: Contiguous Array | D20: Medium | E20: Hashing / Prefix Sum | H20: =IFERROR(VLOOKUP(B20,'📊 Problem Tracker'!$B$4:$F$1200,5,FALSE()),"") -> 0 | J20: Array, Hashing, Prefix Sum | K20: HashMap / HashSet: Store seen values or counts for O(1) average lookups and update the answer during one pass. | L20: O(n) | M20: O(n) | N20: =HYPERLINK("https://leetcode.com/problems/contiguous-array/","https://leetcode.com/problems/contiguous-array/") -> https://leetcode.com/problems/contiguous-array/
A21: 17 | B21: 19 | C21: Remove Nth Node From End of List | D21: Medium | E21: Linked List | F21: Two Pointers | H21: =IFERROR(VLOOKUP(B21,'📊 Problem Tracker'!$B$4:$F$1200,5,FALSE()),"") -> 0 | J21: Linked List, Two Pointers | K21: Two Pointers - n+1 Gap: Use a dummy head, move fast n+1 steps ahead, then move both pointers until fast reaches the end. | L21: O(n) | M21: O(1) | N21: =HYPERLINK("https://leetcode.com/problems/remove-nth-node-from-end-of-list/","https://leetcode.com/problems/remove-nth-node-from-end-of-list/") -> https://leetcode.com/problems/remove-nth-node-from-end-of-list/
A22: 18 | B22: 20 | C22: Valid Parentheses | D22: Easy | E22: Stack | H22: =IFERROR(VLOOKUP(B22,'📊 Problem Tracker'!$B$4:$F$1200,5,FALSE()),"") -> 0 | J22: String, Stack | K22: Stack - Match Brackets: Push opening brackets. For closing brackets, validate against the stack top and ensure stack is empty at the end. | L22: O(n) | M22: O(n) | N22: =HYPERLINK("https://leetcode.com/problems/valid-parentheses/","https://leetcode.com/problems/valid-parentheses/") -> https://leetcode.com/problems/valid-parentheses/
A23: 19 | B23: 21 | C23: Merge Two Sorted Lists | D23: Easy | E23: Linked List | H23: =IFERROR(VLOOKUP(B23,'📊 Problem Tracker'!$B$4:$F$1200,5,FALSE()),"") -> 0 | J23: Linked List | K23: Iterative Merge with Dummy Head: Compare list heads, attach the smaller node, advance that list, and attach the remainder. | L23: O(m + n) | M23: O(1) iterative / O(m+n) recursive | N23: =HYPERLINK("https://leetcode.com/problems/merge-two-sorted-lists/","https://leetcode.com/problems/merge-two-sorted-lists/") -> https://leetcode.com/problems/merge-two-sorted-lists/
A24: 20 | B24: 22 | C24: Generate Parentheses | D24: Medium | E24: Backtracking | H24: =IFERROR(VLOOKUP(B24,'📊 Problem Tracker'!$B$4:$F$1200,5,FALSE()),"") -> 0 | J24: String, Backtracking, Stack | K24: Backtracking with Open/Close Counts: Add '(' when open < n and ')' when close < open; collect when length reaches 2n. | L24: O(4^n / √n) | M24: O(n) | N24: =HYPERLINK("https://leetcode.com/problems/generate-parentheses/","https://leetcode.com/problems/generate-parentheses/") -> https://leetcode.com/problems/generate-parentheses/
A25: 21 | B25: 23 | C25: Merge k Sorted Lists | D25: Hard | E25: K-way Merge / Heap | H25: =IFERROR(VLOOKUP(B25,'📊 Problem Tracker'!$B$4:$F$1200,5,FALSE()),"") -> 0 | J25: Linked List, Heap | K25: Min-Heap with (val, node): Push each list head into a min-heap, repeatedly pop the minimum node, and push its next node. | L25: O(N log k) | M25: O(k) | N25: =HYPERLINK("https://leetcode.com/problems/merge-k-sorted-lists/","https://leetcode.com/problems/merge-k-sorted-lists/") -> https://leetcode.com/problems/merge-k-sorted-lists/
A26: 22 | B26: 24 | C26: Swap Nodes in Pairs | D26: Medium | E26: Linked List | H26: =IFERROR(VLOOKUP(B26,'📊 Problem Tracker'!$B$4:$F$1200,5,FALSE()),"") -> 0 | J26: Linked List | K26: Iterative Pair Swap with Prev Pointer: Use a dummy head and reverse links two nodes at a time while advancing a prev pointer. | L26: O(n) | M26: O(1) | N26: =HYPERLINK("https://leetcode.com/problems/swap-nodes-in-pairs/","https://leetcode.com/problems/swap-nodes-in-pairs/") -> https://leetcode.com/problems/swap-nodes-in-pairs/
A27: 23 | B27: 25 | C27: Reverse Nodes in k-Group | D27: Hard | E27: Linked List / In-place Reversal | H27: =IFERROR(VLOOKUP(B27,'📊 Problem Tracker'!$B$4:$F$1200,5,FALSE()),"") -> 0 | J27: Linked List | K27: Reverse K Nodes with Prev/Next Tracking: Check k nodes remain, reverse that group in-place, connect to previous and next groups. | L27: O(n) | M27: O(1) | N27: =HYPERLINK("https://leetcode.com/problems/reverse-nodes-in-k-group/","https://leetcode.com/problems/reverse-nodes-in-k-group/") -> https://leetcode.com/problems/reverse-nodes-in-k-group/
A28: 24 | B28: 542 | C28: 01 Matrix | D28: Medium | E28: BFS / Multi-source | H28: =IFERROR(VLOOKUP(B28,'📊 Problem Tracker'!$B$4:$F$1200,5,FALSE()),"") -> 0 | J28: Array, Matrix, BFS | K28: Graph Traversal: Build adjacency/state representation, use BFS for shortest path or DFS for reachability/components, and track visited states. | L28: O(m·n) | M28: O(m·n) | N28: =HYPERLINK("https://leetcode.com/problems/01-matrix/","https://leetcode.com/problems/01-matrix/") -> https://leetcode.com/problems/01-matrix/
A29: 25 | B29: 31 | C29: Next Permutation | D29: Medium | E29: Array / Two Pointers | H29: =IFERROR(VLOOKUP(B29,'📊 Problem Tracker'!$B$4:$F$1200,5,FALSE()),"") -> 0 | J29: Array, Two Pointers | K29: Find Rightmost Ascent + Swap + Reverse: Find the rightmost increasing pair, swap with the next larger digit on the right, then reverse the suffix. | L29: O(n) | M29: O(1) | N29: =HYPERLINK("https://leetcode.com/problems/next-permutation/","https://leetcode.com/problems/next-permutation/") -> https://leetcode.com/problems/next-permutation/
A30: 26 | B30: 32 | C30: Longest Valid Parentheses | D30: Hard | E30: Stack | F30: DP | H30: =IFERROR(VLOOKUP(B30,'📊 Problem Tracker'!$B$4:$F$1200,5,FALSE()),"") -> 0 | J30: String, Stack, DP | K30: Stack - Track Unmatched Indices: Use a stack of indices for unmatched parentheses; gaps between unmatched indices give valid lengths. | L30: O(n) | M30: O(n) | N30: =HYPERLINK("https://leetcode.com/problems/longest-valid-parentheses/","https://leetcode.com/problems/longest-valid-parentheses/") -> https://leetcode.com/problems/longest-valid-parentheses/
A31: 27 | B31: 33 | C31: Search in Rotated Sorted Array | D31: Medium | E31: Modified Binary Search | H31: =IFERROR(VLOOKUP(B31,'📊 Problem Tracker'!$B$4:$F$1200,5,FALSE()),"") -> 0 | J31: Array, Binary Search | K31: Binary Search - Identify Sorted Half: At each mid, determine which half is sorted and narrow search to the half that can contain target. | L31: O(log n) | M31: O(1) | N31: =HYPERLINK("https://leetcode.com/problems/search-in-rotated-sorted-array/","https://leetcode.com/problems/search-in-rotated-sorted-array/") -> https://leetcode.com/problems/search-in-rotated-sorted-array/
A32: 28 | B32: 543 | C32: Diameter of Binary Tree | D32: Easy | E32: Tree DFS | H32: =IFERROR(VLOOKUP(B32,'📊 Problem Tracker'!$B$4:$F$1200,5,FALSE()),"") -> 0 | J32: Tree, DFS | K32: Tree DFS/BFS: Traverse the tree recursively or level by level, returning local information needed to build the global answer. | L32: O(n) | M32: O(h) | N32: =HYPERLINK("https://leetcode.com/problems/diameter-of-binary-tree/","https://leetcode.com/problems/diameter-of-binary-tree/") -> https://leetcode.com/problems/diameter-of-binary-tree/
A33: 29 | B33: 36 | C33: Valid Sudoku | D33: Medium | E33: Hashing / Matrix | H33: =IFERROR(VLOOKUP(B33,'📊 Problem Tracker'!$B$4:$F$1200,5,FALSE()),"") -> 0 | J33: Array, Matrix, Hashing | K33: HashSet per Row/Col/Box: Track seen digits in row, column, and 3x3 box sets and reject duplicates. | L33: O(1) | M33: O(1) | N33: =HYPERLINK("https://leetcode.com/problems/valid-sudoku/","https://leetcode.com/problems/valid-sudoku/") -> https://leetcode.com/problems/valid-sudoku/
A34: 30 | B34: 37 | C34: Sudoku Solver | D34: Hard | E34: Backtracking | H34: =IFERROR(VLOOKUP(B34,'📊 Problem Tracker'!$B$4:$F$1200,5,FALSE()),"") -> 0 | J34: Array, Matrix, Backtracking | K34: Backtracking + Constraint Check: Find an empty cell, try digits 1-9 that satisfy row/col/box constraints, recurse, and backtrack. | L34: O(9^E) | M34: O(E) | N34: =HYPERLINK("https://leetcode.com/problems/sudoku-solver/","https://leetcode.com/problems/sudoku-solver/") -> https://leetcode.com/problems/sudoku-solver/
A35: 31 | B35: 1730 | C35: Shortest Path to Get Food | D35: Medium | E35: BFS | H35: =IFERROR(VLOOKUP(B35,'📊 Problem Tracker'!$B$4:$F$1200,5,FALSE()),"") -> 0 | J35: Array, Matrix, BFS | K35: Graph Traversal: Build adjacency/state representation, use BFS for shortest path or DFS for reachability/components, and track visited states. | L35: O(m*n) | M35: O(m*n) | N35: =HYPERLINK("https://leetcode.com/problems/shortest-path-to-get-food/","https://leetcode.com/problems/shortest-path-to-get-food/") -> https://leetcode.com/problems/shortest-path-to-get-food/
A36: 32 | B36: 39 | C36: Combination Sum | D36: Medium | E36: Backtracking | H36: =IFERROR(VLOOKUP(B36,'📊 Problem Tracker'!$B$4:$F$1200,5,FALSE()),"") -> 0 | J36: Array, Backtracking | K36: Backtracking - Allow Reuse, Prune by Sum: Sort candidates, choose candidates while remaining target allows it, and recurse with same index for reuse. | L36: O(N^(T/M)) | M36: O(T/M) | N36: =HYPERLINK("https://leetcode.com/problems/combination-sum/","https://leetcode.com/problems/combination-sum/") -> https://leetcode.com/problems/combination-sum/
A37: 33 | B37: 41 | C37: First Missing Positive | D37: Hard | E37: Cyclic Sort | H37: =IFERROR(VLOOKUP(B37,'📊 Problem Tracker'!$B$4:$F$1200,5,FALSE()),"") -> 0 | J37: Array, Hashing | K37: Cyclic Sort then Scan: Place each positive number x at index x-1 when possible, then scan for first mismatch. | L37: O(n) | M37: O(1) | N37: =HYPERLINK("https://leetcode.com/problems/first-missing-positive/","https://leetcode.com/problems/first-missing-positive/") -> https://leetcode.com/problems/first-missing-positive/
A38: 34 | B38: 42 | C38: Trapping Rain Water | D38: Hard | E38: Two Pointers | F38: Monotonic Stack | H38: =IFERROR(VLOOKUP(B38,'📊 Problem Tracker'!$B$4:$F$1200,5,FALSE()),"") -> 0 | J38: Array, Two Pointers, Monotonic Stack | K38: Two Pointers - Track Max from Each Side: Move the side with smaller max boundary and accumulate trapped water from that boundary. | L38: O(n) | M38: O(1) | N38: =HYPERLINK("https://leetcode.com/problems/trapping-rain-water/","https://leetcode.com/problems/trapping-rain-water/") -> https://leetcode.com/problems/trapping-rain-water/
A39: 35 | B39: 46 | C39: Permutations | D39: Medium | E39: Backtracking | H39: =IFERROR(VLOOKUP(B39,'📊 Problem Tracker'!$B$4:$F$1200,5,FALSE()),"") -> 0 | J39: Array, Backtracking | K39: Backtracking - Swap to Generate: Swap the current index with each candidate index, recurse, and swap back. | L39: O(n · n!) | M39: O(n) | N39: =HYPERLINK("https://leetcode.com/problems/permutations/","https://leetcode.com/problems/permutations/") -> https://leetcode.com/problems/permutations/
A40: 36 | B40: 48 | C40: Rotate Image | D40: Medium | E40: Matrix | H40: =IFERROR(VLOOKUP(B40,'📊 Problem Tracker'!$B$4:$F$1200,5,FALSE()),"") -> 0 | J40: Array, Matrix | K40: Transpose then Reverse Each Row: Transpose the square matrix across the diagonal, then reverse every row. | L40: O(n²) | M40: O(1) | N40: =HYPERLINK("https://leetcode.com/problems/rotate-image/","https://leetcode.com/problems/rotate-image/") -> https://leetcode.com/problems/rotate-image/
A41: 37 | B41: 49 | C41: Group Anagrams | D41: Medium | E41: Hashing | H41: =IFERROR(VLOOKUP(B41,'📊 Problem Tracker'!$B$4:$F$1200,5,FALSE()),"") -> 0 | J41: Array, String, Hashing | K41: HashMap with Sorted String Key: Sort each word to form a key and group words with the same key. | L41: O(n·k) | M41: O(n·k) | N41: =HYPERLINK("https://leetcode.com/problems/group-anagrams/","https://leetcode.com/problems/group-anagrams/") -> https://leetcode.com/problems/group-anagrams/
A42: 38 | B42: 50 | C42: Pow(x, n) | D42: Medium | E42: Binary Search / Fast Power | H42: =IFERROR(VLOOKUP(B42,'📊 Problem Tracker'!$B$4:$F$1200,5,FALSE()),"") -> 0 | J42: Math, Binary Search | K42: Fast Power - Exponentiation by Squaring: Recursively or iteratively square the base and halve the exponent; invert for negative exponents. | L42: O(log n) | M42: O(1) | N42: =HYPERLINK("https://leetcode.com/problems/powx-n/","https://leetcode.com/problems/powx-n/") -> https://leetcode.com/problems/powx-n/
A43: 39 | B43: 51 | C43: N-Queens | D43: Hard | E43: Backtracking | H43: =IFERROR(VLOOKUP(B43,'📊 Problem Tracker'!$B$4:$F$1200,5,FALSE()),"") -> 0 | J43: Array, Backtracking | K43: Backtracking: Build candidates recursively, prune invalid choices early, add a result at the base case, and undo choices before returning. | L43: O(branch^depth) | M43: O(depth) | N43: =HYPERLINK("https://leetcode.com/problems/n-queens/","https://leetcode.com/problems/n-queens/") -> https://leetcode.com/problems/n-queens/
A44: 40 | B44: 560 | C44: Subarray Sum Equals K | D44: Medium | E44: Hashing / Prefix Sum | H44: =IFERROR(VLOOKUP(B44,'📊 Problem Tracker'!$B$4:$F$1200,5,FALSE()),"") -> 0 | J44: Array, Hashing, Prefix Sum | K44: Prefix Sum + HashMap: Track prefix sums and count prior sums equal to currentSum-k. | L44: O(n) | M44: O(n) | N44: =HYPERLINK("https://leetcode.com/problems/subarray-sum-equals-k/","https://leetcode.com/problems/subarray-sum-equals-k/") -> https://leetcode.com/problems/subarray-sum-equals-k/
A45: 41 | B45: 53 | C45: Maximum Subarray | D45: Medium | E45: Kadane / DP | H45: =IFERROR(VLOOKUP(B45,'📊 Problem Tracker'!$B$4:$F$1200,5,FALSE()),"") -> 0 | J45: Array, DP | K45: Kadane's Algorithm: Track best subarray ending at current index and global best; restart when current value is better. | L45: O(n) | M45: O(1) | N45: =HYPERLINK("https://leetcode.com/problems/maximum-subarray/","https://leetcode.com/problems/maximum-subarray/") -> https://leetcode.com/problems/maximum-subarray/
A46: 42 | B46: 54 | C46: Spiral Matrix | D46: Medium | E46: Matrix / Simulation | H46: =IFERROR(VLOOKUP(B46,'📊 Problem Tracker'!$B$4:$F$1200,5,FALSE()),"") -> 0 | J46: Array, Matrix | K46: Boundary Shrinking: Maintain top, bottom, left, and right boundaries and traverse right, down, left, up while shrinking. | L46: O(m·n) | M46: O(1) | N46: =HYPERLINK("https://leetcode.com/problems/spiral-matrix/","https://leetcode.com/problems/spiral-matrix/") -> https://leetcode.com/problems/spiral-matrix/
A47: 43 | B47: 55 | C47: Jump Game | D47: Medium | E47: Greedy | H47: =IFERROR(VLOOKUP(B47,'📊 Problem Tracker'!$B$4:$F$1200,5,FALSE()),"") -> 0 | J47: Array, Greedy | K47: Greedy - Track Max Reachable: Track the farthest reachable index and fail if the current index is beyond it. | L47: O(n) | M47: O(1) | N47: =HYPERLINK("https://leetcode.com/problems/jump-game/","https://leetcode.com/problems/jump-game/") -> https://leetcode.com/problems/jump-game/
A48: 44 | B48: 56 | C48: Merge Intervals | D48: Medium | E48: Merge Intervals | F48: Sorting | H48: =IFERROR(VLOOKUP(B48,'📊 Problem Tracker'!$B$4:$F$1200,5,FALSE()),"") -> 0 | J48: Array, Intervals | K48: Sort by Start + Merge Overlapping: Sort intervals by start and merge into the previous interval when they overlap. | L48: O(n log n) | M48: O(n) | N48: =HYPERLINK("https://leetcode.com/problems/merge-intervals/","https://leetcode.com/problems/merge-intervals/") -> https://leetcode.com/problems/merge-intervals/
A49: 45 | B49: 57 | C49: Insert Interval | D49: Medium | E49: Merge Intervals | H49: =IFERROR(VLOOKUP(B49,'📊 Problem Tracker'!$B$4:$F$1200,5,FALSE()),"") -> 0 | J49: Array, Intervals | K49: Three Phases: Before, Overlap, After: Add intervals before new interval, merge all overlaps with it, then append the rest. | L49: O(n) | M49: O(n) | N49: =HYPERLINK("https://leetcode.com/problems/insert-interval/","https://leetcode.com/problems/insert-interval/") -> https://leetcode.com/problems/insert-interval/
A50: 46 | B50: 572 | C50: Subtree of Another Tree | D50: Easy | E50: Tree DFS | H50: =IFERROR(VLOOKUP(B50,'📊 Problem Tracker'!$B$4:$F$1200,5,FALSE()),"") -> 0 | J50: Tree, DFS | K50: Tree DFS/BFS: Traverse the tree recursively or level by level, returning local information needed to build the global answer. | L50: O(m * n) | M50: O(h) | N50: =HYPERLINK("https://leetcode.com/problems/subtree-of-another-tree/","https://leetcode.com/problems/subtree-of-another-tree/") -> https://leetcode.com/problems/subtree-of-another-tree/
A51: 47 | B51: 61 | C51: Rotate List | D51: Medium | H51: =IFERROR(VLOOKUP(B51,'📊 Problem Tracker'!$B$4:$F$1200,5,FALSE()),"") -> 0 | J51: Linked List | K51: Find New Tail at Position (n-k%len): Compute length, connect tail to head, then break at the new tail position. | L51: O(n) | M51: O(1) | N51: =HYPERLINK("https://leetcode.com/problems/rotate-list/","https://leetcode.com/problems/rotate-list/") -> https://leetcode.com/problems/rotate-list/
A52: 48 | B52: 62 | C52: Unique Paths | D52: Medium | E52: DP / 2D | H52: =IFERROR(VLOOKUP(B52,'📊 Problem Tracker'!$B$4:$F$1200,5,FALSE()),"") -> 0 | J52: DP, Math | K52: DP - Unique Paths Grid: Use dp[i][j] = top + left, with first row and column initialized to 1. | L52: O(m·n) | M52: O(n) | N52: =HYPERLINK("https://leetcode.com/problems/unique-paths/","https://leetcode.com/problems/unique-paths/") -> https://leetcode.com/problems/unique-paths/
A53: 49 | B53: 67 | C53: Add Binary | D53: Easy | E53: Bit Manipulation | H53: =IFERROR(VLOOKUP(B53,'📊 Problem Tracker'!$B$4:$F$1200,5,FALSE()),"") -> 0 | J53: String, Bit Manipulation, Math | K53: Bit Addition with Carry: Add bits from right to left with carry and build the result. | L53: O(max(m, n)) | M53: O(max(m, n)) | N53: =HYPERLINK("https://leetcode.com/problems/add-binary/","https://leetcode.com/problems/add-binary/") -> https://leetcode.com/problems/add-binary/
A54: 50 | B54: 70 | C54: Climbing Stairs | D54: Easy | E54: DP / Fibonacci | H54: =IFERROR(VLOOKUP(B54,'📊 Problem Tracker'!$B$4:$F$1200,5,FALSE()),"") -> 0 | J54: Array, DP, Math | K54: DP Fibonacci: Use the recurrence ways[i] = ways[i-1] + ways[i-2] with two rolling variables. | L54: O(n) | M54: O(1) | N54: =HYPERLINK("https://leetcode.com/problems/climbing-stairs/","https://leetcode.com/problems/climbing-stairs/") -> https://leetcode.com/problems/climbing-stairs/
A55: 51 | B55: 73 | C55: Set Matrix Zeroes | D55: Medium | E55: Matrix | H55: =IFERROR(VLOOKUP(B55,'📊 Problem Tracker'!$B$4:$F$1200,5,FALSE()),"") -> 0 | J55: Array, Matrix | K55: First Pass Record, Second Pass Zero: Use first row and first column as markers, then zero marked rows and columns. | L55: O(m·n) | M55: O(1) | N55: =HYPERLINK("https://leetcode.com/problems/set-matrix-zeroes/","https://leetcode.com/problems/set-matrix-zeroes/") -> https://leetcode.com/problems/set-matrix-zeroes/
A56: 52 | B56: 74 | C56: Search a 2D Matrix | D56: Medium | E56: Modified Binary Search | H56: =IFERROR(VLOOKUP(B56,'📊 Problem Tracker'!$B$4:$F$1200,5,FALSE()),"") -> 0 | J56: Array, Matrix, Binary Search | K56: Binary Search Treating as 1D: Map a virtual 1D index to row and column and run normal binary search. | L56: O(log(m·n)) | M56: O(1) | N56: =HYPERLINK("https://leetcode.com/problems/search-a-2d-matrix/","https://leetcode.com/problems/search-a-2d-matrix/") -> https://leetcode.com/problems/search-a-2d-matrix/
A57: 53 | B57: 75 | C57: Sort Colors | D57: Medium | E57: Two Pointers / Dutch Flag | H57: =IFERROR(VLOOKUP(B57,'📊 Problem Tracker'!$B$4:$F$1200,5,FALSE()),"") -> 0 | J57: Array, Two Pointers | K57: Dutch National Flag - 3-way Partition: Maintain low, mid, high pointers and swap 0s left, 2s right, leaving 1s in the middle. | L57: O(n) | M57: O(1) | N57: =HYPERLINK("https://leetcode.com/problems/sort-colors/","https://leetcode.com/problems/sort-colors/") -> https://leetcode.com/problems/sort-colors/
A58: 54 | B58: 76 | C58: Minimum Window Substring | D58: Hard | E58: Sliding Window | H58: =IFERROR(VLOOKUP(B58,'📊 Problem Tracker'!$B$4:$F$1200,5,FALSE()),"") -> 0 | J58: String, Sliding Window, Hashing | K58: Sliding Window with Need/Have Counters: Expand right to satisfy required counts, shrink left while valid, and track the smallest window. | L58: O(n + m) | M58: O(k) | N58: =HYPERLINK("https://leetcode.com/problems/minimum-window-substring/","https://leetcode.com/problems/minimum-window-substring/") -> https://leetcode.com/problems/minimum-window-substring/
A59: 55 | B59: 588 | C59: Design In-Memory File System | D59: Hard | E59: Trie / Design | H59: =IFERROR(VLOOKUP(B59,'📊 Problem Tracker'!$B$4:$F$1200,5,FALSE()),"") -> 0 | J59: Trie, Design | K59: Trie: Store words/prefixes character by character and traverse the trie to answer prefix or wildcard queries efficiently. | L59: O(L) per op | M59: O(total characters) | N59: =HYPERLINK("https://leetcode.com/problems/design-in-memory-file-system/","https://leetcode.com/problems/design-in-memory-file-system/") -> https://leetcode.com/problems/design-in-memory-file-system/
A60: 56 | B60: 78 | C60: Subsets | D60: Medium | E60: Backtracking / Subsets | H60: =IFERROR(VLOOKUP(B60,'📊 Problem Tracker'!$B$4:$F$1200,5,FALSE()),"") -> 0 | J60: Array, Backtracking | K60: Backtracking / Iterative Subsets: For each number, either include or exclude it; collect all generated subsets. | L60: O(n · 2^n) | M60: O(n) | N60: =HYPERLINK("https://leetcode.com/problems/subsets/","https://leetcode.com/problems/subsets/") -> https://leetcode.com/problems/subsets/
A61: 57 | B61: 79 | C61: Word Search | D61: Medium | E61: Backtracking / DFS | H61: =IFERROR(VLOOKUP(B61,'📊 Problem Tracker'!$B$4:$F$1200,5,FALSE()),"") -> 0 | J61: Array, Matrix, Backtracking, DFS | K61: DFS Backtracking on Grid: DFS from each matching start cell, mark visited in-place, explore 4 directions, then restore. | L61: O(m·n·4^L) | M61: O(L) | N61: =HYPERLINK("https://leetcode.com/problems/word-search/","https://leetcode.com/problems/word-search/") -> https://leetcode.com/problems/word-search/
A62: 58 | B62: 84 | C62: Largest Rectangle in Histogram | D62: Hard | E62: Monotonic Stack | H62: =IFERROR(VLOOKUP(B62,'📊 Problem Tracker'!$B$4:$F$1200,5,FALSE()),"") -> 0 | J62: Array, Stack, Monotonic Stack | K62: Monotonic Stack - Extend Rectangles: Maintain increasing bar indices; when a shorter bar appears, pop and compute rectangle area. | L62: O(n) | M62: O(n) | N62: =HYPERLINK("https://leetcode.com/problems/largest-rectangle-in-histogram/","https://leetcode.com/problems/largest-rectangle-in-histogram/") -> https://leetcode.com/problems/largest-rectangle-in-histogram/
A63: 59 | B63: 91 | C63: Decode Ways | D63: Medium | E63: DP | H63: =IFERROR(VLOOKUP(B63,'📊 Problem Tracker'!$B$4:$F$1200,5,FALSE()),"") -> 0 | J63: String, DP | K63: DP - Count Valid Decodings: At each index, add ways from a valid one-digit decode and a valid two-digit decode. | L63: O(n) | M63: O(1) | N63: =HYPERLINK("https://leetcode.com/problems/decode-ways/","https://leetcode.com/problems/decode-ways/") -> https://leetcode.com/problems/decode-ways/
A64: 60 | B64: 98 | C64: Validate Binary Search Tree | D64: Medium | E64: Tree DFS | F64: BST | H64: =IFERROR(VLOOKUP(B64,'📊 Problem Tracker'!$B$4:$F$1200,5,FALSE()),"") -> 0 | J64: Tree, DFS, BST | K64: DFS with Min/Max Bounds: Pass lower and upper bounds down the tree and ensure every node lies within its valid range. | L64: O(n) | M64: O(h) | N64: =HYPERLINK("https://leetcode.com/problems/validate-binary-search-tree/","https://leetcode.com/problems/validate-binary-search-tree/") -> https://leetcode.com/problems/validate-binary-search-tree/
A65: 61 | B65: 100 | C65: Same Tree | D65: Easy | E65: Tree DFS | H65: =IFERROR(VLOOKUP(B65,'📊 Problem Tracker'!$B$4:$F$1200,5,FALSE()),"") -> 0 | J65: Tree, DFS | K65: DFS - Compare Structure and Values: Recursively compare both trees for null structure, value equality, and matching children. | L65: O(n) | M65: O(h) | N65: =HYPERLINK("https://leetcode.com/problems/same-tree/","https://leetcode.com/problems/same-tree/") -> https://leetcode.com/problems/same-tree/
A66: 62 | B66: 101 | C66: Symmetric Tree | D66: Easy | E66: Tree DFS | H66: =IFERROR(VLOOKUP(B66,'📊 Problem Tracker'!$B$4:$F$1200,5,FALSE()),"") -> 0 | J66: Tree, DFS, BFS | K66: DFS - Mirror Check on Left/Right: Recursively compare left.left with right.right and left.right with right.left. | L66: O(n) | M66: O(h) | N66: =HYPERLINK("https://leetcode.com/problems/symmetric-tree/","https://leetcode.com/problems/symmetric-tree/") -> https://leetcode.com/problems/symmetric-tree/
A67: 63 | B67: 102 | C67: Binary Tree Level Order Traversal | D67: Medium | E67: Tree BFS | H67: =IFERROR(VLOOKUP(B67,'📊 Problem Tracker'!$B$4:$F$1200,5,FALSE()),"") -> 0 | J67: Tree, BFS | K67: BFS with Level Size Snapshot: Use a queue and process exactly the current queue size for each level. | L67: O(n) | M67: O(n) | N67: =HYPERLINK("https://leetcode.com/problems/binary-tree-level-order-traversal/","https://leetcode.com/problems/binary-tree-level-order-traversal/") -> https://leetcode.com/problems/binary-tree-level-order-traversal/
A68: 64 | B68: 103 | C68: Binary Tree Zigzag Level Order Traversal | D68: Medium | E68: Tree BFS | H68: =IFERROR(VLOOKUP(B68,'📊 Problem Tracker'!$B$4:$F$1200,5,FALSE()),"") -> 0 | J68: Tree, BFS, Stack | K68: Stack: Push unresolved items and resolve them when the current item matches or dominates the stack top. | L68: O(n) | M68: O(n) | N68: =HYPERLINK("https://leetcode.com/problems/binary-tree-zigzag-level-order-traversal/","https://leetcode.com/problems/binary-tree-zigzag-level-order-traversal/") -> https://leetcode.com/problems/binary-tree-zigzag-level-order-traversal/
A69: 65 | B69: 104 | C69: Maximum Depth of Binary Tree | D69: Easy | E69: Tree DFS | H69: =IFERROR(VLOOKUP(B69,'📊 Problem Tracker'!$B$4:$F$1200,5,FALSE()),"") -> 0 | J69: Tree, DFS | K69: DFS - Return Max Depth: Return 1 plus the maximum depth of left and right subtrees. | L69: O(n) | M69: O(h) | N69: =HYPERLINK("https://leetcode.com/problems/maximum-depth-of-binary-tree/","https://leetcode.com/problems/maximum-depth-of-binary-tree/") -> https://leetcode.com/problems/maximum-depth-of-binary-tree/
A70: 66 | B70: 105 | C70: Construct Binary Tree from Preorder and Inorder Traversal | D70: Medium | E70: Tree DFS | F70: Divide & Conquer | H70: =IFERROR(VLOOKUP(B70,'📊 Problem Tracker'!$B$4:$F$1200,5,FALSE()),"") -> 0 | J70: Tree, DFS, Array | K70: Divide and Conquer with Inorder Index Map: Use preorder root and inorder index to split left/right subtrees recursively. | L70: O(n) | M70: O(n) | N70: =HYPERLINK("https://leetcode.com/problems/construct-binary-tree-from-preorder-and-inorder-traversal/","https://leetcode.com/problems/construct-binary-tree-from-preorder-and-inorder-traversal/") -> https://leetcode.com/problems/construct-binary-tree-from-preorder-and-inorder-traversal/
A71: 67 | B71: 108 | C71: Convert Sorted Array to Binary Search Tree | D71: Easy | E71: Tree DFS | F71: Binary Search | H71: =IFERROR(VLOOKUP(B71,'📊 Problem Tracker'!$B$4:$F$1200,5,FALSE()),"") -> 0 | J71: Tree, Binary Search, Array | K71: Binary Search: Define a monotonic condition, check the middle value, and discard the half that cannot contain the answer. | L71: O(n) | M71: O(log n) | N71: =HYPERLINK("https://leetcode.com/problems/convert-sorted-array-to-binary-search-tree/","https://leetcode.com/problems/convert-sorted-array-to-binary-search-tree/") -> https://leetcode.com/problems/convert-sorted-array-to-binary-search-tree/
A72: 68 | B72: 621 | C72: Task Scheduler | D72: Medium | E72: Heap / Greedy | H72: =IFERROR(VLOOKUP(B72,'📊 Problem Tracker'!$B$4:$F$1200,5,FALSE()),"") -> 0 | J72: Array, Heap, Greedy | K72: Heap / Priority Queue: Keep the next best candidate at the heap top, pop in priority order, and push newly reachable candidates. | L72: O(n) | M72: O(1) | N72: =HYPERLINK("https://leetcode.com/problems/task-scheduler/","https://leetcode.com/problems/task-scheduler/") -> https://leetcode.com/problems/task-scheduler/
A73: 69 | B73: 110 | C73: Balanced Binary Tree | D73: Easy | E73: Tree DFS | H73: =IFERROR(VLOOKUP(B73,'📊 Problem Tracker'!$B$4:$F$1200,5,FALSE()),"") -> 0 | J73: Tree, DFS | K73: Tree DFS/BFS: Traverse the tree recursively or level by level, returning local information needed to build the global answer. | L73: O(n) | M73: O(h) | N73: =HYPERLINK("https://leetcode.com/problems/balanced-binary-tree/","https://leetcode.com/problems/balanced-binary-tree/") -> https://leetcode.com/problems/balanced-binary-tree/
A74: 70 | B74: 113 | C74: Path Sum II | D74: Medium | E74: Tree DFS | F74: Backtracking | H74: =IFERROR(VLOOKUP(B74,'📊 Problem Tracker'!$B$4:$F$1200,5,FALSE()),"") -> 0 | J74: Tree, DFS, Backtracking | K74: Backtracking: Build candidates recursively, prune invalid choices early, add a result at the base case, and undo choices before returning. | L74: O(n²) | M74: O(h) | N74: =HYPERLINK("https://leetcode.com/problems/path-sum-ii/","https://leetcode.com/problems/path-sum-ii/") -> https://leetcode.com/problems/path-sum-ii/
A75: 71 | B75: 1197 | C75: Minimum Knight Moves | D75: Medium | E75: BFS | H75: =IFERROR(VLOOKUP(B75,'📊 Problem Tracker'!$B$4:$F$1200,5,FALSE()),"") -> 0 | J75: Graph, BFS | K75: Graph Traversal: Build adjacency/state representation, use BFS for shortest path or DFS for reachability/components, and track visited states. | L75: O(V+E) | M75: O(V+E) | N75: =HYPERLINK("https://leetcode.com/problems/minimum-knight-moves/","https://leetcode.com/problems/minimum-knight-moves/") -> https://leetcode.com/problems/minimum-knight-moves/
A76: 72 | B76: 632 | C76: Smallest Range Covering Elements from K Lists | D76: Hard | E76: K-way Merge / Heap | F76: Sliding Window | H76: =IFERROR(VLOOKUP(B76,'📊 Problem Tracker'!$B$4:$F$1200,5,FALSE()),"") -> 0 | J76: Array, Heap, Sliding Window | K76: Sliding Window: Expand the right pointer to include new items, shrink from the left when the constraint is violated, and track the best valid window. | L76: O(n) | M76: O(1) | N76: =HYPERLINK("https://leetcode.com/problems/smallest-range-covering-elements-from-k-lists/","https://leetcode.com/problems/smallest-range-covering-elements-from-k-lists/") -> https://leetcode.com/problems/smallest-range-covering-elements-from-k-lists/
A77: 73 | B77: 121 | C77: Best Time to Buy and Sell Stock | D77: Easy | E77: Array / Greedy | H77: =IFERROR(VLOOKUP(B77,'📊 Problem Tracker'!$B$4:$F$1200,5,FALSE()),"") -> 0 | J77: Array, Greedy | K77: Single Pass - Track Min Price: Track the lowest price so far and update max profit using current price minus min price. | L77: O(n) | M77: O(1) | N77: =HYPERLINK("https://leetcode.com/problems/best-time-to-buy-and-sell-stock/","https://leetcode.com/problems/best-time-to-buy-and-sell-stock/") -> https://leetcode.com/problems/best-time-to-buy-and-sell-stock/
A78: 74 | B78: 124 | C78: Binary Tree Maximum Path Sum | D78: Hard | E78: Tree DFS | H78: =IFERROR(VLOOKUP(B78,'📊 Problem Tracker'!$B$4:$F$1200,5,FALSE()),"") -> 0 | J78: Tree, DFS, DP | K78: DFS - Global Max with Local Gain: Return max downward gain from each node and update global path using left + node + right. | L78: O(n) | M78: O(h) | N78: =HYPERLINK("https://leetcode.com/problems/binary-tree-maximum-path-sum/","https://leetcode.com/problems/binary-tree-maximum-path-sum/") -> https://leetcode.com/problems/binary-tree-maximum-path-sum/
A79: 75 | B79: 125 | C79: Valid Palindrome | D79: Easy | E79: Two Pointers | H79: =IFERROR(VLOOKUP(B79,'📊 Problem Tracker'!$B$4:$F$1200,5,FALSE()),"") -> 0 | J79: String, Two Pointers | K79: Two Pointers - Skip Non-Alphanumeric: Move inward while skipping non-alphanumeric chars and compare lowercase values. | L79: O(n) | M79: O(1) | N79: =HYPERLINK("https://leetcode.com/problems/valid-palindrome/","https://leetcode.com/problems/valid-palindrome/") -> https://leetcode.com/problems/valid-palindrome/
A80: 76 | B80: 127 | C80: Word Ladder | D80: Hard | E80: BFS | H80: =IFERROR(VLOOKUP(B80,'📊 Problem Tracker'!$B$4:$F$1200,5,FALSE()),"") -> 0 | J80: String, BFS, Hashing | K80: Graph Traversal: Build adjacency/state representation, use BFS for shortest path or DFS for reachability/components, and track visited states. | L80: O(N·L²) | M80: O(N·L) | N80: =HYPERLINK("https://leetcode.com/problems/word-ladder/","https://leetcode.com/problems/word-ladder/") -> https://leetcode.com/problems/word-ladder/
A81: 77 | B81: 128 | C81: Longest Consecutive Sequence | D81: Medium | E81: Hashing | F81: Union-Find | H81: =IFERROR(VLOOKUP(B81,'📊 Problem Tracker'!$B$4:$F$1200,5,FALSE()),"") -> 0 | J81: Array, Hashing, Union-Find | K81: HashSet - Chain Counting: Start counting only from numbers that have no predecessor and extend the consecutive chain. | L81: O(n) | M81: O(n) | N81: =HYPERLINK("https://leetcode.com/problems/longest-consecutive-sequence/","https://leetcode.com/problems/longest-consecutive-sequence/") -> https://leetcode.com/problems/longest-consecutive-sequence/
A82: 78 | B82: 133 | C82: Clone Graph | D82: Medium | E82: Graph DFS/BFS | F82: Hashing | H82: =IFERROR(VLOOKUP(B82,'📊 Problem Tracker'!$B$4:$F$1200,5,FALSE()),"") -> 0 | J82: Graph, DFS, BFS, Hashing | K82: Graph Traversal: Build adjacency/state representation, use BFS for shortest path or DFS for reachability/components, and track visited states. | L82: O(V+E) | M82: O(V) | N82: =HYPERLINK("https://leetcode.com/problems/clone-graph/","https://leetcode.com/problems/clone-graph/") -> https://leetcode.com/problems/clone-graph/
A83: 79 | B83: 134 | C83: Gas Station | D83: Medium | E83: Greedy | H83: =IFERROR(VLOOKUP(B83,'📊 Problem Tracker'!$B$4:$F$1200,5,FALSE()),"") -> 0 | J83: Array, Greedy | K83: Array Scan: Iterate through the array while maintaining running state and update the result in-place when possible. | L83: O(n) | M83: O(1) | N83: =HYPERLINK("https://leetcode.com/problems/gas-station/","https://leetcode.com/problems/gas-station/") -> https://leetcode.com/problems/gas-station/
A84: 80 | B84: 136 | C84: Single Number | D84: Easy | E84: Bit Manipulation / XOR | H84: =IFERROR(VLOOKUP(B84,'📊 Problem Tracker'!$B$4:$F$1200,5,FALSE()),"") -> 0 | J84: Array, Bit Manipulation | K84: XOR All Elements: XOR all values so duplicate pairs cancel and the single number remains. | L84: O(n) | M84: O(1) | N84: =HYPERLINK("https://leetcode.com/problems/single-number/","https://leetcode.com/problems/single-number/") -> https://leetcode.com/problems/single-number/
A85: 81 | B85: 139 | C85: Word Break | D85: Medium | E85: DP | H85: =IFERROR(VLOOKUP(B85,'📊 Problem Tracker'!$B$4:$F$1200,5,FALSE()),"") -> 0 | J85: String, DP, Hashing | K85: Dynamic Programming: Define the state, initialize base cases, and transition from smaller subproblems to compute the answer. | L85: O(n²) | M85: O(n) | N85: =HYPERLINK("https://leetcode.com/problems/word-break/","https://leetcode.com/problems/word-break/") -> https://leetcode.com/problems/word-break/
A86: 82 | B86: 141 | C86: Linked List Cycle | D86: Easy | E86: Fast & Slow Pointers | H86: =IFERROR(VLOOKUP(B86,'📊 Problem Tracker'!$B$4:$F$1200,5,FALSE()),"") -> 0 | J86: Linked List, Two Pointers | K86: Fast and Slow Pointers: Move slow by 1 and fast by 2; if they meet, a cycle exists. | L86: O(n) | M86: O(1) | N86: =HYPERLINK("https://leetcode.com/problems/linked-list-cycle/","https://leetcode.com/problems/linked-list-cycle/") -> https://leetcode.com/problems/linked-list-cycle/
A87: 83 | B87: 143 | C87: Reorder List | D87: Medium | E87: Linked List / In-place Reversal | H87: =IFERROR(VLOOKUP(B87,'📊 Problem Tracker'!$B$4:$F$1200,5,FALSE()),"") -> 0 | J87: Linked List, Two Pointers | K87: Two Pointers: Maintain two indices and move the pointer that helps satisfy the condition while updating the answer. | L87: O(n) | M87: O(1) | N87: =HYPERLINK("https://leetcode.com/problems/reorder-list/","https://leetcode.com/problems/reorder-list/") -> https://leetcode.com/problems/reorder-list/
A88: 84 | B88: 146 | C88: LRU Cache | D88: Medium | E88: Hashing | F88: Linked List | H88: =IFERROR(VLOOKUP(B88,'📊 Problem Tracker'!$B$4:$F$1200,5,FALSE()),"") -> 0 | J88: Design, Linked List, Hashing | K88: HashMap + Doubly Linked List: Use a map for O(1) access and a DLL to maintain recency for eviction. | L88: O(1) get/put | M88: O(capacity) | N88: =HYPERLINK("https://leetcode.com/problems/lru-cache/","https://leetcode.com/problems/lru-cache/") -> https://leetcode.com/problems/lru-cache/
A89: 85 | B89: 658 | C89: Find K Closest Elements | D89: Medium | E89: Binary Search | F89: Sliding Window | H89: =IFERROR(VLOOKUP(B89,'📊 Problem Tracker'!$B$4:$F$1200,5,FALSE()),"") -> 0 | J89: Array, Binary Search, Sliding Window | K89: Sliding Window: Expand the right pointer to include new items, shrink from the left when the constraint is violated, and track the best valid window. | L89: O(log n + k) | M89: O(1) | N89: =HYPERLINK("https://leetcode.com/problems/find-k-closest-elements/","https://leetcode.com/problems/find-k-closest-elements/") -> https://leetcode.com/problems/find-k-closest-elements/
A90: 86 | B90: 148 | C90: Sort List | D90: Medium | E90: Merge Sort / Linked List | H90: =IFERROR(VLOOKUP(B90,'📊 Problem Tracker'!$B$4:$F$1200,5,FALSE()),"") -> 0 | J90: Linked List, Sorting | K90: Linked List Pointers: Use dummy nodes and careful prev/curr/next pointer updates to handle edge cases cleanly. | L90: O(n log n) | M90: O(log n) | N90: =HYPERLINK("https://leetcode.com/problems/sort-list/","https://leetcode.com/problems/sort-list/") -> https://leetcode.com/problems/sort-list/
A91: 87 | B91: 150 | C91: Evaluate Reverse Polish Notation | D91: Medium | E91: Stack | H91: =IFERROR(VLOOKUP(B91,'📊 Problem Tracker'!$B$4:$F$1200,5,FALSE()),"") -> 0 | J91: Array, Stack, Math | K91: Stack - Evaluate RPN: Push numbers; on an operator, pop two operands, compute, and push the result. | L91: O(n) | M91: O(n) | N91: =HYPERLINK("https://leetcode.com/problems/evaluate-reverse-polish-notation/","https://leetcode.com/problems/evaluate-reverse-polish-notation/") -> https://leetcode.com/problems/evaluate-reverse-polish-notation/
A92: 88 | B92: 662 | C92: Maximum Width of Binary Tree | D92: Medium | E92: Tree BFS | H92: =IFERROR(VLOOKUP(B92,'📊 Problem Tracker'!$B$4:$F$1200,5,FALSE()),"") -> 0 | J92: Tree, BFS | K92: Tree DFS/BFS: Traverse the tree recursively or level by level, returning local information needed to build the global answer. | L92: O(n) | M92: O(n) | N92: =HYPERLINK("https://leetcode.com/problems/maximum-width-of-binary-tree/","https://leetcode.com/problems/maximum-width-of-binary-tree/") -> https://leetcode.com/problems/maximum-width-of-binary-tree/
A93: 89 | B93: 152 | C93: Maximum Product Subarray | D93: Medium | E93: DP | H93: =IFERROR(VLOOKUP(B93,'📊 Problem Tracker'!$B$4:$F$1200,5,FALSE()),"") -> 0 | J93: Array, DP | K93: DP - Track Max and Min Product: Track both max and min product ending here because negatives can flip them. | L93: O(n) | M93: O(1) | N93: =HYPERLINK("https://leetcode.com/problems/maximum-product-subarray/","https://leetcode.com/problems/maximum-product-subarray/") -> https://leetcode.com/problems/maximum-product-subarray/
A94: 90 | B94: 153 | C94: Find Minimum in Rotated Sorted Array | D94: Medium | E94: Modified Binary Search | H94: =IFERROR(VLOOKUP(B94,'📊 Problem Tracker'!$B$4:$F$1200,5,FALSE()),"") -> 0 | J94: Array, Binary Search | K94: Binary Search - Minimum in Rotated: Compare mid with right boundary to decide which side contains the minimum. | L94: O(log n) | M94: O(1) | N94: =HYPERLINK("https://leetcode.com/problems/find-minimum-in-rotated-sorted-array/","https://leetcode.com/problems/find-minimum-in-rotated-sorted-array/") -> https://leetcode.com/problems/find-minimum-in-rotated-sorted-array/
A95: 91 | B95: 155 | C95: Min Stack | D95: Medium | E95: Stack | H95: =IFERROR(VLOOKUP(B95,'📊 Problem Tracker'!$B$4:$F$1200,5,FALSE()),"") -> 0 | J95: Stack, Design | K95: Stack + Auxiliary Min Stack: Maintain a normal stack and a min stack so getMin reads the current minimum in O(1). | L95: O(1) per op | M95: O(n) | N95: =HYPERLINK("https://leetcode.com/problems/min-stack/","https://leetcode.com/problems/min-stack/") -> https://leetcode.com/problems/min-stack/
A96: 92 | B96: 169 | C96: Majority Element | D96: Easy | E96: Array / Boyer-Moore | H96: =IFERROR(VLOOKUP(B96,'📊 Problem Tracker'!$B$4:$F$1200,5,FALSE()),"") -> 0 | J96: Array | K96: Boyer-Moore Voting Algorithm: Maintain a candidate and count; majority survives cancellations, then candidate is answer. | L96: O(n) | M96: O(1) | N96: =HYPERLINK("https://leetcode.com/problems/majority-element/","https://leetcode.com/problems/majority-element/") -> https://leetcode.com/problems/majority-element/
A97: 93 | B97: 179 | C97: Largest Number | D97: Medium | E97: Sorting / Custom Comparator | H97: =IFERROR(VLOOKUP(B97,'📊 Problem Tracker'!$B$4:$F$1200,5,FALSE()),"") -> 0 | J97: Array, String, Sorting | K97: Sorting + Scan: Sort to expose ordering, then scan once or use pointers to merge, group, or find valid combinations. | L97: O(n log n · k) | M97: O(n·k) | N97: =HYPERLINK("https://leetcode.com/problems/largest-number/","https://leetcode.com/problems/largest-number/") -> https://leetcode.com/problems/largest-number/
A98: 94 | B98: 692 | C98: Top K Frequent Words | D98: Medium | E98: Top-K / Heap | H98: =IFERROR(VLOOKUP(B98,'📊 Problem Tracker'!$B$4:$F$1200,5,FALSE()),"") -> 0 | J98: String, Heap, Hashing | K98: Heap / Priority Queue: Keep the next best candidate at the heap top, pop in priority order, and push newly reachable candidates. | L98: O(n) | M98: O(n) | N98: =HYPERLINK("https://leetcode.com/problems/top-k-frequent-words/","https://leetcode.com/problems/top-k-frequent-words/") -> https://leetcode.com/problems/top-k-frequent-words/
A99: 95 | B99: 189 | C99: Rotate Array | D99: Medium | E99: Array / Two Pointers | H99: =IFERROR(VLOOKUP(B99,'📊 Problem Tracker'!$B$4:$F$1200,5,FALSE()),"") -> 0 | J99: Array, Two Pointers, Math | K99: Two Pointers: Maintain two indices and move the pointer that helps satisfy the condition while updating the answer. | L99: O(n) | M99: O(1) | N99: =HYPERLINK("https://leetcode.com/problems/rotate-array/","https://leetcode.com/problems/rotate-array/") -> https://leetcode.com/problems/rotate-array/
A100: 96 | B100: 190 | C100: Reverse Bits | D100: Easy | E100: Bit Manipulation | H100: =IFERROR(VLOOKUP(B100,'📊 Problem Tracker'!$B$4:$F$1200,5,FALSE()),"") -> 0 | J100: Bit Manipulation | K100: Math / Bit Manipulation: Use numeric properties or bit operations to avoid extra data structures and compute directly. | L100: O(1) | M100: O(1) | N100: =HYPERLINK("https://leetcode.com/problems/reverse-bits/","https://leetcode.com/problems/reverse-bits/") -> https://leetcode.com/problems/reverse-bits/
A101: 97 | B101: 191 | C101: Number of 1 Bits | D101: Easy | E101: Bit Manipulation | H101: =IFERROR(VLOOKUP(B101,'📊 Problem Tracker'!$B$4:$F$1200,5,FALSE()),"") -> 0 | J101: Bit Manipulation | K101: Math / Bit Manipulation: Use numeric properties or bit operations to avoid extra data structures and compute directly. | L101: O(1) | M101: O(1) | N101: =HYPERLINK("https://leetcode.com/problems/number-of-1-bits/","https://leetcode.com/problems/number-of-1-bits/") -> https://leetcode.com/problems/number-of-1-bits/
...

Sheet ⚡ Grind 75
A1: ⚡ GRIND 75 — Essential 75 Problems with Pattern Mapping
A3: 🔍 FILTER TIPS: ▼ on Difficulty → filter Easy / Medium / Hard | ▼ on Problem Types → Text Filters → Contains → type e.g. 'Array' or 'DP' | For multiple types: Custom Filter → Contains 'Array' AND/OR Contains 'BFS'
A4: # | B4: LC # | C4: Problem Title | D4: Difficulty | E4: Primary Pattern | F4: Secondary Pattern | G4: Status | H4: ✅ Status (auto) | I4: Notes | J4: Problem Types | K4: How to Solve | L4: Time Complexity | M4: Space Complexity | N4: 🔗 LeetCode URL
A5: 1 | B5: 1 | C5: Two Sum | D5: Easy | E5: Hashing | H5: =IFERROR(VLOOKUP(B5,'📊 Problem Tracker'!$B$4:$F$1200,5,FALSE()),"") -> 0 | J5: Array, Hashing | K5: HashMap (One-Pass): Store each number's index in a map. For each element, check if (target - num) exists before inserting. | L5: O(n) | M5: O(n) | N5: =HYPERLINK("https://leetcode.com/problems/two-sum/","https://leetcode.com/problems/two-sum/") -> https://leetcode.com/problems/two-sum/
A6: 2 | B6: 3 | C6: Longest Substring Without Repeating Characters | D6: Medium | E6: Sliding Window | F6: Hashing | H6: =IFERROR(VLOOKUP(B6,'📊 Problem Tracker'!$B$4:$F$1200,5,FALSE()),"") -> 0 | J6: String, Sliding Window, Hashing | K6: Sliding Window + HashSet: Expand right pointer. If a char repeats, shrink left until removed. Track max window size. | L6: O(n) | M6: O(min(n, charset)) | N6: =HYPERLINK("https://leetcode.com/problems/longest-substring-without-repeating-characters/","https://leetcode.com/problems/longest-substring-without-repeating-characters/") -> https://leetcode.com/problems/longest-substring-without-repeating-characters/
A7: 3 | B7: 5 | C7: Longest Palindromic Substring | D7: Medium | E7: DP / Expand Around Center | H7: =IFERROR(VLOOKUP(B7,'📊 Problem Tracker'!$B$4:$F$1200,5,FALSE()),"") -> 0 | J7: String, DP | K7: Expand Around Center: For every character and gap center, expand outward while characters match and track the longest palindrome. | L7: O(n²) | M7: O(1) | N7: =HYPERLINK("https://leetcode.com/problems/longest-palindromic-substring/","https://leetcode.com/problems/longest-palindromic-substring/") -> https://leetcode.com/problems/longest-palindromic-substring/
A8: 4 | B8: 133 | C8: Clone Graph | D8: Medium | E8: Graph DFS/BFS | F8: Hashing | H8: =IFERROR(VLOOKUP(B8,'📊 Problem Tracker'!$B$4:$F$1200,5,FALSE()),"") -> 0 | J8: Graph, DFS, BFS, Hashing | K8: Graph Traversal: Build adjacency/state representation, use BFS for shortest path or DFS for reachability/components, and track visited states. | L8: O(V+E) | M8: O(V) | N8: =HYPERLINK("https://leetcode.com/problems/clone-graph/","https://leetcode.com/problems/clone-graph/") -> https://leetcode.com/problems/clone-graph/
A9: 5 | B9: 383 | C9: Ransom Note | D9: Easy | E9: Hashing | H9: =IFERROR(VLOOKUP(B9,'📊 Problem Tracker'!$B$4:$F$1200,5,FALSE()),"") -> 0 | J9: String, Hashing | K9: Frequency Count: Count magazine characters, decrement for ransom note, and fail if any count becomes negative. | L9: O(m+n) | M9: O(1) | N9: =HYPERLINK("https://leetcode.com/problems/ransom-note/","https://leetcode.com/problems/ransom-note/") -> https://leetcode.com/problems/ransom-note/
A10: 6 | B10: 8 | C10: String to Integer (atoi) | D10: Medium | E10: String Parsing | H10: =IFERROR(VLOOKUP(B10,'📊 Problem Tracker'!$B$4:$F$1200,5,FALSE()),"") -> 0 | J10: String, Math | K10: State Machine String Parsing: Skip spaces, handle sign, parse digits until a non-digit, and clamp to integer bounds. | L10: O(n) | M10: O(1) | N10: =HYPERLINK("https://leetcode.com/problems/string-to-integer-atoi/","https://leetcode.com/problems/string-to-integer-atoi/") -> https://leetcode.com/problems/string-to-integer-atoi/
A11: 7 | B11: 11 | C11: Container With Most Water | D11: Medium | E11: Two Pointers | H11: =IFERROR(VLOOKUP(B11,'📊 Problem Tracker'!$B$4:$F$1200,5,FALSE()),"") -> 0 | J11: Array, Two Pointers | K11: Two Pointers from Both Ends: Move the shorter height inward because it is the limiting side; update max area each step. | L11: O(n) | M11: O(1) | N11: =HYPERLINK("https://leetcode.com/problems/container-with-most-water/","https://leetcode.com/problems/container-with-most-water/") -> https://leetcode.com/problems/container-with-most-water/
A12: 8 | B12: 139 | C12: Word Break | D12: Medium | E12: DP | H12: =IFERROR(VLOOKUP(B12,'📊 Problem Tracker'!$B$4:$F$1200,5,FALSE()),"") -> 0 | J12: String, DP, Hashing | K12: Dynamic Programming: Define the state, initialize base cases, and transition from smaller subproblems to compute the answer. | L12: O(n²) | M12: O(n) | N12: =HYPERLINK("https://leetcode.com/problems/word-break/","https://leetcode.com/problems/word-break/") -> https://leetcode.com/problems/word-break/
A13: 9 | B13: 141 | C13: Linked List Cycle | D13: Easy | E13: Fast & Slow Pointers | H13: =IFERROR(VLOOKUP(B13,'📊 Problem Tracker'!$B$4:$F$1200,5,FALSE()),"") -> 0 | J13: Linked List, Two Pointers | K13: Fast and Slow Pointers: Move slow by 1 and fast by 2; if they meet, a cycle exists. | L13: O(n) | M13: O(1) | N13: =HYPERLINK("https://leetcode.com/problems/linked-list-cycle/","https://leetcode.com/problems/linked-list-cycle/") -> https://leetcode.com/problems/linked-list-cycle/
A14: 10 | B14: 876 | C14: Middle of the Linked List | D14: Easy | E14: Fast & Slow Pointers | H14: =IFERROR(VLOOKUP(B14,'📊 Problem Tracker'!$B$4:$F$1200,5,FALSE()),"") -> 0 | J14: Linked List, Two Pointers | K14: Two Pointers: Maintain two indices and move the pointer that helps satisfy the condition while updating the answer. | L14: O(n) | M14: O(1) | N14: =HYPERLINK("https://leetcode.com/problems/middle-of-the-linked-list/","https://leetcode.com/problems/middle-of-the-linked-list/") -> https://leetcode.com/problems/middle-of-the-linked-list/
A15: 11 | B15: 15 | C15: 3Sum | D15: Medium | E15: Two Pointers | F15: Sorting | H15: =IFERROR(VLOOKUP(B15,'📊 Problem Tracker'!$B$4:$F$1200,5,FALSE()),"") -> 0 | J15: Array, Two Pointers | K15: Sort + Two Pointers: Sort, fix one index, then use two pointers for the remaining pair while skipping duplicates. | L15: O(n²) | M15: O(1) | N15: =HYPERLINK("https://leetcode.com/problems/3sum/","https://leetcode.com/problems/3sum/") -> https://leetcode.com/problems/3sum/
A16: 12 | B16: 994 | C16: Rotting Oranges | D16: Medium | E16: BFS / Multi-source | H16: =IFERROR(VLOOKUP(B16,'📊 Problem Tracker'!$B$4:$F$1200,5,FALSE()),"") -> 0 | J16: Array, Matrix, BFS | K16: Multi-Source BFS from Rotten Oranges: Start BFS from all rotten oranges and spread level by level to fresh neighbors. | L16: O(m·n) | M16: O(m·n) | N16: =HYPERLINK("https://leetcode.com/problems/rotting-oranges/","https://leetcode.com/problems/rotting-oranges/") -> https://leetcode.com/problems/rotting-oranges/
A17: 13 | B17: 17 | C17: Letter Combinations of a Phone Number | D17: Medium | E17: Backtracking | H17: =IFERROR(VLOOKUP(B17,'📊 Problem Tracker'!$B$4:$F$1200,5,FALSE()),"") -> 0 | J17: String, Backtracking | K17: Backtracking with Phone Map: Map each digit to letters, recursively choose one letter per digit, and backtrack. | L17: O(4^n · n) | M17: O(n) | N17: =HYPERLINK("https://leetcode.com/problems/letter-combinations-of-a-phone-number/","https://leetcode.com/problems/letter-combinations-of-a-phone-number/") -> https://leetcode.com/problems/letter-combinations-of-a-phone-number/
A18: 14 | B18: 146 | C18: LRU Cache | D18: Medium | E18: Hashing | F18: Linked List | H18: =IFERROR(VLOOKUP(B18,'📊 Problem Tracker'!$B$4:$F$1200,5,FALSE()),"") -> 0 | J18: Design, Linked List, Hashing | K18: HashMap + Doubly Linked List: Use a map for O(1) access and a DLL to maintain recency for eviction. | L18: O(1) get/put | M18: O(capacity) | N18: =HYPERLINK("https://leetcode.com/problems/lru-cache/","https://leetcode.com/problems/lru-cache/") -> https://leetcode.com/problems/lru-cache/
A19: 15 | B19: 20 | C19: Valid Parentheses | D19: Easy | E19: Stack | H19: =IFERROR(VLOOKUP(B19,'📊 Problem Tracker'!$B$4:$F$1200,5,FALSE()),"") -> 0 | J19: String, Stack | K19: Stack - Match Brackets: Push opening brackets. For closing brackets, validate against the stack top and ensure stack is empty at the end. | L19: O(n) | M19: O(n) | N19: =HYPERLINK("https://leetcode.com/problems/valid-parentheses/","https://leetcode.com/problems/valid-parentheses/") -> https://leetcode.com/problems/valid-parentheses/
A20: 16 | B20: 21 | C20: Merge Two Sorted Lists | D20: Easy | E20: Linked List | H20: =IFERROR(VLOOKUP(B20,'📊 Problem Tracker'!$B$4:$F$1200,5,FALSE()),"") -> 0 | J20: Linked List | K20: Iterative Merge with Dummy Head: Compare list heads, attach the smaller node, advance that list, and attach the remainder. | L20: O(m + n) | M20: O(1) iterative / O(m+n) recursive | N20: =HYPERLINK("https://leetcode.com/problems/merge-two-sorted-lists/","https://leetcode.com/problems/merge-two-sorted-lists/") -> https://leetcode.com/problems/merge-two-sorted-lists/
A21: 17 | B21: 150 | C21: Evaluate Reverse Polish Notation | D21: Medium | E21: Stack | H21: =IFERROR(VLOOKUP(B21,'📊 Problem Tracker'!$B$4:$F$1200,5,FALSE()),"") -> 0 | J21: Array, Stack, Math | K21: Stack - Evaluate RPN: Push numbers; on an operator, pop two operands, compute, and push the result. | L21: O(n) | M21: O(n) | N21: =HYPERLINK("https://leetcode.com/problems/evaluate-reverse-polish-notation/","https://leetcode.com/problems/evaluate-reverse-polish-notation/") -> https://leetcode.com/problems/evaluate-reverse-polish-notation/
A22: 18 | B22: 23 | C22: Merge k Sorted Lists | D22: Hard | E22: K-way Merge / Heap | H22: =IFERROR(VLOOKUP(B22,'📊 Problem Tracker'!$B$4:$F$1200,5,FALSE()),"") -> 0 | J22: Linked List, Heap | K22: Min-Heap with (val, node): Push each list head into a min-heap, repeatedly pop the minimum node, and push its next node. | L22: O(N log k) | M22: O(k) | N22: =HYPERLINK("https://leetcode.com/problems/merge-k-sorted-lists/","https://leetcode.com/problems/merge-k-sorted-lists/") -> https://leetcode.com/problems/merge-k-sorted-lists/
A23: 19 | B23: 278 | C23: First Bad Version | D23: Easy | E23: Modified Binary Search | H23: =IFERROR(VLOOKUP(B23,'📊 Problem Tracker'!$B$4:$F$1200,5,FALSE()),"") -> 0 | J23: Binary Search | K23: Binary Search: Define a monotonic condition, check the middle value, and discard the half that cannot contain the answer. | L23: O(log n) | M23: O(1) | N23: =HYPERLINK("https://leetcode.com/problems/first-bad-version/","https://leetcode.com/problems/first-bad-version/") -> https://leetcode.com/problems/first-bad-version/
A24: 20 | B24: 409 | C24: Longest Palindrome | D24: Easy | E24: Hashing / Greedy | H24: =IFERROR(VLOOKUP(B24,'📊 Problem Tracker'!$B$4:$F$1200,5,FALSE()),"") -> 0 | J24: String, Hashing, Greedy | K24: HashMap / HashSet: Store seen values or counts for O(1) average lookups and update the answer during one pass. | L24: O(n) | M24: O(n) | N24: =HYPERLINK("https://leetcode.com/problems/longest-palindrome/","https://leetcode.com/problems/longest-palindrome/") -> https://leetcode.com/problems/longest-palindrome/
A25: 21 | B25: 704 | C25: Binary Search | D25: Easy | E25: Binary Search | H25: =IFERROR(VLOOKUP(B25,'📊 Problem Tracker'!$B$4:$F$1200,5,FALSE()),"") -> 0 | J25: Array, Binary Search | K25: Standard Binary Search: Use low/high/mid and discard half based on comparison with target. | L25: O(log n) | M25: O(1) | N25: =HYPERLINK("https://leetcode.com/problems/binary-search/","https://leetcode.com/problems/binary-search/") -> https://leetcode.com/problems/binary-search/
A26: 22 | B26: 155 | C26: Min Stack | D26: Medium | E26: Stack | H26: =IFERROR(VLOOKUP(B26,'📊 Problem Tracker'!$B$4:$F$1200,5,FALSE()),"") -> 0 | J26: Stack, Design | K26: Stack + Auxiliary Min Stack: Maintain a normal stack and a min stack so getMin reads the current minimum in O(1). | L26: O(1) per op | M26: O(n) | N26: =HYPERLINK("https://leetcode.com/problems/min-stack/","https://leetcode.com/problems/min-stack/") -> https://leetcode.com/problems/min-stack/
A27: 23 | B27: 981 | C27: Time Based Key-Value Store | D27: Medium | E27: Binary Search | F27: Hashing | H27: =IFERROR(VLOOKUP(B27,'📊 Problem Tracker'!$B$4:$F$1200,5,FALSE()),"") -> 0 | J27: Design, Hashing, Binary Search | K27: Binary Search: Define a monotonic condition, check the middle value, and discard the half that cannot contain the answer. | L27: O(log n) get, O(1) set | M27: O(n) | N27: =HYPERLINK("https://leetcode.com/problems/time-based-key-value-store/","https://leetcode.com/problems/time-based-key-value-store/") -> https://leetcode.com/problems/time-based-key-value-store/
A28: 24 | B28: 542 | C28: 01 Matrix | D28: Medium | E28: BFS / Multi-source | H28: =IFERROR(VLOOKUP(B28,'📊 Problem Tracker'!$B$4:$F$1200,5,FALSE()),"") -> 0 | J28: Array, Matrix, BFS | K28: Graph Traversal: Build adjacency/state representation, use BFS for shortest path or DFS for reachability/components, and track visited states. | L28: O(m·n) | M28: O(m·n) | N28: =HYPERLINK("https://leetcode.com/problems/01-matrix/","https://leetcode.com/problems/01-matrix/") -> https://leetcode.com/problems/01-matrix/
A29: 25 | B29: 543 | C29: Diameter of Binary Tree | D29: Easy | E29: Tree DFS | H29: =IFERROR(VLOOKUP(B29,'📊 Problem Tracker'!$B$4:$F$1200,5,FALSE()),"") -> 0 | J29: Tree, DFS | K29: Tree DFS/BFS: Traverse the tree recursively or level by level, returning local information needed to build the global answer. | L29: O(n) | M29: O(h) | N29: =HYPERLINK("https://leetcode.com/problems/diameter-of-binary-tree/","https://leetcode.com/problems/diameter-of-binary-tree/") -> https://leetcode.com/problems/diameter-of-binary-tree/
A30: 26 | B30: 416 | C30: Partition Equal Subset Sum | D30: Medium | E30: DP / 0-1 Knapsack | H30: =IFERROR(VLOOKUP(B30,'📊 Problem Tracker'!$B$4:$F$1200,5,FALSE()),"") -> 0 | J30: Array, DP | K30: Dynamic Programming: Define the state, initialize base cases, and transition from smaller subproblems to compute the answer. | L30: O(n·sum) | M30: O(sum) | N30: =HYPERLINK("https://leetcode.com/problems/partition-equal-subset-sum/","https://leetcode.com/problems/partition-equal-subset-sum/") -> https://leetcode.com/problems/partition-equal-subset-sum/
A31: 27 | B31: 33 | C31: Search in Rotated Sorted Array | D31: Medium | E31: Modified Binary Search | H31: =IFERROR(VLOOKUP(B31,'📊 Problem Tracker'!$B$4:$F$1200,5,FALSE()),"") -> 0 | J31: Array, Binary Search | K31: Binary Search - Identify Sorted Half: At each mid, determine which half is sorted and narrow search to the half that can contain target. | L31: O(log n) | M31: O(1) | N31: =HYPERLINK("https://leetcode.com/problems/search-in-rotated-sorted-array/","https://leetcode.com/problems/search-in-rotated-sorted-array/") -> https://leetcode.com/problems/search-in-rotated-sorted-array/
A32: 28 | B32: 39 | C32: Combination Sum | D32: Medium | E32: Backtracking | H32: =IFERROR(VLOOKUP(B32,'📊 Problem Tracker'!$B$4:$F$1200,5,FALSE()),"") -> 0 | J32: Array, Backtracking | K32: Backtracking - Allow Reuse, Prune by Sum: Sort candidates, choose candidates while remaining target allows it, and recurse with same index for reuse. | L32: O(N^(T/M)) | M32: O(T/M) | N32: =HYPERLINK("https://leetcode.com/problems/combination-sum/","https://leetcode.com/problems/combination-sum/") -> https://leetcode.com/problems/combination-sum/
A33: 29 | B33: 295 | C33: Find Median from Data Stream | D33: Hard | E33: Two Heaps | H33: =IFERROR(VLOOKUP(B33,'📊 Problem Tracker'!$B$4:$F$1200,5,FALSE()),"") -> 0 | J33: Heap, Design, Two Pointers | K33: Two Heaps - Lower and Upper Half: Maintain max-heap for lower half and min-heap for upper half, balanced by size. | L33: O(log n) add, O(1) median | M33: O(n) | N33: =HYPERLINK("https://leetcode.com/problems/find-median-from-data-stream/","https://leetcode.com/problems/find-median-from-data-stream/") -> https://leetcode.com/problems/find-median-from-data-stream/
A34: 30 | B34: 169 | C34: Majority Element | D34: Easy | E34: Array / Boyer-Moore | H34: =IFERROR(VLOOKUP(B34,'📊 Problem Tracker'!$B$4:$F$1200,5,FALSE()),"") -> 0 | J34: Array | K34: Boyer-Moore Voting Algorithm: Maintain a candidate and count; majority survives cancellations, then candidate is answer. | L34: O(n) | M34: O(1) | N34: =HYPERLINK("https://leetcode.com/problems/majority-element/","https://leetcode.com/problems/majority-element/") -> https://leetcode.com/problems/majority-element/
A35: 31 | B35: 42 | C35: Trapping Rain Water | D35: Hard | E35: Two Pointers | F35: Monotonic Stack | H35: =IFERROR(VLOOKUP(B35,'📊 Problem Tracker'!$B$4:$F$1200,5,FALSE()),"") -> 0 | J35: Array, Two Pointers, Monotonic Stack | K35: Two Pointers - Track Max from Each Side: Move the side with smaller max boundary and accumulate trapped water from that boundary. | L35: O(n) | M35: O(1) | N35: =HYPERLINK("https://leetcode.com/problems/trapping-rain-water/","https://leetcode.com/problems/trapping-rain-water/") -> https://leetcode.com/problems/trapping-rain-water/
A36: 32 | B36: 297 | C36: Serialize and Deserialize Binary Tree | D36: Hard | E36: Tree BFS/DFS | F36: Serialization | H36: =IFERROR(VLOOKUP(B36,'📊 Problem Tracker'!$B$4:$F$1200,5,FALSE()),"") -> 0 | J36: Tree, BFS, DFS, Design | K36: Tree DFS/BFS: Traverse the tree recursively or level by level, returning local information needed to build the global answer. | L36: O(n) | M36: O(n) | N36: =HYPERLINK("https://leetcode.com/problems/serialize-and-deserialize-binary-tree/","https://leetcode.com/problems/serialize-and-deserialize-binary-tree/") -> https://leetcode.com/problems/serialize-and-deserialize-binary-tree/
A37: 33 | B37: 46 | C37: Permutations | D37: Medium | E37: Backtracking | H37: =IFERROR(VLOOKUP(B37,'📊 Problem Tracker'!$B$4:$F$1200,5,FALSE()),"") -> 0 | J37: Array, Backtracking | K37: Backtracking - Swap to Generate: Swap the current index with each candidate index, recurse, and swap back. | L37: O(n · n!) | M37: O(n) | N37: =HYPERLINK("https://leetcode.com/problems/permutations/","https://leetcode.com/problems/permutations/") -> https://leetcode.com/problems/permutations/
A38: 34 | B38: 53 | C38: Maximum Subarray | D38: Medium | E38: Kadane / DP | H38: =IFERROR(VLOOKUP(B38,'📊 Problem Tracker'!$B$4:$F$1200,5,FALSE()),"") -> 0 | J38: Array, DP | K38: Kadane's Algorithm: Track best subarray ending at current index and global best; restart when current value is better. | L38: O(n) | M38: O(1) | N38: =HYPERLINK("https://leetcode.com/problems/maximum-subarray/","https://leetcode.com/problems/maximum-subarray/") -> https://leetcode.com/problems/maximum-subarray/
A39: 35 | B39: 54 | C39: Spiral Matrix | D39: Medium | E39: Matrix / Simulation | H39: =IFERROR(VLOOKUP(B39,'📊 Problem Tracker'!$B$4:$F$1200,5,FALSE()),"") -> 0 | J39: Array, Matrix | K39: Boundary Shrinking: Maintain top, bottom, left, and right boundaries and traverse right, down, left, up while shrinking. | L39: O(m·n) | M39: O(1) | N39: =HYPERLINK("https://leetcode.com/problems/spiral-matrix/","https://leetcode.com/problems/spiral-matrix/") -> https://leetcode.com/problems/spiral-matrix/
A40: 36 | B40: 310 | C40: Minimum Height Trees | D40: Medium | E40: Topological Sort / BFS | H40: =IFERROR(VLOOKUP(B40,'📊 Problem Tracker'!$B$4:$F$1200,5,FALSE()),"") -> 0 | J40: Graph, BFS, Topological Sort | K40: Tree DFS/BFS: Traverse the tree recursively or level by level, returning local information needed to build the global answer. | L40: O(V + E) | M40: O(V) | N40: =HYPERLINK("https://leetcode.com/problems/minimum-height-trees/","https://leetcode.com/problems/minimum-height-trees/") -> https://leetcode.com/problems/minimum-height-trees/
A41: 37 | B41: 56 | C41: Merge Intervals | D41: Medium | E41: Merge Intervals | F41: Sorting | H41: =IFERROR(VLOOKUP(B41,'📊 Problem Tracker'!$B$4:$F$1200,5,FALSE()),"") -> 0 | J41: Array, Intervals | K41: Sort by Start + Merge Overlapping: Sort intervals by start and merge into the previous interval when they overlap. | L41: O(n log n) | M41: O(n) | N41: =HYPERLINK("https://leetcode.com/problems/merge-intervals/","https://leetcode.com/problems/merge-intervals/") -> https://leetcode.com/problems/merge-intervals/
A42: 38 | B42: 57 | C42: Insert Interval | D42: Medium | E42: Merge Intervals | H42: =IFERROR(VLOOKUP(B42,'📊 Problem Tracker'!$B$4:$F$1200,5,FALSE()),"") -> 0 | J42: Array, Intervals | K42: Three Phases: Before, Overlap, After: Add intervals before new interval, merge all overlaps with it, then append the rest. | L42: O(n) | M42: O(n) | N42: =HYPERLINK("https://leetcode.com/problems/insert-interval/","https://leetcode.com/problems/insert-interval/") -> https://leetcode.com/problems/insert-interval/
A43: 39 | B43: 438 | C43: Find All Anagrams in a String | D43: Medium | E43: Sliding Window | F43: Hashing | H43: =IFERROR(VLOOKUP(B43,'📊 Problem Tracker'!$B$4:$F$1200,5,FALSE()),"") -> 0 | J43: String, Sliding Window, Hashing | K43: Sliding Window with Char Counts: Use a fixed-size window matching p length and compare character counts. | L43: O(n) | M43: O(1) | N43: =HYPERLINK("https://leetcode.com/problems/find-all-anagrams-in-a-string/","https://leetcode.com/problems/find-all-anagrams-in-a-string/") -> https://leetcode.com/problems/find-all-anagrams-in-a-string/
A44: 40 | B44: 62 | C44: Unique Paths | D44: Medium | E44: DP / 2D | H44: =IFERROR(VLOOKUP(B44,'📊 Problem Tracker'!$B$4:$F$1200,5,FALSE()),"") -> 0 | J44: DP, Math | K44: DP - Unique Paths Grid: Use dp[i][j] = top + left, with first row and column initialized to 1. | L44: O(m·n) | M44: O(n) | N44: =HYPERLINK("https://leetcode.com/problems/unique-paths/","https://leetcode.com/problems/unique-paths/") -> https://leetcode.com/problems/unique-paths/
A45: 41 | B45: 322 | C45: Coin Change | D45: Medium | E45: DP / BFS | H45: =IFERROR(VLOOKUP(B45,'📊 Problem Tracker'!$B$4:$F$1200,5,FALSE()),"") -> 0 | J45: Array, DP, BFS | K45: DP - Coin Change: For every amount, try each coin and take the minimum coins from dp[amount-coin]+1. | L45: O(amount · n) | M45: O(amount) | N45: =HYPERLINK("https://leetcode.com/problems/coin-change/","https://leetcode.com/problems/coin-change/") -> https://leetcode.com/problems/coin-change/
A46: 42 | B46: 67 | C46: Add Binary | D46: Easy | E46: Bit Manipulation | H46: =IFERROR(VLOOKUP(B46,'📊 Problem Tracker'!$B$4:$F$1200,5,FALSE()),"") -> 0 | J46: String, Bit Manipulation, Math | K46: Bit Addition with Carry: Add bits from right to left with carry and build the result. | L46: O(max(m, n)) | M46: O(max(m, n)) | N46: =HYPERLINK("https://leetcode.com/problems/add-binary/","https://leetcode.com/problems/add-binary/") -> https://leetcode.com/problems/add-binary/
A47: 43 | B47: 70 | C47: Climbing Stairs | D47: Easy | E47: DP / Fibonacci | H47: =IFERROR(VLOOKUP(B47,'📊 Problem Tracker'!$B$4:$F$1200,5,FALSE()),"") -> 0 | J47: Array, DP, Math | K47: DP Fibonacci: Use the recurrence ways[i] = ways[i-1] + ways[i-2] with two rolling variables. | L47: O(n) | M47: O(1) | N47: =HYPERLINK("https://leetcode.com/problems/climbing-stairs/","https://leetcode.com/problems/climbing-stairs/") -> https://leetcode.com/problems/climbing-stairs/
A48: 44 | B48: 199 | C48: Binary Tree Right Side View | D48: Medium | E48: Tree BFS | H48: =IFERROR(VLOOKUP(B48,'📊 Problem Tracker'!$B$4:$F$1200,5,FALSE()),"") -> 0 | J48: Tree, BFS, DFS | K48: Tree DFS/BFS: Traverse the tree recursively or level by level, returning local information needed to build the global answer. | L48: O(n) | M48: O(n) | N48: =HYPERLINK("https://leetcode.com/problems/binary-tree-right-side-view/","https://leetcode.com/problems/binary-tree-right-side-view/") -> https://leetcode.com/problems/binary-tree-right-side-view/
A49: 45 | B49: 200 | C49: Number of Islands | D49: Medium | E49: Graph DFS/BFS | F49: Union-Find | H49: =IFERROR(VLOOKUP(B49,'📊 Problem Tracker'!$B$4:$F$1200,5,FALSE()),"") -> 0 | J49: Array, Matrix, DFS, BFS, Union-Find | K49: DFS/BFS Flood Fill: For each unvisited land cell, flood-fill the whole island and increment count. | L49: O(m·n) | M49: O(m·n) | N49: =HYPERLINK("https://leetcode.com/problems/number-of-islands/","https://leetcode.com/problems/number-of-islands/") -> https://leetcode.com/problems/number-of-islands/
